// 
// Decompiled by Procyon v0.6.0
// 

package X;

import android.os.IBinder;
import com.bytedance.covode.number.Covode;

public final class 04s
{
    public final 011 LIZ;
    
    static {
        Covode.recordClassIndex(572);
    }
    
    public 04s(final 011 liz) {
        // 
        // This method could not be decompiled.
        // 
        // Original Bytecode:
        // 
        //     1: invokespecial   java/lang/Object.<init>:()V
        //     4: aload_0        
        //     5: aload_1        
        //     6: putfield        X/04s.LIZ:LX/011;
        //     9: new             LX/13h;
        //    12: dup            
        //    13: aload_0        
        //    14: invokespecial   X/13h.<init>:(LX/04s;)V
        //    17: pop            
        //    18: return         
        // 
        // The error that occurred was:
        // 
        // java.lang.NullPointerException
        //     at com.strobel.decompiler.languages.java.ast.AstBuilder.convertType(AstBuilder.java:419)
        //     at com.strobel.decompiler.languages.java.ast.AstBuilder.convertType(AstBuilder.java:207)
        //     at com.strobel.decompiler.languages.java.ast.AstBuilder.convertType(AstBuilder.java:203)
        //     at com.strobel.decompiler.languages.java.ast.AstMethodBodyBuilder.transformByteCode(AstMethodBodyBuilder.java:541)
        //     at com.strobel.decompiler.languages.java.ast.AstMethodBodyBuilder.transformExpression(AstMethodBodyBuilder.java:534)
        //     at com.strobel.decompiler.languages.java.ast.AstMethodBodyBuilder.transformByteCode(AstMethodBodyBuilder.java:548)
        //     at com.strobel.decompiler.languages.java.ast.AstMethodBodyBuilder.transformExpression(AstMethodBodyBuilder.java:534)
        //     at com.strobel.decompiler.languages.java.ast.AstMethodBodyBuilder.transformNode(AstMethodBodyBuilder.java:377)
        //     at com.strobel.decompiler.languages.java.ast.AstMethodBodyBuilder.transformBlock(AstMethodBodyBuilder.java:318)
        //     at com.strobel.decompiler.languages.java.ast.AstMethodBodyBuilder.createMethodBody(AstMethodBodyBuilder.java:213)
        //     at com.strobel.decompiler.languages.java.ast.AstMethodBodyBuilder.createMethodBody(AstMethodBodyBuilder.java:93)
        //     at com.strobel.decompiler.languages.java.ast.AstBuilder.createMethodBody(AstBuilder.java:868)
        //     at com.strobel.decompiler.languages.java.ast.AstBuilder.createConstructor(AstBuilder.java:799)
        //     at com.strobel.decompiler.languages.java.ast.AstBuilder.addTypeMembers(AstBuilder.java:635)
        //     at com.strobel.decompiler.languages.java.ast.AstBuilder.createTypeCore(AstBuilder.java:605)
        //     at com.strobel.decompiler.languages.java.ast.AstBuilder.createTypeNoCache(AstBuilder.java:195)
        //     at com.strobel.decompiler.languages.java.ast.AstBuilder.createType(AstBuilder.java:162)
        //     at com.strobel.decompiler.languages.java.ast.AstBuilder.addType(AstBuilder.java:137)
        //     at com.strobel.decompiler.languages.java.JavaLanguage.buildAst(JavaLanguage.java:71)
        //     at com.strobel.decompiler.languages.java.JavaLanguage.decompileType(JavaLanguage.java:59)
        //     at com.strobel.decompiler.DecompilerDriver.decompileType(DecompilerDriver.java:333)
        //     at com.strobel.decompiler.DecompilerDriver.decompileJar(DecompilerDriver.java:254)
        //     at com.strobel.decompiler.DecompilerDriver.main(DecompilerDriver.java:129)
        // 
        throw new IllegalStateException("An error occurred while decompiling this method.");
    }
    
    public final IBinder LIZ() {
        return this.LIZ.asBinder();
    }
    
    @Override
    public final boolean equals(final Object o) {
        return o instanceof 04s && ((04s)o).LIZ().equals(this.LIZ.asBinder());
    }
    
    @Override
    public final int hashCode() {
        return this.LIZ().hashCode();
    }
}
