// 
// Decompiled by Procyon v0.6.0
// 

package X;

import com.bytedance.covode.number.Covode;

public final class 0Oo
{
    static {
        Covode.recordClassIndex(4026);
    }
    
    public static final void LIZ(final 0On 0On, final SRS<? super 0Ox, 2P9> srs) {
        public final class 1Co implements 0Oy
        {
            public final /* synthetic */ SRS LIZ;
            
            static {
                Covode.recordClassIndex(4027);
            }
            
            public 1Co(final SRS liz) {
                this.LIZ = liz;
            }
            
            @Override
            public final void onEvent(final 0Ox 0Ox) {
                CTM.LIZ((Object)0Ox);
                this.LIZ.invoke((Object)0Ox);
            }
        }
        // 
        // This method could not be decompiled.
        // 
        // Original Bytecode:
        // 
        //     1: aload_1        
        //     2: invokestatic    X/CTM.LIZ:(Ljava/lang/Object;Ljava/lang/Object;)V
        //     5: aload_0        
        //     6: new             LX/1Co;
        //     9: dup            
        //    10: aload_1        
        //    11: invokespecial   X/1Co.<init>:(LX/SRS;)V
        //    14: invokevirtual   X/0On.LIZ:(LX/0Oy;)V
        //    17: return         
        //    Signature:
        //  (LX/0On;LX/SRS<-LX/0Ox;LX/2P9;>;)V
        // 
        // The error that occurred was:
        // 
        // java.lang.NullPointerException
        //     at com.strobel.decompiler.languages.java.ast.AstBuilder.convertType(AstBuilder.java:419)
        //     at com.strobel.decompiler.languages.java.ast.AstBuilder.convertType(AstBuilder.java:207)
        //     at com.strobel.decompiler.languages.java.ast.AstMethodBodyBuilder.transformCall(AstMethodBodyBuilder.java:1106)
        //     at com.strobel.decompiler.languages.java.ast.AstMethodBodyBuilder.transformByteCode(AstMethodBodyBuilder.java:993)
        //     at com.strobel.decompiler.languages.java.ast.AstMethodBodyBuilder.transformExpression(AstMethodBodyBuilder.java:534)
        //     at com.strobel.decompiler.languages.java.ast.AstMethodBodyBuilder.transformByteCode(AstMethodBodyBuilder.java:548)
        //     at com.strobel.decompiler.languages.java.ast.AstMethodBodyBuilder.transformExpression(AstMethodBodyBuilder.java:534)
        //     at com.strobel.decompiler.languages.java.ast.AstMethodBodyBuilder.transformNode(AstMethodBodyBuilder.java:377)
        //     at com.strobel.decompiler.languages.java.ast.AstMethodBodyBuilder.transformBlock(AstMethodBodyBuilder.java:318)
        //     at com.strobel.decompiler.languages.java.ast.AstMethodBodyBuilder.createMethodBody(AstMethodBodyBuilder.java:213)
        //     at com.strobel.decompiler.languages.java.ast.AstMethodBodyBuilder.createMethodBody(AstMethodBodyBuilder.java:93)
        //     at com.strobel.decompiler.languages.java.ast.AstBuilder.createMethodBody(AstBuilder.java:868)
        //     at com.strobel.decompiler.languages.java.ast.AstBuilder.createMethod(AstBuilder.java:761)
        //     at com.strobel.decompiler.languages.java.ast.AstBuilder.addTypeMembers(AstBuilder.java:638)
        //     at com.strobel.decompiler.languages.java.ast.AstBuilder.createTypeCore(AstBuilder.java:605)
        //     at com.strobel.decompiler.languages.java.ast.AstBuilder.createTypeNoCache(AstBuilder.java:195)
        //     at com.strobel.decompiler.languages.java.ast.AstBuilder.createType(AstBuilder.java:162)
        //     at com.strobel.decompiler.languages.java.ast.AstBuilder.addType(AstBuilder.java:137)
        //     at com.strobel.decompiler.languages.java.JavaLanguage.buildAst(JavaLanguage.java:71)
        //     at com.strobel.decompiler.languages.java.JavaLanguage.decompileType(JavaLanguage.java:59)
        //     at com.strobel.decompiler.DecompilerDriver.decompileType(DecompilerDriver.java:333)
        //     at com.strobel.decompiler.DecompilerDriver.decompileJar(DecompilerDriver.java:254)
        //     at com.strobel.decompiler.DecompilerDriver.main(DecompilerDriver.java:129)
        // 
        throw new IllegalStateException("An error occurred while decompiling this method.");
    }
    
    public static final void LIZIZ(final 0On 0On, final SRS<? super 0Or, 2P9> srs) {
        public final class 1oI extends F5g implements SRS<0Or, 2P9>
        {
            public final /* synthetic */ SRS LIZ;
            
            static {
                Covode.recordClassIndex(4028);
            }
            
            public 1oI(final SRS liz) {
                this.LIZ = liz;
                super(1);
            }
        }
        // 
        // This method could not be decompiled.
        // 
        // Original Bytecode:
        // 
        //     1: aload_1        
        //     2: invokestatic    X/CTM.LIZ:(Ljava/lang/Object;Ljava/lang/Object;)V
        //     5: aload_0        
        //     6: iconst_0       
        //     7: new             LX/1oI;
        //    10: dup            
        //    11: aload_1        
        //    12: invokespecial   X/1oI.<init>:(LX/SRS;)V
        //    15: invokevirtual   X/0On.LIZ:(ZLX/SRS;)V
        //    18: return         
        //    Signature:
        //  (LX/0On;LX/SRS<-LX/0Or;LX/2P9;>;)V
        // 
        // The error that occurred was:
        // 
        // java.lang.NullPointerException
        //     at com.strobel.decompiler.languages.java.ast.AstBuilder.convertType(AstBuilder.java:419)
        //     at com.strobel.decompiler.languages.java.ast.AstBuilder.convertType(AstBuilder.java:207)
        //     at com.strobel.decompiler.languages.java.ast.AstMethodBodyBuilder.transformCall(AstMethodBodyBuilder.java:1106)
        //     at com.strobel.decompiler.languages.java.ast.AstMethodBodyBuilder.transformByteCode(AstMethodBodyBuilder.java:993)
        //     at com.strobel.decompiler.languages.java.ast.AstMethodBodyBuilder.transformExpression(AstMethodBodyBuilder.java:534)
        //     at com.strobel.decompiler.languages.java.ast.AstMethodBodyBuilder.transformByteCode(AstMethodBodyBuilder.java:548)
        //     at com.strobel.decompiler.languages.java.ast.AstMethodBodyBuilder.transformExpression(AstMethodBodyBuilder.java:534)
        //     at com.strobel.decompiler.languages.java.ast.AstMethodBodyBuilder.transformNode(AstMethodBodyBuilder.java:377)
        //     at com.strobel.decompiler.languages.java.ast.AstMethodBodyBuilder.transformBlock(AstMethodBodyBuilder.java:318)
        //     at com.strobel.decompiler.languages.java.ast.AstMethodBodyBuilder.createMethodBody(AstMethodBodyBuilder.java:213)
        //     at com.strobel.decompiler.languages.java.ast.AstMethodBodyBuilder.createMethodBody(AstMethodBodyBuilder.java:93)
        //     at com.strobel.decompiler.languages.java.ast.AstBuilder.createMethodBody(AstBuilder.java:868)
        //     at com.strobel.decompiler.languages.java.ast.AstBuilder.createMethod(AstBuilder.java:761)
        //     at com.strobel.decompiler.languages.java.ast.AstBuilder.addTypeMembers(AstBuilder.java:638)
        //     at com.strobel.decompiler.languages.java.ast.AstBuilder.createTypeCore(AstBuilder.java:605)
        //     at com.strobel.decompiler.languages.java.ast.AstBuilder.createTypeNoCache(AstBuilder.java:195)
        //     at com.strobel.decompiler.languages.java.ast.AstBuilder.createType(AstBuilder.java:162)
        //     at com.strobel.decompiler.languages.java.ast.AstBuilder.addType(AstBuilder.java:137)
        //     at com.strobel.decompiler.languages.java.JavaLanguage.buildAst(JavaLanguage.java:71)
        //     at com.strobel.decompiler.languages.java.JavaLanguage.decompileType(JavaLanguage.java:59)
        //     at com.strobel.decompiler.DecompilerDriver.decompileType(DecompilerDriver.java:333)
        //     at com.strobel.decompiler.DecompilerDriver.decompileJar(DecompilerDriver.java:254)
        //     at com.strobel.decompiler.DecompilerDriver.main(DecompilerDriver.java:129)
        // 
        throw new IllegalStateException("An error occurred while decompiling this method.");
    }
}
