// 
// Decompiled by Procyon v0.6.0
// 

package X;

import java.util.LinkedHashMap;
import com.bytedance.covode.number.Covode;
import java.util.Map;

public final class 0PW
{
    public static final Map<String, 0PZ> LIZ;
    public static final 0PW LIZIZ;
    public static final 0Q6 LIZJ;
    
    static {
        Covode.recordClassIndex(4176);
        LIZIZ = new 0PW();
        LIZJ = new 0Q6();
        LIZ = new LinkedHashMap<String, 0PZ>();
    }
    
    public final 0PZ LIZ(final String s) {
        public final class 1pC extends F5g implements QgG<0PZ>
        {
            public final /* synthetic */ String LIZ;
            
            static {
                Covode.recordClassIndex(4179);
            }
            
            public 1pC(final String liz) {
                this.LIZ = liz;
                super(0);
            }
        }
        // 
        // This method could not be decompiled.
        // 
        // Original Bytecode:
        // 
        //     1: invokestatic    X/CTM.LIZ:(Ljava/lang/Object;)V
        //     4: getstatic       X/0PW.LIZJ:LX/0Q6;
        //     7: new             LX/1pC;
        //    10: dup            
        //    11: aload_1        
        //    12: invokespecial   X/1pC.<init>:(Ljava/lang/String;)V
        //    15: invokevirtual   X/0Q6.LIZ:(LX/QgG;)Ljava/lang/Object;
        //    18: checkcast       LX/0PZ;
        //    21: areturn        
        // 
        // The error that occurred was:
        // 
        // java.lang.NullPointerException
        //     at com.strobel.decompiler.languages.java.ast.AstBuilder.convertType(AstBuilder.java:419)
        //     at com.strobel.decompiler.languages.java.ast.AstBuilder.convertType(AstBuilder.java:207)
        //     at com.strobel.decompiler.languages.java.ast.AstMethodBodyBuilder.transformCall(AstMethodBodyBuilder.java:1106)
        //     at com.strobel.decompiler.languages.java.ast.AstMethodBodyBuilder.transformByteCode(AstMethodBodyBuilder.java:993)
        //     at com.strobel.decompiler.languages.java.ast.AstMethodBodyBuilder.transformExpression(AstMethodBodyBuilder.java:534)
        //     at com.strobel.decompiler.languages.java.ast.AstMethodBodyBuilder.transformByteCode(AstMethodBodyBuilder.java:548)
        //     at com.strobel.decompiler.languages.java.ast.AstMethodBodyBuilder.transformExpression(AstMethodBodyBuilder.java:534)
        //     at com.strobel.decompiler.languages.java.ast.AstMethodBodyBuilder.transformByteCode(AstMethodBodyBuilder.java:548)
        //     at com.strobel.decompiler.languages.java.ast.AstMethodBodyBuilder.transformExpression(AstMethodBodyBuilder.java:534)
        //     at com.strobel.decompiler.languages.java.ast.AstMethodBodyBuilder.transformByteCode(AstMethodBodyBuilder.java:548)
        //     at com.strobel.decompiler.languages.java.ast.AstMethodBodyBuilder.transformExpression(AstMethodBodyBuilder.java:534)
        //     at com.strobel.decompiler.languages.java.ast.AstMethodBodyBuilder.transformNode(AstMethodBodyBuilder.java:377)
        //     at com.strobel.decompiler.languages.java.ast.AstMethodBodyBuilder.transformBlock(AstMethodBodyBuilder.java:318)
        //     at com.strobel.decompiler.languages.java.ast.AstMethodBodyBuilder.createMethodBody(AstMethodBodyBuilder.java:213)
        //     at com.strobel.decompiler.languages.java.ast.AstMethodBodyBuilder.createMethodBody(AstMethodBodyBuilder.java:93)
        //     at com.strobel.decompiler.languages.java.ast.AstBuilder.createMethodBody(AstBuilder.java:868)
        //     at com.strobel.decompiler.languages.java.ast.AstBuilder.createMethod(AstBuilder.java:761)
        //     at com.strobel.decompiler.languages.java.ast.AstBuilder.addTypeMembers(AstBuilder.java:638)
        //     at com.strobel.decompiler.languages.java.ast.AstBuilder.createTypeCore(AstBuilder.java:605)
        //     at com.strobel.decompiler.languages.java.ast.AstBuilder.createTypeNoCache(AstBuilder.java:195)
        //     at com.strobel.decompiler.languages.java.ast.AstBuilder.createType(AstBuilder.java:162)
        //     at com.strobel.decompiler.languages.java.ast.AstBuilder.addType(AstBuilder.java:137)
        //     at com.strobel.decompiler.languages.java.JavaLanguage.buildAst(JavaLanguage.java:71)
        //     at com.strobel.decompiler.languages.java.JavaLanguage.decompileType(JavaLanguage.java:59)
        //     at com.strobel.decompiler.DecompilerDriver.decompileType(DecompilerDriver.java:333)
        //     at com.strobel.decompiler.DecompilerDriver.decompileJar(DecompilerDriver.java:254)
        //     at com.strobel.decompiler.DecompilerDriver.main(DecompilerDriver.java:129)
        // 
        throw new IllegalStateException("An error occurred while decompiling this method.");
    }
    
    public final void LIZ(final 0PZ 0pz) {
        public final class 1pA extends F5g implements QgG<2P9>
        {
            public final /* synthetic */ 0PZ LIZ;
            
            static {
                Covode.recordClassIndex(4177);
            }
            
            public 1pA(final 0PZ liz) {
                this.LIZ = liz;
                super(0);
            }
        }
        // 
        // This method could not be decompiled.
        // 
        // Original Bytecode:
        // 
        //     1: invokestatic    X/CTM.LIZ:(Ljava/lang/Object;)V
        //     4: getstatic       X/0PW.LIZJ:LX/0Q6;
        //     7: new             LX/1pA;
        //    10: dup            
        //    11: aload_1        
        //    12: invokespecial   X/1pA.<init>:(LX/0PZ;)V
        //    15: invokevirtual   X/0Q6.LIZIZ:(LX/QgG;)V
        //    18: return         
        // 
        // The error that occurred was:
        // 
        // java.lang.NullPointerException
        //     at com.strobel.decompiler.languages.java.ast.AstBuilder.convertType(AstBuilder.java:419)
        //     at com.strobel.decompiler.languages.java.ast.AstBuilder.convertType(AstBuilder.java:207)
        //     at com.strobel.decompiler.languages.java.ast.AstMethodBodyBuilder.transformCall(AstMethodBodyBuilder.java:1106)
        //     at com.strobel.decompiler.languages.java.ast.AstMethodBodyBuilder.transformByteCode(AstMethodBodyBuilder.java:993)
        //     at com.strobel.decompiler.languages.java.ast.AstMethodBodyBuilder.transformExpression(AstMethodBodyBuilder.java:534)
        //     at com.strobel.decompiler.languages.java.ast.AstMethodBodyBuilder.transformByteCode(AstMethodBodyBuilder.java:548)
        //     at com.strobel.decompiler.languages.java.ast.AstMethodBodyBuilder.transformExpression(AstMethodBodyBuilder.java:534)
        //     at com.strobel.decompiler.languages.java.ast.AstMethodBodyBuilder.transformNode(AstMethodBodyBuilder.java:377)
        //     at com.strobel.decompiler.languages.java.ast.AstMethodBodyBuilder.transformBlock(AstMethodBodyBuilder.java:318)
        //     at com.strobel.decompiler.languages.java.ast.AstMethodBodyBuilder.createMethodBody(AstMethodBodyBuilder.java:213)
        //     at com.strobel.decompiler.languages.java.ast.AstMethodBodyBuilder.createMethodBody(AstMethodBodyBuilder.java:93)
        //     at com.strobel.decompiler.languages.java.ast.AstBuilder.createMethodBody(AstBuilder.java:868)
        //     at com.strobel.decompiler.languages.java.ast.AstBuilder.createMethod(AstBuilder.java:761)
        //     at com.strobel.decompiler.languages.java.ast.AstBuilder.addTypeMembers(AstBuilder.java:638)
        //     at com.strobel.decompiler.languages.java.ast.AstBuilder.createTypeCore(AstBuilder.java:605)
        //     at com.strobel.decompiler.languages.java.ast.AstBuilder.createTypeNoCache(AstBuilder.java:195)
        //     at com.strobel.decompiler.languages.java.ast.AstBuilder.createType(AstBuilder.java:162)
        //     at com.strobel.decompiler.languages.java.ast.AstBuilder.addType(AstBuilder.java:137)
        //     at com.strobel.decompiler.languages.java.JavaLanguage.buildAst(JavaLanguage.java:71)
        //     at com.strobel.decompiler.languages.java.JavaLanguage.decompileType(JavaLanguage.java:59)
        //     at com.strobel.decompiler.DecompilerDriver.decompileType(DecompilerDriver.java:333)
        //     at com.strobel.decompiler.DecompilerDriver.decompileJar(DecompilerDriver.java:254)
        //     at com.strobel.decompiler.DecompilerDriver.main(DecompilerDriver.java:129)
        // 
        throw new IllegalStateException("An error occurred while decompiling this method.");
    }
    
    public final void LIZIZ(final 0PZ 0pz) {
        public final class 1pB extends F5g implements QgG<2P9>
        {
            public final /* synthetic */ 0PZ LIZ;
            
            static {
                Covode.recordClassIndex(4178);
            }
            
            public 1pB(final 0PZ liz) {
                this.LIZ = liz;
                super(0);
            }
        }
        // 
        // This method could not be decompiled.
        // 
        // Original Bytecode:
        // 
        //     1: invokestatic    X/CTM.LIZ:(Ljava/lang/Object;)V
        //     4: getstatic       X/0PW.LIZJ:LX/0Q6;
        //     7: new             LX/1pB;
        //    10: dup            
        //    11: aload_1        
        //    12: invokespecial   X/1pB.<init>:(LX/0PZ;)V
        //    15: invokevirtual   X/0Q6.LIZIZ:(LX/QgG;)V
        //    18: return         
        // 
        // The error that occurred was:
        // 
        // java.lang.NullPointerException
        //     at com.strobel.decompiler.languages.java.ast.AstBuilder.convertType(AstBuilder.java:419)
        //     at com.strobel.decompiler.languages.java.ast.AstBuilder.convertType(AstBuilder.java:207)
        //     at com.strobel.decompiler.languages.java.ast.AstMethodBodyBuilder.transformCall(AstMethodBodyBuilder.java:1106)
        //     at com.strobel.decompiler.languages.java.ast.AstMethodBodyBuilder.transformByteCode(AstMethodBodyBuilder.java:993)
        //     at com.strobel.decompiler.languages.java.ast.AstMethodBodyBuilder.transformExpression(AstMethodBodyBuilder.java:534)
        //     at com.strobel.decompiler.languages.java.ast.AstMethodBodyBuilder.transformByteCode(AstMethodBodyBuilder.java:548)
        //     at com.strobel.decompiler.languages.java.ast.AstMethodBodyBuilder.transformExpression(AstMethodBodyBuilder.java:534)
        //     at com.strobel.decompiler.languages.java.ast.AstMethodBodyBuilder.transformNode(AstMethodBodyBuilder.java:377)
        //     at com.strobel.decompiler.languages.java.ast.AstMethodBodyBuilder.transformBlock(AstMethodBodyBuilder.java:318)
        //     at com.strobel.decompiler.languages.java.ast.AstMethodBodyBuilder.createMethodBody(AstMethodBodyBuilder.java:213)
        //     at com.strobel.decompiler.languages.java.ast.AstMethodBodyBuilder.createMethodBody(AstMethodBodyBuilder.java:93)
        //     at com.strobel.decompiler.languages.java.ast.AstBuilder.createMethodBody(AstBuilder.java:868)
        //     at com.strobel.decompiler.languages.java.ast.AstBuilder.createMethod(AstBuilder.java:761)
        //     at com.strobel.decompiler.languages.java.ast.AstBuilder.addTypeMembers(AstBuilder.java:638)
        //     at com.strobel.decompiler.languages.java.ast.AstBuilder.createTypeCore(AstBuilder.java:605)
        //     at com.strobel.decompiler.languages.java.ast.AstBuilder.createTypeNoCache(AstBuilder.java:195)
        //     at com.strobel.decompiler.languages.java.ast.AstBuilder.createType(AstBuilder.java:162)
        //     at com.strobel.decompiler.languages.java.ast.AstBuilder.addType(AstBuilder.java:137)
        //     at com.strobel.decompiler.languages.java.JavaLanguage.buildAst(JavaLanguage.java:71)
        //     at com.strobel.decompiler.languages.java.JavaLanguage.decompileType(JavaLanguage.java:59)
        //     at com.strobel.decompiler.DecompilerDriver.decompileType(DecompilerDriver.java:333)
        //     at com.strobel.decompiler.DecompilerDriver.decompileJar(DecompilerDriver.java:254)
        //     at com.strobel.decompiler.DecompilerDriver.main(DecompilerDriver.java:129)
        // 
        throw new IllegalStateException("An error occurred while decompiling this method.");
    }
}
