// 
// Decompiled by Procyon v0.6.0
// 

package X;

import android.util.Pair;
import java.util.Map;
import java.util.List;
import android.os.Looper;
import com.bytedance.covode.number.Covode;

public final class 1Ec implements 0UC
{
    static {
        Covode.recordClassIndex(4708);
    }
    
    @Override
    public final void LIZ(final 1E7 1e7, final 0Tu 0Tu) {
        public final class 0UJ implements Runnable
        {
            public final /* synthetic */ 1E7 LIZ;
            public final /* synthetic */ 0Tu LIZIZ;
            public final /* synthetic */ 1Ec LIZJ;
            
            static {
                Covode.recordClassIndex(4711);
            }
            
            public 0UJ(final 1Ec lizj, final 1E7 liz, final 0Tu liziz) {
                this.LIZJ = lizj;
                this.LIZ = liz;
                this.LIZIZ = liziz;
            }
            
            @Override
            public final void run() {
                this.LIZJ.LIZIZ(this.LIZ, this.LIZIZ);
            }
        }
        // 
        // This method could not be decompiled.
        // 
        // Original Bytecode:
        // 
        //     3: invokestatic    android/os/Looper.myLooper:()Landroid/os/Looper;
        //     6: if_acmpne       23
        //     9: new             LX/0UJ;
        //    12: dup            
        //    13: aload_0        
        //    14: aload_1        
        //    15: aload_2        
        //    16: invokespecial   X/0UJ.<init>:(LX/1Ec;LX/1E7;LX/0Tu;)V
        //    19: invokestatic    X/6vJ.LIZ:(Ljava/lang/Runnable;)V
        //    22: return         
        //    23: aload_0        
        //    24: aload_1        
        //    25: aload_2        
        //    26: invokevirtual   X/1Ec.LIZIZ:(LX/1E7;LX/0Tu;)V
        //    29: return         
        // 
        // The error that occurred was:
        // 
        // java.lang.NullPointerException
        //     at com.strobel.decompiler.languages.java.ast.AstBuilder.convertType(AstBuilder.java:419)
        //     at com.strobel.decompiler.languages.java.ast.AstBuilder.convertType(AstBuilder.java:207)
        //     at com.strobel.decompiler.languages.java.ast.AstMethodBodyBuilder.transformCall(AstMethodBodyBuilder.java:1106)
        //     at com.strobel.decompiler.languages.java.ast.AstMethodBodyBuilder.transformByteCode(AstMethodBodyBuilder.java:993)
        //     at com.strobel.decompiler.languages.java.ast.AstMethodBodyBuilder.transformExpression(AstMethodBodyBuilder.java:534)
        //     at com.strobel.decompiler.languages.java.ast.AstMethodBodyBuilder.transformByteCode(AstMethodBodyBuilder.java:548)
        //     at com.strobel.decompiler.languages.java.ast.AstMethodBodyBuilder.transformExpression(AstMethodBodyBuilder.java:534)
        //     at com.strobel.decompiler.languages.java.ast.AstMethodBodyBuilder.transformNode(AstMethodBodyBuilder.java:377)
        //     at com.strobel.decompiler.languages.java.ast.AstMethodBodyBuilder.transformBlock(AstMethodBodyBuilder.java:318)
        //     at com.strobel.decompiler.languages.java.ast.AstMethodBodyBuilder.transformNode(AstMethodBodyBuilder.java:425)
        //     at com.strobel.decompiler.languages.java.ast.AstMethodBodyBuilder.transformBlock(AstMethodBodyBuilder.java:318)
        //     at com.strobel.decompiler.languages.java.ast.AstMethodBodyBuilder.createMethodBody(AstMethodBodyBuilder.java:213)
        //     at com.strobel.decompiler.languages.java.ast.AstMethodBodyBuilder.createMethodBody(AstMethodBodyBuilder.java:93)
        //     at com.strobel.decompiler.languages.java.ast.AstBuilder.createMethodBody(AstBuilder.java:868)
        //     at com.strobel.decompiler.languages.java.ast.AstBuilder.createMethod(AstBuilder.java:761)
        //     at com.strobel.decompiler.languages.java.ast.AstBuilder.addTypeMembers(AstBuilder.java:638)
        //     at com.strobel.decompiler.languages.java.ast.AstBuilder.createTypeCore(AstBuilder.java:605)
        //     at com.strobel.decompiler.languages.java.ast.AstBuilder.createTypeNoCache(AstBuilder.java:195)
        //     at com.strobel.decompiler.languages.java.ast.AstBuilder.createType(AstBuilder.java:162)
        //     at com.strobel.decompiler.languages.java.ast.AstBuilder.addType(AstBuilder.java:137)
        //     at com.strobel.decompiler.languages.java.JavaLanguage.buildAst(JavaLanguage.java:71)
        //     at com.strobel.decompiler.languages.java.JavaLanguage.decompileType(JavaLanguage.java:59)
        //     at com.strobel.decompiler.DecompilerDriver.decompileType(DecompilerDriver.java:333)
        //     at com.strobel.decompiler.DecompilerDriver.decompileJar(DecompilerDriver.java:254)
        //     at com.strobel.decompiler.DecompilerDriver.main(DecompilerDriver.java:129)
        // 
        throw new IllegalStateException("An error occurred while decompiling this method.");
    }
    
    @Override
    public final void LIZ(final 1E8 1e8, final 0Tx 0Tx) {
        public final class 0UH implements Runnable
        {
            public final /* synthetic */ 1E8 LIZ;
            public final /* synthetic */ 0Tx LIZIZ;
            public final /* synthetic */ 1Ec LIZJ;
            
            static {
                Covode.recordClassIndex(4709);
            }
            
            public 0UH(final 1Ec lizj, final 1E8 liz, final 0Tx liziz) {
                this.LIZJ = lizj;
                this.LIZ = liz;
                this.LIZIZ = liziz;
            }
            
            @Override
            public final void run() {
                this.LIZJ.LIZIZ(this.LIZ, this.LIZIZ);
            }
        }
        // 
        // This method could not be decompiled.
        // 
        // Original Bytecode:
        // 
        //     3: invokestatic    android/os/Looper.myLooper:()Landroid/os/Looper;
        //     6: if_acmpne       23
        //     9: new             LX/0UH;
        //    12: dup            
        //    13: aload_0        
        //    14: aload_1        
        //    15: aload_2        
        //    16: invokespecial   X/0UH.<init>:(LX/1Ec;LX/1E8;LX/0Tx;)V
        //    19: invokestatic    X/6vJ.LIZ:(Ljava/lang/Runnable;)V
        //    22: return         
        //    23: aload_0        
        //    24: aload_1        
        //    25: aload_2        
        //    26: invokevirtual   X/1Ec.LIZIZ:(LX/1E8;LX/0Tx;)V
        //    29: return         
        // 
        // The error that occurred was:
        // 
        // java.lang.NullPointerException
        //     at com.strobel.decompiler.languages.java.ast.AstBuilder.convertType(AstBuilder.java:419)
        //     at com.strobel.decompiler.languages.java.ast.AstBuilder.convertType(AstBuilder.java:207)
        //     at com.strobel.decompiler.languages.java.ast.AstMethodBodyBuilder.transformCall(AstMethodBodyBuilder.java:1106)
        //     at com.strobel.decompiler.languages.java.ast.AstMethodBodyBuilder.transformByteCode(AstMethodBodyBuilder.java:993)
        //     at com.strobel.decompiler.languages.java.ast.AstMethodBodyBuilder.transformExpression(AstMethodBodyBuilder.java:534)
        //     at com.strobel.decompiler.languages.java.ast.AstMethodBodyBuilder.transformByteCode(AstMethodBodyBuilder.java:548)
        //     at com.strobel.decompiler.languages.java.ast.AstMethodBodyBuilder.transformExpression(AstMethodBodyBuilder.java:534)
        //     at com.strobel.decompiler.languages.java.ast.AstMethodBodyBuilder.transformNode(AstMethodBodyBuilder.java:377)
        //     at com.strobel.decompiler.languages.java.ast.AstMethodBodyBuilder.transformBlock(AstMethodBodyBuilder.java:318)
        //     at com.strobel.decompiler.languages.java.ast.AstMethodBodyBuilder.transformNode(AstMethodBodyBuilder.java:425)
        //     at com.strobel.decompiler.languages.java.ast.AstMethodBodyBuilder.transformBlock(AstMethodBodyBuilder.java:318)
        //     at com.strobel.decompiler.languages.java.ast.AstMethodBodyBuilder.createMethodBody(AstMethodBodyBuilder.java:213)
        //     at com.strobel.decompiler.languages.java.ast.AstMethodBodyBuilder.createMethodBody(AstMethodBodyBuilder.java:93)
        //     at com.strobel.decompiler.languages.java.ast.AstBuilder.createMethodBody(AstBuilder.java:868)
        //     at com.strobel.decompiler.languages.java.ast.AstBuilder.createMethod(AstBuilder.java:761)
        //     at com.strobel.decompiler.languages.java.ast.AstBuilder.addTypeMembers(AstBuilder.java:638)
        //     at com.strobel.decompiler.languages.java.ast.AstBuilder.createTypeCore(AstBuilder.java:605)
        //     at com.strobel.decompiler.languages.java.ast.AstBuilder.createTypeNoCache(AstBuilder.java:195)
        //     at com.strobel.decompiler.languages.java.ast.AstBuilder.createType(AstBuilder.java:162)
        //     at com.strobel.decompiler.languages.java.ast.AstBuilder.addType(AstBuilder.java:137)
        //     at com.strobel.decompiler.languages.java.JavaLanguage.buildAst(JavaLanguage.java:71)
        //     at com.strobel.decompiler.languages.java.JavaLanguage.decompileType(JavaLanguage.java:59)
        //     at com.strobel.decompiler.DecompilerDriver.decompileType(DecompilerDriver.java:333)
        //     at com.strobel.decompiler.DecompilerDriver.decompileJar(DecompilerDriver.java:254)
        //     at com.strobel.decompiler.DecompilerDriver.main(DecompilerDriver.java:129)
        // 
        throw new IllegalStateException("An error occurred while decompiling this method.");
    }
    
    @Override
    public final void LIZ(final 1E9 1e9, final 0Ty 0Ty) {
        public final class 0UI implements Runnable
        {
            public final /* synthetic */ 1E9 LIZ;
            public final /* synthetic */ 0Ty LIZIZ;
            public final /* synthetic */ 1Ec LIZJ;
            
            static {
                Covode.recordClassIndex(4710);
            }
            
            public 0UI(final 1Ec lizj, final 1E9 liz, final 0Ty liziz) {
                this.LIZJ = lizj;
                this.LIZ = liz;
                this.LIZIZ = liziz;
            }
            
            @Override
            public final void run() {
                this.LIZJ.LIZIZ(this.LIZ, this.LIZIZ);
            }
        }
        // 
        // This method could not be decompiled.
        // 
        // Original Bytecode:
        // 
        //     3: invokestatic    android/os/Looper.myLooper:()Landroid/os/Looper;
        //     6: if_acmpne       23
        //     9: new             LX/0UI;
        //    12: dup            
        //    13: aload_0        
        //    14: aload_1        
        //    15: aload_2        
        //    16: invokespecial   X/0UI.<init>:(LX/1Ec;LX/1E9;LX/0Ty;)V
        //    19: invokestatic    X/6vJ.LIZ:(Ljava/lang/Runnable;)V
        //    22: return         
        //    23: aload_0        
        //    24: aload_1        
        //    25: aload_2        
        //    26: invokevirtual   X/1Ec.LIZIZ:(LX/1E9;LX/0Ty;)V
        //    29: return         
        // 
        // The error that occurred was:
        // 
        // java.lang.NullPointerException
        //     at com.strobel.decompiler.languages.java.ast.AstBuilder.convertType(AstBuilder.java:419)
        //     at com.strobel.decompiler.languages.java.ast.AstBuilder.convertType(AstBuilder.java:207)
        //     at com.strobel.decompiler.languages.java.ast.AstMethodBodyBuilder.transformCall(AstMethodBodyBuilder.java:1106)
        //     at com.strobel.decompiler.languages.java.ast.AstMethodBodyBuilder.transformByteCode(AstMethodBodyBuilder.java:993)
        //     at com.strobel.decompiler.languages.java.ast.AstMethodBodyBuilder.transformExpression(AstMethodBodyBuilder.java:534)
        //     at com.strobel.decompiler.languages.java.ast.AstMethodBodyBuilder.transformByteCode(AstMethodBodyBuilder.java:548)
        //     at com.strobel.decompiler.languages.java.ast.AstMethodBodyBuilder.transformExpression(AstMethodBodyBuilder.java:534)
        //     at com.strobel.decompiler.languages.java.ast.AstMethodBodyBuilder.transformNode(AstMethodBodyBuilder.java:377)
        //     at com.strobel.decompiler.languages.java.ast.AstMethodBodyBuilder.transformBlock(AstMethodBodyBuilder.java:318)
        //     at com.strobel.decompiler.languages.java.ast.AstMethodBodyBuilder.transformNode(AstMethodBodyBuilder.java:425)
        //     at com.strobel.decompiler.languages.java.ast.AstMethodBodyBuilder.transformBlock(AstMethodBodyBuilder.java:318)
        //     at com.strobel.decompiler.languages.java.ast.AstMethodBodyBuilder.createMethodBody(AstMethodBodyBuilder.java:213)
        //     at com.strobel.decompiler.languages.java.ast.AstMethodBodyBuilder.createMethodBody(AstMethodBodyBuilder.java:93)
        //     at com.strobel.decompiler.languages.java.ast.AstBuilder.createMethodBody(AstBuilder.java:868)
        //     at com.strobel.decompiler.languages.java.ast.AstBuilder.createMethod(AstBuilder.java:761)
        //     at com.strobel.decompiler.languages.java.ast.AstBuilder.addTypeMembers(AstBuilder.java:638)
        //     at com.strobel.decompiler.languages.java.ast.AstBuilder.createTypeCore(AstBuilder.java:605)
        //     at com.strobel.decompiler.languages.java.ast.AstBuilder.createTypeNoCache(AstBuilder.java:195)
        //     at com.strobel.decompiler.languages.java.ast.AstBuilder.createType(AstBuilder.java:162)
        //     at com.strobel.decompiler.languages.java.ast.AstBuilder.addType(AstBuilder.java:137)
        //     at com.strobel.decompiler.languages.java.JavaLanguage.buildAst(JavaLanguage.java:71)
        //     at com.strobel.decompiler.languages.java.JavaLanguage.decompileType(JavaLanguage.java:59)
        //     at com.strobel.decompiler.DecompilerDriver.decompileType(DecompilerDriver.java:333)
        //     at com.strobel.decompiler.DecompilerDriver.decompileJar(DecompilerDriver.java:254)
        //     at com.strobel.decompiler.DecompilerDriver.main(DecompilerDriver.java:129)
        // 
        throw new IllegalStateException("An error occurred while decompiling this method.");
    }
    
    public final void LIZIZ(final 1E7 p0, final 0Tu p1) {
        // 
        // This method could not be decompiled.
        // 
        // Original Bytecode:
        // 
        //     3: invokestatic    com/bytedance/frameworks/apm/trace/MethodCollector.i:(I)V
        //     6: aload_1        
        //     7: invokevirtual   X/0Te.LIZ:()Ljava/util/List;
        //    10: astore_3       
        //    11: aload_1        
        //    12: getfield        X/0Te.LIZLLL:Ljava/util/Map;
        //    15: astore          4
        //    17: new             Ljava/lang/StringBuilder;
        //    20: astore          5
        //    22: aload           5
        //    24: ldc             ""
        //    26: invokespecial   java/lang/StringBuilder.<init>:(Ljava/lang/String;)V
        //    29: iconst_0       
        //    30: istore          6
        //    32: aload_3        
        //    33: invokeinterface java/util/List.size:()I
        //    38: istore          7
        //    40: iload           6
        //    42: iload           7
        //    44: if_icmpge       146
        //    47: aload_3        
        //    48: iload           6
        //    50: invokeinterface java/util/List.get:(I)Ljava/lang/Object;
        //    55: checkcast       Landroid/util/Pair;
        //    58: astore_1       
        //    59: new             Ljava/lang/StringBuilder;
        //    62: astore          8
        //    64: aload           8
        //    66: invokespecial   java/lang/StringBuilder.<init>:()V
        //    69: aload           8
        //    71: aload_1        
        //    72: getfield        android/util/Pair.first:Ljava/lang/Object;
        //    75: checkcast       Ljava/lang/String;
        //    78: invokevirtual   java/lang/StringBuilder.append:(Ljava/lang/String;)Ljava/lang/StringBuilder;
        //    81: pop            
        //    82: aload           8
        //    84: ldc             "="
        //    86: invokevirtual   java/lang/StringBuilder.append:(Ljava/lang/String;)Ljava/lang/StringBuilder;
        //    89: pop            
        //    90: aload           8
        //    92: aload_1        
        //    93: getfield        android/util/Pair.second:Ljava/lang/Object;
        //    96: checkcast       Ljava/lang/String;
        //    99: ldc             "UTF-8"
        //   101: invokestatic    java/net/URLEncoder.encode:(Ljava/lang/String;Ljava/lang/String;)Ljava/lang/String;
        //   104: invokevirtual   java/lang/StringBuilder.append:(Ljava/lang/String;)Ljava/lang/StringBuilder;
        //   107: pop            
        //   108: aload           5
        //   110: aload           8
        //   112: invokevirtual   java/lang/StringBuilder.toString:()Ljava/lang/String;
        //   115: invokevirtual   java/lang/StringBuilder.append:(Ljava/lang/String;)Ljava/lang/StringBuilder;
        //   118: pop            
        //   119: iload           6
        //   121: aload_3        
        //   122: invokeinterface java/util/List.size:()I
        //   127: iconst_1       
        //   128: isub           
        //   129: if_icmpge       140
        //   132: aload           5
        //   134: ldc             "&"
        //   136: invokevirtual   java/lang/StringBuilder.append:(Ljava/lang/String;)Ljava/lang/StringBuilder;
        //   139: pop            
        //   140: iinc            6, 1
        //   143: goto            32
        //   146: aload           5
        //   148: invokevirtual   java/lang/StringBuilder.toString:()Ljava/lang/String;
        //   151: ldc             "UTF-8"
        //   153: invokevirtual   java/lang/String.getBytes:(Ljava/lang/String;)[B
        //   156: astore          8
        //   158: new             Ljava/io/ByteArrayOutputStream;
        //   161: astore_3       
        //   162: aload_3        
        //   163: sipush          8192
        //   166: invokespecial   java/io/ByteArrayOutputStream.<init>:(I)V
        //   169: new             Ljava/util/zip/GZIPOutputStream;
        //   172: astore_1       
        //   173: aload_1        
        //   174: aload_3        
        //   175: invokespecial   java/util/zip/GZIPOutputStream.<init>:(Ljava/io/OutputStream;)V
        //   178: aload_1        
        //   179: aload           8
        //   181: invokevirtual   java/util/zip/GZIPOutputStream.write:([B)V
        //   184: aload_1        
        //   185: invokevirtual   java/util/zip/GZIPOutputStream.close:()V
        //   188: aload_3        
        //   189: invokevirtual   java/io/ByteArrayOutputStream.toByteArray:()[B
        //   192: astore_3       
        //   193: aload           4
        //   195: astore_1       
        //   196: aload           4
        //   198: ifnonnull       209
        //   201: new             Ljava/util/HashMap;
        //   204: astore_1       
        //   205: aload_1        
        //   206: invokespecial   java/util/HashMap.<init>:()V
        //   209: aload_1        
        //   210: ldc             "Content-Type"
        //   212: ldc             "application/x-www-form-urlencoded"
        //   214: invokeinterface java/util/Map.put:(Ljava/lang/Object;Ljava/lang/Object;)Ljava/lang/Object;
        //   219: pop            
        //   220: aload_1        
        //   221: ldc             "Content-Encoding"
        //   223: ldc             "gzip"
        //   225: invokeinterface java/util/Map.put:(Ljava/lang/Object;Ljava/lang/Object;)Ljava/lang/Object;
        //   230: pop            
        //   231: aload_1        
        //   232: ldc             "Accept-Encoding"
        //   234: ldc             "gzip"
        //   236: invokeinterface java/util/Map.put:(Ljava/lang/Object;Ljava/lang/Object;)Ljava/lang/Object;
        //   241: pop            
        //   242: getstatic       X/1EK.LIZ:LX/1EK;
        //   245: invokevirtual   X/1EK.LIZLLL:()LX/0U1;
        //   248: getfield        X/0U1.LJIIJJI:LX/5zW;
        //   251: ldc             "/payment/v1/get_bankcard_info_by_ocr"
        //   253: invokestatic    X/0Tz.LIZ:(Ljava/lang/String;)Ljava/lang/String;
        //   256: aload_3        
        //   257: aload_1        
        //   258: invokevirtual   X/5zW.LIZ:(Ljava/lang/String;[BLjava/util/Map;)Ljava/lang/String;
        //   261: astore_1       
        //   262: new             LX/1EA;
        //   265: astore          4
        //   267: aload           4
        //   269: aload_1        
        //   270: invokespecial   X/1EA.<init>:(Ljava/lang/String;)V
        //   273: aload_2        
        //   274: iconst_1       
        //   275: ldc             ""
        //   277: aload           4
        //   279: invokeinterface X/0Tu.LIZ:(ZLjava/lang/String;LX/1EA;)V
        //   284: sipush          6898
        //   287: invokestatic    com/bytedance/frameworks/apm/trace/MethodCollector.o:(I)V
        //   290: return         
        //   291: astore_1       
        //   292: aload_1        
        //   293: invokevirtual   java/lang/Throwable.getMessage:()Ljava/lang/String;
        //   296: pop            
        //   297: aload_1        
        //   298: invokestatic    android/util/Log.getStackTraceString:(Ljava/lang/Throwable;)Ljava/lang/String;
        //   301: pop            
        //   302: aload_2        
        //   303: iconst_0       
        //   304: aload_1        
        //   305: invokevirtual   java/lang/Throwable.getMessage:()Ljava/lang/String;
        //   308: aconst_null    
        //   309: invokeinterface X/0Tu.LIZ:(ZLjava/lang/String;LX/1EA;)V
        //   314: sipush          6898
        //   317: invokestatic    com/bytedance/frameworks/apm/trace/MethodCollector.o:(I)V
        //   320: return         
        //   321: astore          8
        //   323: goto            184
        //    Exceptions:
        //  Try           Handler
        //  Start  End    Start  End    Type
        //  -----  -----  -----  -----  ----
        //  17     29     291    321    Any
        //  32     40     291    321    Any
        //  47     140    291    321    Any
        //  146    178    291    321    Any
        //  178    184    321    326    Any
        //  184    193    291    321    Any
        //  201    209    291    321    Any
        //  209    284    291    321    Any
        // 
        // The error that occurred was:
        // 
        // java.lang.IllegalStateException: Expression is linked from several locations: Label_0184:
        //     at com.strobel.decompiler.ast.Error.expressionLinkedFromMultipleLocations(Error.java:27)
        //     at com.strobel.decompiler.ast.AstOptimizer.mergeDisparateObjectInitializations(AstOptimizer.java:2604)
        //     at com.strobel.decompiler.ast.AstOptimizer.optimize(AstOptimizer.java:235)
        //     at com.strobel.decompiler.ast.AstOptimizer.optimize(AstOptimizer.java:42)
        //     at com.strobel.decompiler.languages.java.ast.AstMethodBodyBuilder.createMethodBody(AstMethodBodyBuilder.java:206)
        //     at com.strobel.decompiler.languages.java.ast.AstMethodBodyBuilder.createMethodBody(AstMethodBodyBuilder.java:93)
        //     at com.strobel.decompiler.languages.java.ast.AstBuilder.createMethodBody(AstBuilder.java:868)
        //     at com.strobel.decompiler.languages.java.ast.AstBuilder.createMethod(AstBuilder.java:761)
        //     at com.strobel.decompiler.languages.java.ast.AstBuilder.addTypeMembers(AstBuilder.java:638)
        //     at com.strobel.decompiler.languages.java.ast.AstBuilder.createTypeCore(AstBuilder.java:605)
        //     at com.strobel.decompiler.languages.java.ast.AstBuilder.createTypeNoCache(AstBuilder.java:195)
        //     at com.strobel.decompiler.languages.java.ast.AstBuilder.createType(AstBuilder.java:162)
        //     at com.strobel.decompiler.languages.java.ast.AstBuilder.addType(AstBuilder.java:137)
        //     at com.strobel.decompiler.languages.java.JavaLanguage.buildAst(JavaLanguage.java:71)
        //     at com.strobel.decompiler.languages.java.JavaLanguage.decompileType(JavaLanguage.java:59)
        //     at com.strobel.decompiler.DecompilerDriver.decompileType(DecompilerDriver.java:333)
        //     at com.strobel.decompiler.DecompilerDriver.decompileJar(DecompilerDriver.java:254)
        //     at com.strobel.decompiler.DecompilerDriver.main(DecompilerDriver.java:129)
        // 
        throw new IllegalStateException("An error occurred while decompiling this method.");
    }
    
    public final void LIZIZ(final 1E8 1e8, final 0Tx 0Tx) {
        final String liz = 0Tz.LIZ("/payment/v1/pay");
        final List<Pair<String, String>> liz2 = 1e8.LIZ();
        1EB 1eb = new 1EB();
        try {
            final 1EB 1eb2 = new 1EB(1EK.LIZ.LIZLLL().LJIIJJI.LIZ(liz, (List)liz2, (Map)1e8.LIZLLL));
            try {
                0Tx.LIZ(1eb2);
            }
            finally {
                1eb = 1eb2;
            }
            return;
        }
        finally {}
        1eb.LIZLLL = "exception";
        final Throwable t;
        1eb.LJ = t.getLocalizedMessage();
        0Tx.LIZ(1eb);
    }
    
    public final void LIZIZ(final 1E9 1e9, final 0Ty 0Ty) {
        System.currentTimeMillis();
        final String liz = 0Tz.LIZ("/payment/v1/payment_details");
        final List<Pair<String, String>> liz2 = 1e9.LIZ();
        try {
            0Ty.LIZ(new 1EC(1EK.LIZ.LIZLLL().LJIIJJI.LIZ(liz, (List)liz2, (Map)1e9.LIZLLL)));
        }
        finally {
            final 1EC 1ec = new 1EC();
            1ec.LJFF = "exception";
            final Throwable t;
            1ec.LJI = t.getLocalizedMessage();
            0Ty.LIZ(1ec);
        }
    }
}
