// 
// Decompiled by Procyon v0.6.0
// 

package X;

import com.bytedance.covode.number.Covode;
import com.bytedance.android.live.liveinteract.cohost.business.contract.CoHostSettingContract;

public final class 1k2 extends a
{
    static {
        Covode.recordClassIndex(7269);
    }
    
    public 1k2(final CoHostSettingContract.AbsView absView) {
        super(absView);
    }
    
    @Override
    public final void LIZ(final boolean b) {
        public final class 1OH<T> implements 2d6
        {
            public final /* synthetic */ 1k2 LIZ;
            
            static {
                Covode.recordClassIndex(7271);
            }
            
            public 1OH(final 1k2 liz) {
                this.LIZ = liz;
            }
        }
        public final class 1OG<T> implements 2d6
        {
            public final /* synthetic */ 1k2 LIZ;
            
            static {
                Covode.recordClassIndex(7270);
            }
            
            public 1OG(final 1k2 liz) {
                this.LIZ = liz;
            }
        }
        // 
        // This method could not be decompiled.
        // 
        // Original Bytecode:
        // 
        //     1: iload_1        
        //     2: invokestatic    X/0xT.LIZ:(IZ)LX/FBF;
        //     5: astore_2       
        //     6: aload_2        
        //     7: ifnonnull       11
        //    10: return         
        //    11: aload_2        
        //    12: aload_0        
        //    13: invokevirtual   X/0kz.LJI:()LX/FCn;
        //    16: invokevirtual   X/FBF.LIZ:(LX/FBZ;)Ljava/lang/Object;
        //    19: checkcast       LX/FIc;
        //    22: new             LX/1OG;
        //    25: dup            
        //    26: aload_0        
        //    27: invokespecial   X/1OG.<init>:(LX/1k2;)V
        //    30: new             LX/1OH;
        //    33: dup            
        //    34: aload_0        
        //    35: invokespecial   X/1OH.<init>:(LX/1k2;)V
        //    38: invokeinterface X/FIc.LIZ:(LX/2d6;LX/2d6;)LX/2fc;
        //    43: pop            
        //    44: return         
        // 
        // The error that occurred was:
        // 
        // java.lang.NullPointerException
        //     at com.strobel.decompiler.languages.java.ast.AstBuilder.convertType(AstBuilder.java:419)
        //     at com.strobel.decompiler.languages.java.ast.AstBuilder.convertType(AstBuilder.java:207)
        //     at com.strobel.decompiler.languages.java.ast.AstMethodBodyBuilder.transformCall(AstMethodBodyBuilder.java:1106)
        //     at com.strobel.decompiler.languages.java.ast.AstMethodBodyBuilder.transformByteCode(AstMethodBodyBuilder.java:993)
        //     at com.strobel.decompiler.languages.java.ast.AstMethodBodyBuilder.transformExpression(AstMethodBodyBuilder.java:534)
        //     at com.strobel.decompiler.languages.java.ast.AstMethodBodyBuilder.transformByteCode(AstMethodBodyBuilder.java:548)
        //     at com.strobel.decompiler.languages.java.ast.AstMethodBodyBuilder.transformExpression(AstMethodBodyBuilder.java:534)
        //     at com.strobel.decompiler.languages.java.ast.AstMethodBodyBuilder.transformNode(AstMethodBodyBuilder.java:377)
        //     at com.strobel.decompiler.languages.java.ast.AstMethodBodyBuilder.transformBlock(AstMethodBodyBuilder.java:318)
        //     at com.strobel.decompiler.languages.java.ast.AstMethodBodyBuilder.createMethodBody(AstMethodBodyBuilder.java:213)
        //     at com.strobel.decompiler.languages.java.ast.AstMethodBodyBuilder.createMethodBody(AstMethodBodyBuilder.java:93)
        //     at com.strobel.decompiler.languages.java.ast.AstBuilder.createMethodBody(AstBuilder.java:868)
        //     at com.strobel.decompiler.languages.java.ast.AstBuilder.createMethod(AstBuilder.java:761)
        //     at com.strobel.decompiler.languages.java.ast.AstBuilder.addTypeMembers(AstBuilder.java:638)
        //     at com.strobel.decompiler.languages.java.ast.AstBuilder.createTypeCore(AstBuilder.java:605)
        //     at com.strobel.decompiler.languages.java.ast.AstBuilder.createTypeNoCache(AstBuilder.java:195)
        //     at com.strobel.decompiler.languages.java.ast.AstBuilder.createType(AstBuilder.java:162)
        //     at com.strobel.decompiler.languages.java.ast.AstBuilder.addType(AstBuilder.java:137)
        //     at com.strobel.decompiler.languages.java.JavaLanguage.buildAst(JavaLanguage.java:71)
        //     at com.strobel.decompiler.languages.java.JavaLanguage.decompileType(JavaLanguage.java:59)
        //     at com.strobel.decompiler.DecompilerDriver.decompileType(DecompilerDriver.java:333)
        //     at com.strobel.decompiler.DecompilerDriver.decompileJar(DecompilerDriver.java:254)
        //     at com.strobel.decompiler.DecompilerDriver.main(DecompilerDriver.java:129)
        // 
        throw new IllegalStateException("An error occurred while decompiling this method.");
    }
    
    @Override
    public final void LIZIZ(final boolean b) {
        public final class 1OL<T> implements 2d6
        {
            public final /* synthetic */ 1k2 LIZ;
            
            static {
                Covode.recordClassIndex(7275);
            }
            
            public 1OL(final 1k2 liz) {
                this.LIZ = liz;
            }
        }
        public final class 1OK<T> implements 2d6
        {
            public final /* synthetic */ 1k2 LIZ;
            
            static {
                Covode.recordClassIndex(7274);
            }
            
            public 1OK(final 1k2 liz) {
                this.LIZ = liz;
            }
        }
        // 
        // This method could not be decompiled.
        // 
        // Original Bytecode:
        // 
        //     1: iload_1        
        //     2: invokestatic    X/0xT.LIZ:(IZ)LX/FBF;
        //     5: astore_2       
        //     6: aload_2        
        //     7: ifnonnull       11
        //    10: return         
        //    11: aload_2        
        //    12: aload_0        
        //    13: invokevirtual   X/0kz.LJI:()LX/FCn;
        //    16: invokevirtual   X/FBF.LIZ:(LX/FBZ;)Ljava/lang/Object;
        //    19: checkcast       LX/FIc;
        //    22: new             LX/1OK;
        //    25: dup            
        //    26: aload_0        
        //    27: invokespecial   X/1OK.<init>:(LX/1k2;)V
        //    30: new             LX/1OL;
        //    33: dup            
        //    34: aload_0        
        //    35: invokespecial   X/1OL.<init>:(LX/1k2;)V
        //    38: invokeinterface X/FIc.LIZ:(LX/2d6;LX/2d6;)LX/2fc;
        //    43: pop            
        //    44: return         
        // 
        // The error that occurred was:
        // 
        // java.lang.NullPointerException
        //     at com.strobel.decompiler.languages.java.ast.AstBuilder.convertType(AstBuilder.java:419)
        //     at com.strobel.decompiler.languages.java.ast.AstBuilder.convertType(AstBuilder.java:207)
        //     at com.strobel.decompiler.languages.java.ast.AstMethodBodyBuilder.transformCall(AstMethodBodyBuilder.java:1106)
        //     at com.strobel.decompiler.languages.java.ast.AstMethodBodyBuilder.transformByteCode(AstMethodBodyBuilder.java:993)
        //     at com.strobel.decompiler.languages.java.ast.AstMethodBodyBuilder.transformExpression(AstMethodBodyBuilder.java:534)
        //     at com.strobel.decompiler.languages.java.ast.AstMethodBodyBuilder.transformByteCode(AstMethodBodyBuilder.java:548)
        //     at com.strobel.decompiler.languages.java.ast.AstMethodBodyBuilder.transformExpression(AstMethodBodyBuilder.java:534)
        //     at com.strobel.decompiler.languages.java.ast.AstMethodBodyBuilder.transformNode(AstMethodBodyBuilder.java:377)
        //     at com.strobel.decompiler.languages.java.ast.AstMethodBodyBuilder.transformBlock(AstMethodBodyBuilder.java:318)
        //     at com.strobel.decompiler.languages.java.ast.AstMethodBodyBuilder.createMethodBody(AstMethodBodyBuilder.java:213)
        //     at com.strobel.decompiler.languages.java.ast.AstMethodBodyBuilder.createMethodBody(AstMethodBodyBuilder.java:93)
        //     at com.strobel.decompiler.languages.java.ast.AstBuilder.createMethodBody(AstBuilder.java:868)
        //     at com.strobel.decompiler.languages.java.ast.AstBuilder.createMethod(AstBuilder.java:761)
        //     at com.strobel.decompiler.languages.java.ast.AstBuilder.addTypeMembers(AstBuilder.java:638)
        //     at com.strobel.decompiler.languages.java.ast.AstBuilder.createTypeCore(AstBuilder.java:605)
        //     at com.strobel.decompiler.languages.java.ast.AstBuilder.createTypeNoCache(AstBuilder.java:195)
        //     at com.strobel.decompiler.languages.java.ast.AstBuilder.createType(AstBuilder.java:162)
        //     at com.strobel.decompiler.languages.java.ast.AstBuilder.addType(AstBuilder.java:137)
        //     at com.strobel.decompiler.languages.java.JavaLanguage.buildAst(JavaLanguage.java:71)
        //     at com.strobel.decompiler.languages.java.JavaLanguage.decompileType(JavaLanguage.java:59)
        //     at com.strobel.decompiler.DecompilerDriver.decompileType(DecompilerDriver.java:333)
        //     at com.strobel.decompiler.DecompilerDriver.decompileJar(DecompilerDriver.java:254)
        //     at com.strobel.decompiler.DecompilerDriver.main(DecompilerDriver.java:129)
        // 
        throw new IllegalStateException("An error occurred while decompiling this method.");
    }
    
    @Override
    public final void LIZJ(final boolean b) {
        public final class 1OJ<T> implements 2d6
        {
            public final /* synthetic */ 1k2 LIZ;
            
            static {
                Covode.recordClassIndex(7273);
            }
            
            public 1OJ(final 1k2 liz) {
                this.LIZ = liz;
            }
        }
        public final class 1OI<T> implements 2d6
        {
            public final /* synthetic */ 1k2 LIZ;
            
            static {
                Covode.recordClassIndex(7272);
            }
            
            public 1OI(final 1k2 liz) {
                this.LIZ = liz;
            }
        }
        // 
        // This method could not be decompiled.
        // 
        // Original Bytecode:
        // 
        //     2: iload_1        
        //     3: invokestatic    X/0xT.LIZ:(IZ)LX/FBF;
        //     6: astore_2       
        //     7: aload_2        
        //     8: ifnonnull       12
        //    11: return         
        //    12: aload_2        
        //    13: aload_0        
        //    14: invokevirtual   X/0kz.LJI:()LX/FCn;
        //    17: invokevirtual   X/FBF.LIZ:(LX/FBZ;)Ljava/lang/Object;
        //    20: checkcast       LX/FIc;
        //    23: new             LX/1OI;
        //    26: dup            
        //    27: aload_0        
        //    28: invokespecial   X/1OI.<init>:(LX/1k2;)V
        //    31: new             LX/1OJ;
        //    34: dup            
        //    35: aload_0        
        //    36: invokespecial   X/1OJ.<init>:(LX/1k2;)V
        //    39: invokeinterface X/FIc.LIZ:(LX/2d6;LX/2d6;)LX/2fc;
        //    44: pop            
        //    45: return         
        // 
        // The error that occurred was:
        // 
        // java.lang.NullPointerException
        //     at com.strobel.decompiler.languages.java.ast.AstBuilder.convertType(AstBuilder.java:419)
        //     at com.strobel.decompiler.languages.java.ast.AstBuilder.convertType(AstBuilder.java:207)
        //     at com.strobel.decompiler.languages.java.ast.AstMethodBodyBuilder.transformCall(AstMethodBodyBuilder.java:1106)
        //     at com.strobel.decompiler.languages.java.ast.AstMethodBodyBuilder.transformByteCode(AstMethodBodyBuilder.java:993)
        //     at com.strobel.decompiler.languages.java.ast.AstMethodBodyBuilder.transformExpression(AstMethodBodyBuilder.java:534)
        //     at com.strobel.decompiler.languages.java.ast.AstMethodBodyBuilder.transformByteCode(AstMethodBodyBuilder.java:548)
        //     at com.strobel.decompiler.languages.java.ast.AstMethodBodyBuilder.transformExpression(AstMethodBodyBuilder.java:534)
        //     at com.strobel.decompiler.languages.java.ast.AstMethodBodyBuilder.transformNode(AstMethodBodyBuilder.java:377)
        //     at com.strobel.decompiler.languages.java.ast.AstMethodBodyBuilder.transformBlock(AstMethodBodyBuilder.java:318)
        //     at com.strobel.decompiler.languages.java.ast.AstMethodBodyBuilder.createMethodBody(AstMethodBodyBuilder.java:213)
        //     at com.strobel.decompiler.languages.java.ast.AstMethodBodyBuilder.createMethodBody(AstMethodBodyBuilder.java:93)
        //     at com.strobel.decompiler.languages.java.ast.AstBuilder.createMethodBody(AstBuilder.java:868)
        //     at com.strobel.decompiler.languages.java.ast.AstBuilder.createMethod(AstBuilder.java:761)
        //     at com.strobel.decompiler.languages.java.ast.AstBuilder.addTypeMembers(AstBuilder.java:638)
        //     at com.strobel.decompiler.languages.java.ast.AstBuilder.createTypeCore(AstBuilder.java:605)
        //     at com.strobel.decompiler.languages.java.ast.AstBuilder.createTypeNoCache(AstBuilder.java:195)
        //     at com.strobel.decompiler.languages.java.ast.AstBuilder.createType(AstBuilder.java:162)
        //     at com.strobel.decompiler.languages.java.ast.AstBuilder.addType(AstBuilder.java:137)
        //     at com.strobel.decompiler.languages.java.JavaLanguage.buildAst(JavaLanguage.java:71)
        //     at com.strobel.decompiler.languages.java.JavaLanguage.decompileType(JavaLanguage.java:59)
        //     at com.strobel.decompiler.DecompilerDriver.decompileType(DecompilerDriver.java:333)
        //     at com.strobel.decompiler.DecompilerDriver.decompileJar(DecompilerDriver.java:254)
        //     at com.strobel.decompiler.DecompilerDriver.main(DecompilerDriver.java:129)
        // 
        throw new IllegalStateException("An error occurred while decompiling this method.");
    }
}
