// 
// Decompiled by Procyon v0.6.0
// 

package X;

import android.view.View;
import kotlin.jvm.internal.n;
import androidx.recyclerview.widget.RecyclerView;
import android.view.ViewGroup;
import android.view.LayoutInflater;
import com.bytedance.covode.number.Covode;

public final class 1PB extends Evv<1P4, a>
{
    static {
        Covode.recordClassIndex(7400);
    }
    
    public final class a extends ViewHolder
    {
        public final 5DO LIZ;
        
        static {
            Covode.recordClassIndex(7401);
        }
        
        public a(final View view) {
            // 
            // This method could not be decompiled.
            // 
            // Original Bytecode:
            // 
            //     1: invokestatic    X/CTM.LIZ:(Ljava/lang/Object;)V
            //     4: aload_0        
            //     5: aload_1        
            //     6: invokespecial   androidx/recyclerview/widget/RecyclerView$ViewHolder.<init>:(Landroid/view/View;)V
            //     9: aload_0        
            //    10: new             LX/1vg;
            //    13: dup            
            //    14: aload_1        
            //    15: invokespecial   X/1vg.<init>:(Landroid/view/View;)V
            //    18: invokestatic    X/3Os.LIZ:(LX/QgG;)LX/5DO;
            //    21: putfield        X/1PA.LIZ:LX/5DO;
            //    24: return         
            //    Signature:
            //  (Landroid/view/View;)V
            // 
            // The error that occurred was:
            // 
            // java.lang.NullPointerException
            //     at com.strobel.decompiler.languages.java.ast.AstBuilder.convertType(AstBuilder.java:419)
            //     at com.strobel.decompiler.languages.java.ast.AstBuilder.convertType(AstBuilder.java:207)
            //     at com.strobel.decompiler.languages.java.ast.AstMethodBodyBuilder.transformCall(AstMethodBodyBuilder.java:1106)
            //     at com.strobel.decompiler.languages.java.ast.AstMethodBodyBuilder.transformByteCode(AstMethodBodyBuilder.java:993)
            //     at com.strobel.decompiler.languages.java.ast.AstMethodBodyBuilder.transformExpression(AstMethodBodyBuilder.java:534)
            //     at com.strobel.decompiler.languages.java.ast.AstMethodBodyBuilder.transformByteCode(AstMethodBodyBuilder.java:548)
            //     at com.strobel.decompiler.languages.java.ast.AstMethodBodyBuilder.transformExpression(AstMethodBodyBuilder.java:534)
            //     at com.strobel.decompiler.languages.java.ast.AstMethodBodyBuilder.transformByteCode(AstMethodBodyBuilder.java:548)
            //     at com.strobel.decompiler.languages.java.ast.AstMethodBodyBuilder.transformExpression(AstMethodBodyBuilder.java:534)
            //     at com.strobel.decompiler.languages.java.ast.AstMethodBodyBuilder.transformNode(AstMethodBodyBuilder.java:377)
            //     at com.strobel.decompiler.languages.java.ast.AstMethodBodyBuilder.transformBlock(AstMethodBodyBuilder.java:318)
            //     at com.strobel.decompiler.languages.java.ast.AstMethodBodyBuilder.createMethodBody(AstMethodBodyBuilder.java:213)
            //     at com.strobel.decompiler.languages.java.ast.AstMethodBodyBuilder.createMethodBody(AstMethodBodyBuilder.java:93)
            //     at com.strobel.decompiler.languages.java.ast.AstBuilder.createMethodBody(AstBuilder.java:868)
            //     at com.strobel.decompiler.languages.java.ast.AstBuilder.createConstructor(AstBuilder.java:799)
            //     at com.strobel.decompiler.languages.java.ast.AstBuilder.addTypeMembers(AstBuilder.java:635)
            //     at com.strobel.decompiler.languages.java.ast.AstBuilder.createTypeCore(AstBuilder.java:605)
            //     at com.strobel.decompiler.languages.java.ast.AstBuilder.createTypeNoCache(AstBuilder.java:195)
            //     at com.strobel.decompiler.languages.java.ast.AstBuilder.addTypeMembers(AstBuilder.java:662)
            //     at com.strobel.decompiler.languages.java.ast.AstBuilder.createTypeCore(AstBuilder.java:605)
            //     at com.strobel.decompiler.languages.java.ast.AstBuilder.createTypeNoCache(AstBuilder.java:195)
            //     at com.strobel.decompiler.languages.java.ast.AstBuilder.createType(AstBuilder.java:162)
            //     at com.strobel.decompiler.languages.java.ast.AstBuilder.addType(AstBuilder.java:137)
            //     at com.strobel.decompiler.languages.java.JavaLanguage.buildAst(JavaLanguage.java:71)
            //     at com.strobel.decompiler.languages.java.JavaLanguage.decompileType(JavaLanguage.java:59)
            //     at com.strobel.decompiler.DecompilerDriver.decompileType(DecompilerDriver.java:333)
            //     at com.strobel.decompiler.DecompilerDriver.decompileJar(DecompilerDriver.java:254)
            //     at com.strobel.decompiler.DecompilerDriver.main(DecompilerDriver.java:129)
            // 
            throw new IllegalStateException("An error occurred while decompiling this method.");
        }
    }
}
