// 
// Decompiled by Procyon v0.6.0
// 

package androidx.p;

import java.util.Collection;
import X.16Y;
import java.util.ArrayList;
import android.view.View;
import android.graphics.Rect;
import X.0Di;
import android.view.ViewGroup;
import X.16Z;
import java.util.List;
import X.0Dg;
import com.bytedance.covode.number.Covode;
import X.0Ac;

public class d extends 0Ac
{
    static {
        Covode.recordClassIndex(1429);
    }
    
    public static boolean LIZ(final 0Dg 0Dg) {
        return !0Ac.LIZ(0Dg.LJFF) || !0Ac.LIZ(0Dg.LJII) || !0Ac.LIZ(0Dg.LJIIIIZZ);
    }
    
    @Override
    public final Object LIZ(final Object o, final Object o2, final Object o3) {
        final 16Z 16Z = new 16Z();
        if (o != null) {
            16Z.LIZ((0Dg)o);
        }
        if (o2 != null) {
            16Z.LIZ((0Dg)o2);
        }
        if (o3 != null) {
            16Z.LIZ((0Dg)o3);
        }
        return 16Z;
    }
    
    @Override
    public final void LIZ(final ViewGroup viewGroup, final Object o) {
        0Di.LIZ(viewGroup, (0Dg)o);
    }
    
    @Override
    public final void LIZ(final Object o, final Rect rect) {
        public final class 16U extends b
        {
            public final /* synthetic */ Rect LIZ;
            
            static {
                Covode.recordClassIndex(1433);
            }
            
            public 16U(final Rect liz) {
                this.LIZ = liz;
            }
            
            @Override
            public final Rect LIZ() {
                final Rect liz = this.LIZ;
                if (liz == null || liz.isEmpty()) {
                    return null;
                }
                return this.LIZ;
            }
        }
        // 
        // This method could not be decompiled.
        // 
        // Original Bytecode:
        // 
        //     1: ifnull          19
        //     4: aload_1        
        //     5: checkcast       LX/0Dg;
        //     8: new             LX/16U;
        //    11: dup            
        //    12: aload_2        
        //    13: invokespecial   X/16U.<init>:(Landroid/graphics/Rect;)V
        //    16: invokevirtual   X/0Dg.LIZ:(LX/0De;)V
        //    19: return         
        // 
        // The error that occurred was:
        // 
        // java.lang.NullPointerException
        //     at com.strobel.decompiler.languages.java.ast.AstBuilder.convertType(AstBuilder.java:419)
        //     at com.strobel.decompiler.languages.java.ast.AstBuilder.convertType(AstBuilder.java:207)
        //     at com.strobel.decompiler.languages.java.ast.AstMethodBodyBuilder.transformCall(AstMethodBodyBuilder.java:1106)
        //     at com.strobel.decompiler.languages.java.ast.AstMethodBodyBuilder.transformByteCode(AstMethodBodyBuilder.java:993)
        //     at com.strobel.decompiler.languages.java.ast.AstMethodBodyBuilder.transformExpression(AstMethodBodyBuilder.java:534)
        //     at com.strobel.decompiler.languages.java.ast.AstMethodBodyBuilder.transformByteCode(AstMethodBodyBuilder.java:548)
        //     at com.strobel.decompiler.languages.java.ast.AstMethodBodyBuilder.transformExpression(AstMethodBodyBuilder.java:534)
        //     at com.strobel.decompiler.languages.java.ast.AstMethodBodyBuilder.transformNode(AstMethodBodyBuilder.java:377)
        //     at com.strobel.decompiler.languages.java.ast.AstMethodBodyBuilder.transformBlock(AstMethodBodyBuilder.java:318)
        //     at com.strobel.decompiler.languages.java.ast.AstMethodBodyBuilder.transformNode(AstMethodBodyBuilder.java:425)
        //     at com.strobel.decompiler.languages.java.ast.AstMethodBodyBuilder.transformBlock(AstMethodBodyBuilder.java:318)
        //     at com.strobel.decompiler.languages.java.ast.AstMethodBodyBuilder.createMethodBody(AstMethodBodyBuilder.java:213)
        //     at com.strobel.decompiler.languages.java.ast.AstMethodBodyBuilder.createMethodBody(AstMethodBodyBuilder.java:93)
        //     at com.strobel.decompiler.languages.java.ast.AstBuilder.createMethodBody(AstBuilder.java:868)
        //     at com.strobel.decompiler.languages.java.ast.AstBuilder.createMethod(AstBuilder.java:761)
        //     at com.strobel.decompiler.languages.java.ast.AstBuilder.addTypeMembers(AstBuilder.java:638)
        //     at com.strobel.decompiler.languages.java.ast.AstBuilder.createTypeCore(AstBuilder.java:605)
        //     at com.strobel.decompiler.languages.java.ast.AstBuilder.createTypeNoCache(AstBuilder.java:195)
        //     at com.strobel.decompiler.languages.java.ast.AstBuilder.createType(AstBuilder.java:162)
        //     at com.strobel.decompiler.languages.java.ast.AstBuilder.addType(AstBuilder.java:137)
        //     at com.strobel.decompiler.languages.java.JavaLanguage.buildAst(JavaLanguage.java:71)
        //     at com.strobel.decompiler.languages.java.JavaLanguage.decompileType(JavaLanguage.java:59)
        //     at com.strobel.decompiler.DecompilerDriver.decompileType(DecompilerDriver.java:333)
        //     at com.strobel.decompiler.DecompilerDriver.decompileJar(DecompilerDriver.java:254)
        //     at com.strobel.decompiler.DecompilerDriver.main(DecompilerDriver.java:129)
        // 
        throw new IllegalStateException("An error occurred while decompiling this method.");
    }
    
    @Override
    public final void LIZ(final Object o, final View view) {
        public final class 16S extends b
        {
            public final /* synthetic */ Rect LIZ;
            
            static {
                Covode.recordClassIndex(1430);
            }
            
            public 16S(final Rect liz) {
                this.LIZ = liz;
            }
            
            @Override
            public final Rect LIZ() {
                return this.LIZ;
            }
        }
        // 
        // This method could not be decompiled.
        // 
        // Original Bytecode:
        // 
        //     1: ifnull          35
        //     4: aload_1        
        //     5: checkcast       LX/0Dg;
        //     8: astore_3       
        //     9: new             Landroid/graphics/Rect;
        //    12: dup            
        //    13: invokespecial   android/graphics/Rect.<init>:()V
        //    16: astore_1       
        //    17: aload_0        
        //    18: aload_2        
        //    19: aload_1        
        //    20: invokevirtual   X/0Ac.LIZ:(Landroid/view/View;Landroid/graphics/Rect;)V
        //    23: aload_3        
        //    24: new             LX/16S;
        //    27: dup            
        //    28: aload_1        
        //    29: invokespecial   X/16S.<init>:(Landroid/graphics/Rect;)V
        //    32: invokevirtual   X/0Dg.LIZ:(LX/0De;)V
        //    35: return         
        // 
        // The error that occurred was:
        // 
        // java.lang.NullPointerException
        //     at com.strobel.decompiler.languages.java.ast.AstBuilder.convertType(AstBuilder.java:419)
        //     at com.strobel.decompiler.languages.java.ast.AstBuilder.convertType(AstBuilder.java:207)
        //     at com.strobel.decompiler.languages.java.ast.AstMethodBodyBuilder.transformCall(AstMethodBodyBuilder.java:1106)
        //     at com.strobel.decompiler.languages.java.ast.AstMethodBodyBuilder.transformByteCode(AstMethodBodyBuilder.java:993)
        //     at com.strobel.decompiler.languages.java.ast.AstMethodBodyBuilder.transformExpression(AstMethodBodyBuilder.java:534)
        //     at com.strobel.decompiler.languages.java.ast.AstMethodBodyBuilder.transformByteCode(AstMethodBodyBuilder.java:548)
        //     at com.strobel.decompiler.languages.java.ast.AstMethodBodyBuilder.transformExpression(AstMethodBodyBuilder.java:534)
        //     at com.strobel.decompiler.languages.java.ast.AstMethodBodyBuilder.transformNode(AstMethodBodyBuilder.java:377)
        //     at com.strobel.decompiler.languages.java.ast.AstMethodBodyBuilder.transformBlock(AstMethodBodyBuilder.java:318)
        //     at com.strobel.decompiler.languages.java.ast.AstMethodBodyBuilder.transformNode(AstMethodBodyBuilder.java:425)
        //     at com.strobel.decompiler.languages.java.ast.AstMethodBodyBuilder.transformBlock(AstMethodBodyBuilder.java:318)
        //     at com.strobel.decompiler.languages.java.ast.AstMethodBodyBuilder.createMethodBody(AstMethodBodyBuilder.java:213)
        //     at com.strobel.decompiler.languages.java.ast.AstMethodBodyBuilder.createMethodBody(AstMethodBodyBuilder.java:93)
        //     at com.strobel.decompiler.languages.java.ast.AstBuilder.createMethodBody(AstBuilder.java:868)
        //     at com.strobel.decompiler.languages.java.ast.AstBuilder.createMethod(AstBuilder.java:761)
        //     at com.strobel.decompiler.languages.java.ast.AstBuilder.addTypeMembers(AstBuilder.java:638)
        //     at com.strobel.decompiler.languages.java.ast.AstBuilder.createTypeCore(AstBuilder.java:605)
        //     at com.strobel.decompiler.languages.java.ast.AstBuilder.createTypeNoCache(AstBuilder.java:195)
        //     at com.strobel.decompiler.languages.java.ast.AstBuilder.createType(AstBuilder.java:162)
        //     at com.strobel.decompiler.languages.java.ast.AstBuilder.addType(AstBuilder.java:137)
        //     at com.strobel.decompiler.languages.java.JavaLanguage.buildAst(JavaLanguage.java:71)
        //     at com.strobel.decompiler.languages.java.JavaLanguage.decompileType(JavaLanguage.java:59)
        //     at com.strobel.decompiler.DecompilerDriver.decompileType(DecompilerDriver.java:333)
        //     at com.strobel.decompiler.DecompilerDriver.decompileJar(DecompilerDriver.java:254)
        //     at com.strobel.decompiler.DecompilerDriver.main(DecompilerDriver.java:129)
        // 
        throw new IllegalStateException("An error occurred while decompiling this method.");
    }
    
    @Override
    public final void LIZ(final Object o, final View view, final ArrayList<View> list) {
        final 0Dg 0Dg = (0Dg)o;
        final ArrayList<View> lji = 0Dg.LJI;
        lji.clear();
        for (int size = list.size(), i = 0; i < size; ++i) {
            0Ac.LIZ((List<View>)lji, (View)list.get(i));
        }
        lji.add(view);
        list.add(view);
        this.LIZ(0Dg, list);
    }
    
    @Override
    public final void LIZ(final Object o, final Object o2, final ArrayList<View> list, final Object o3, final ArrayList<View> list2, final Object o4, final ArrayList<View> list3) {
        public final class 1gO extends 16Y
        {
            public final /* synthetic */ Object LIZ;
            public final /* synthetic */ ArrayList LIZIZ;
            public final /* synthetic */ Object LIZJ;
            public final /* synthetic */ ArrayList LIZLLL;
            public final /* synthetic */ Object LJ;
            public final /* synthetic */ ArrayList LJFF;
            public final /* synthetic */ d LJI;
            
            static {
                Covode.recordClassIndex(1432);
            }
            
            public 1gO(final d lji, final Object liz, final ArrayList liziz, final Object lizj, final ArrayList lizlll, final Object lj, final ArrayList ljff) {
                this.LJI = lji;
                this.LIZ = liz;
                this.LIZIZ = liziz;
                this.LIZJ = lizj;
                this.LIZLLL = lizlll;
                this.LJ = lj;
                this.LJFF = ljff;
            }
            
            @Override
            public final void LIZ(final 0Dg 0Dg) {
                0Dg.LIZIZ((0Dg.c)this);
            }
            
            @Override
            public final void LIZIZ(final 0Dg 0Dg) {
                final Object liz = this.LIZ;
                if (liz != null) {
                    this.LJI.LIZIZ(liz, this.LIZIZ, null);
                }
                final Object lizj = this.LIZJ;
                if (lizj != null) {
                    this.LJI.LIZIZ(lizj, this.LIZLLL, null);
                }
                final Object lj = this.LJ;
                if (lj != null) {
                    this.LJI.LIZIZ(lj, this.LJFF, null);
                }
            }
        }
        // 
        // This method could not be decompiled.
        // 
        // Original Bytecode:
        // 
        //     1: checkcast       LX/0Dg;
        //     4: new             LX/1gO;
        //     7: dup            
        //     8: aload_0        
        //     9: aload_2        
        //    10: aload_3        
        //    11: aload           4
        //    13: aload           5
        //    15: aload           6
        //    17: aload           7
        //    19: invokespecial   X/1gO.<init>:(Landroidx/p/d;Ljava/lang/Object;Ljava/util/ArrayList;Ljava/lang/Object;Ljava/util/ArrayList;Ljava/lang/Object;Ljava/util/ArrayList;)V
        //    22: invokevirtual   X/0Dg.LIZ:(LX/0Df;)LX/0Dg;
        //    25: pop            
        //    26: return         
        //    Signature:
        //  (Ljava/lang/Object;Ljava/lang/Object;Ljava/util/ArrayList<Landroid/view/View;>;Ljava/lang/Object;Ljava/util/ArrayList<Landroid/view/View;>;Ljava/lang/Object;Ljava/util/ArrayList<Landroid/view/View;>;)V
        // 
        // The error that occurred was:
        // 
        // java.lang.NullPointerException
        //     at com.strobel.decompiler.languages.java.ast.AstBuilder.convertType(AstBuilder.java:419)
        //     at com.strobel.decompiler.languages.java.ast.AstBuilder.convertType(AstBuilder.java:207)
        //     at com.strobel.decompiler.languages.java.ast.AstMethodBodyBuilder.transformCall(AstMethodBodyBuilder.java:1106)
        //     at com.strobel.decompiler.languages.java.ast.AstMethodBodyBuilder.transformByteCode(AstMethodBodyBuilder.java:993)
        //     at com.strobel.decompiler.languages.java.ast.AstMethodBodyBuilder.transformExpression(AstMethodBodyBuilder.java:534)
        //     at com.strobel.decompiler.languages.java.ast.AstMethodBodyBuilder.transformByteCode(AstMethodBodyBuilder.java:548)
        //     at com.strobel.decompiler.languages.java.ast.AstMethodBodyBuilder.transformExpression(AstMethodBodyBuilder.java:534)
        //     at com.strobel.decompiler.languages.java.ast.AstMethodBodyBuilder.transformNode(AstMethodBodyBuilder.java:377)
        //     at com.strobel.decompiler.languages.java.ast.AstMethodBodyBuilder.transformBlock(AstMethodBodyBuilder.java:318)
        //     at com.strobel.decompiler.languages.java.ast.AstMethodBodyBuilder.createMethodBody(AstMethodBodyBuilder.java:213)
        //     at com.strobel.decompiler.languages.java.ast.AstMethodBodyBuilder.createMethodBody(AstMethodBodyBuilder.java:93)
        //     at com.strobel.decompiler.languages.java.ast.AstBuilder.createMethodBody(AstBuilder.java:868)
        //     at com.strobel.decompiler.languages.java.ast.AstBuilder.createMethod(AstBuilder.java:761)
        //     at com.strobel.decompiler.languages.java.ast.AstBuilder.addTypeMembers(AstBuilder.java:638)
        //     at com.strobel.decompiler.languages.java.ast.AstBuilder.createTypeCore(AstBuilder.java:605)
        //     at com.strobel.decompiler.languages.java.ast.AstBuilder.createTypeNoCache(AstBuilder.java:195)
        //     at com.strobel.decompiler.languages.java.ast.AstBuilder.createType(AstBuilder.java:162)
        //     at com.strobel.decompiler.languages.java.ast.AstBuilder.addType(AstBuilder.java:137)
        //     at com.strobel.decompiler.languages.java.JavaLanguage.buildAst(JavaLanguage.java:71)
        //     at com.strobel.decompiler.languages.java.JavaLanguage.decompileType(JavaLanguage.java:59)
        //     at com.strobel.decompiler.DecompilerDriver.decompileType(DecompilerDriver.java:333)
        //     at com.strobel.decompiler.DecompilerDriver.decompileJar(DecompilerDriver.java:254)
        //     at com.strobel.decompiler.DecompilerDriver.main(DecompilerDriver.java:129)
        // 
        throw new IllegalStateException("An error occurred while decompiling this method.");
    }
    
    @Override
    public final void LIZ(final Object o, final ArrayList<View> list) {
        final 0Dg 0Dg = (0Dg)o;
        if (0Dg == null) {
            return;
        }
        final boolean b = 0Dg instanceof 16Z;
        final int n = 0;
        int i = 0;
        if (b) {
            for (16Z 16Z = (16Z)0Dg; i < 16Z.LIZ.size(); ++i) {
                this.LIZ(16Z.LIZIZ(i), list);
            }
            return;
        }
        if (!LIZ(0Dg) && 0Ac.LIZ((List)0Dg.LJI)) {
            for (int size = list.size(), j = n; j < size; ++j) {
                0Dg.LIZIZ((View)list.get(j));
            }
        }
    }
    
    @Override
    public final void LIZ(final Object o, final ArrayList<View> list, final ArrayList<View> list2) {
        final 0Dg 0Dg = (0Dg)o;
        if (0Dg != null) {
            0Dg.LJI.clear();
            0Dg.LJI.addAll((Collection<?>)list2);
            this.LIZIZ(0Dg, list, list2);
        }
    }
    
    @Override
    public final boolean LIZ(final Object o) {
        return o instanceof 0Dg;
    }
    
    @Override
    public final Object LIZIZ(final Object o) {
        0Dg ljff;
        if (o != null) {
            ljff = ((0Dg)o).LJFF();
        }
        else {
            ljff = null;
        }
        return ljff;
    }
    
    @Override
    public final Object LIZIZ(final Object o, Object o2, final Object o3) {
        final 0Dg 0Dg = (0Dg)o;
        final 0Dg 0Dg2 = (0Dg)o2;
        final 0Dg 0Dg3 = (0Dg)o3;
        0Dg 0Dg4;
        if (0Dg != null) {
            0Dg4 = 0Dg;
            if (0Dg2 != null) {
                0Dg4 = new 16Z();
                ((16Z)0Dg4).LIZ(0Dg);
                ((16Z)0Dg4).LIZ(0Dg2);
                ((16Z)0Dg4).LIZ(1);
            }
        }
        else if (0Dg2 != null) {
            0Dg4 = 0Dg2;
        }
        else {
            0Dg4 = null;
        }
        if (0Dg3 != null) {
            o2 = new 16Z();
            if (0Dg4 != null) {
                ((16Z)o2).LIZ(0Dg4);
            }
            ((16Z)o2).LIZ(0Dg3);
            return o2;
        }
        return 0Dg4;
    }
    
    @Override
    public final void LIZIZ(final Object o, final View view) {
        if (o != null) {
            ((0Dg)o).LIZIZ(view);
        }
    }
    
    @Override
    public final void LIZIZ(final Object o, final View view, final ArrayList<View> list) {
        public final class 16T implements c
        {
            public final /* synthetic */ View LIZ;
            public final /* synthetic */ ArrayList LIZIZ;
            
            static {
                Covode.recordClassIndex(1431);
            }
            
            public 16T(final View liz, final ArrayList liziz) {
                this.LIZ = liz;
                this.LIZIZ = liziz;
            }
            
            @Override
            public final void LIZ() {
            }
            
            @Override
            public final void LIZ(final 0Dg 0Dg) {
                0Dg.LIZIZ((0Dg.c)this);
                this.LIZ.setVisibility(8);
                for (int size = this.LIZIZ.size(), i = 0; i < size; ++i) {
                    ((View)this.LIZIZ.get(i)).setVisibility(0);
                }
            }
            
            @Override
            public final void LIZIZ() {
            }
            
            @Override
            public final void LIZIZ(final 0Dg 0Dg) {
            }
            
            @Override
            public final void LIZJ() {
            }
        }
        // 
        // This method could not be decompiled.
        // 
        // Original Bytecode:
        // 
        //     1: checkcast       LX/0Dg;
        //     4: new             LX/16T;
        //     7: dup            
        //     8: aload_2        
        //     9: aload_3        
        //    10: invokespecial   X/16T.<init>:(Landroid/view/View;Ljava/util/ArrayList;)V
        //    13: invokevirtual   X/0Dg.LIZ:(LX/0Df;)LX/0Dg;
        //    16: pop            
        //    17: return         
        //    Signature:
        //  (Ljava/lang/Object;Landroid/view/View;Ljava/util/ArrayList<Landroid/view/View;>;)V
        // 
        // The error that occurred was:
        // 
        // java.lang.NullPointerException
        //     at com.strobel.decompiler.languages.java.ast.AstBuilder.convertType(AstBuilder.java:419)
        //     at com.strobel.decompiler.languages.java.ast.AstBuilder.convertType(AstBuilder.java:207)
        //     at com.strobel.decompiler.languages.java.ast.AstMethodBodyBuilder.transformCall(AstMethodBodyBuilder.java:1106)
        //     at com.strobel.decompiler.languages.java.ast.AstMethodBodyBuilder.transformByteCode(AstMethodBodyBuilder.java:993)
        //     at com.strobel.decompiler.languages.java.ast.AstMethodBodyBuilder.transformExpression(AstMethodBodyBuilder.java:534)
        //     at com.strobel.decompiler.languages.java.ast.AstMethodBodyBuilder.transformByteCode(AstMethodBodyBuilder.java:548)
        //     at com.strobel.decompiler.languages.java.ast.AstMethodBodyBuilder.transformExpression(AstMethodBodyBuilder.java:534)
        //     at com.strobel.decompiler.languages.java.ast.AstMethodBodyBuilder.transformNode(AstMethodBodyBuilder.java:377)
        //     at com.strobel.decompiler.languages.java.ast.AstMethodBodyBuilder.transformBlock(AstMethodBodyBuilder.java:318)
        //     at com.strobel.decompiler.languages.java.ast.AstMethodBodyBuilder.createMethodBody(AstMethodBodyBuilder.java:213)
        //     at com.strobel.decompiler.languages.java.ast.AstMethodBodyBuilder.createMethodBody(AstMethodBodyBuilder.java:93)
        //     at com.strobel.decompiler.languages.java.ast.AstBuilder.createMethodBody(AstBuilder.java:868)
        //     at com.strobel.decompiler.languages.java.ast.AstBuilder.createMethod(AstBuilder.java:761)
        //     at com.strobel.decompiler.languages.java.ast.AstBuilder.addTypeMembers(AstBuilder.java:638)
        //     at com.strobel.decompiler.languages.java.ast.AstBuilder.createTypeCore(AstBuilder.java:605)
        //     at com.strobel.decompiler.languages.java.ast.AstBuilder.createTypeNoCache(AstBuilder.java:195)
        //     at com.strobel.decompiler.languages.java.ast.AstBuilder.createType(AstBuilder.java:162)
        //     at com.strobel.decompiler.languages.java.ast.AstBuilder.addType(AstBuilder.java:137)
        //     at com.strobel.decompiler.languages.java.JavaLanguage.buildAst(JavaLanguage.java:71)
        //     at com.strobel.decompiler.languages.java.JavaLanguage.decompileType(JavaLanguage.java:59)
        //     at com.strobel.decompiler.DecompilerDriver.decompileType(DecompilerDriver.java:333)
        //     at com.strobel.decompiler.DecompilerDriver.decompileJar(DecompilerDriver.java:254)
        //     at com.strobel.decompiler.DecompilerDriver.main(DecompilerDriver.java:129)
        // 
        throw new IllegalStateException("An error occurred while decompiling this method.");
    }
    
    @Override
    public final void LIZIZ(final Object o, final ArrayList<View> list, final ArrayList<View> list2) {
        final 0Dg 0Dg = (0Dg)o;
        final boolean b = 0Dg instanceof 16Z;
        final int n = 0;
        int i = 0;
        if (b) {
            for (16Z 16Z = (16Z)0Dg; i < 16Z.LIZ.size(); ++i) {
                this.LIZIZ(16Z.LIZIZ(i), list, list2);
            }
            return;
        }
        if (!LIZ(0Dg)) {
            final ArrayList<View> lji = 0Dg.LJI;
            if (lji.size() == list.size() && lji.containsAll(list)) {
                if (list2 != null) {
                    for (int size = list2.size(), j = n; j < size; ++j) {
                        0Dg.LIZIZ((View)list2.get(j));
                    }
                }
                for (int k = list.size() - 1; k >= 0; --k) {
                    0Dg.LIZJ((View)list.get(k));
                }
            }
        }
    }
    
    @Override
    public final Object LIZJ(final Object o) {
        if (o == null) {
            return null;
        }
        final 16Z 16Z = new 16Z();
        16Z.LIZ((0Dg)o);
        return 16Z;
    }
    
    @Override
    public final void LIZJ(final Object o, final View view) {
        if (o != null) {
            ((0Dg)o).LIZJ(view);
        }
    }
}
