// 
// Decompiled by Procyon v0.6.0
// 

package com.sendbird.android;

import fc2.i;
import sg2.e;
import java.util.ArrayList;
import bd0.a;
import a4.a0;
import java.util.List;
import java.util.Set;

public final class o3
{
    public static final Set<String> j;
    public final long a;
    public final long b;
    public final String c;
    public final String d;
    public final long e;
    public final List<User> f;
    public long g;
    public long h;
    public long i;
    
    static {
        j = a0.B0("poll_id", "id", "text", "created_by", "created_at", "partial_voter_list", "vote_count", "updated_at", "ts");
        new a() {};
    }
    
    public o3(final long a, final long b, final String c, final String d, final long e, final ArrayList f, final long g, final long h, final long i) {
        this.a = a;
        this.b = b;
        this.c = c;
        this.d = d;
        this.e = e;
        this.f = f;
        this.g = g;
        this.h = h;
        this.i = i;
    }
    
    @Override
    public final boolean equals(final Object o) {
        if (this != o) {
            if (o instanceof o3) {
                final o3 o2 = (o3)o;
                if (this.a == o2.a && this.b == o2.b && sg2.e.a((Object)this.c, (Object)o2.c) && sg2.e.a((Object)this.d, (Object)o2.d) && this.e == o2.e && sg2.e.a((Object)this.f, (Object)o2.f) && this.g == o2.g && this.h == o2.h && this.i == o2.i) {
                    return true;
                }
            }
            return false;
        }
        return true;
    }
    
    @Override
    public final int hashCode() {
        final long a = this.a;
        final int n = (int)(a ^ a >>> 32);
        final long b = this.b;
        final int n2 = (int)(b ^ b >>> 32);
        final String c = this.c;
        int hashCode = 0;
        int hashCode2;
        if (c != null) {
            hashCode2 = c.hashCode();
        }
        else {
            hashCode2 = 0;
        }
        final String d = this.d;
        int hashCode3;
        if (d != null) {
            hashCode3 = d.hashCode();
        }
        else {
            hashCode3 = 0;
        }
        final long e = this.e;
        final int n3 = (int)(e ^ e >>> 32);
        final List<User> f = this.f;
        if (f != null) {
            hashCode = f.hashCode();
        }
        final long g = this.g;
        final int n4 = (int)(g ^ g >>> 32);
        final long h = this.h;
        final int n5 = (int)(h ^ h >>> 32);
        final long i = this.i;
        return (((((((n * 31 + n2) * 31 + hashCode2) * 31 + hashCode3) * 31 + n3) * 31 + hashCode) * 31 + n4) * 31 + n5) * 31 + (int)(i >>> 32 ^ i);
    }
    
    @Override
    public final String toString() {
        final StringBuilder r = a.r("PollOption(pollId=");
        r.append(this.a);
        r.append(", id=");
        r.append(this.b);
        r.append(", text=");
        r.append(this.c);
        r.append(", createdBy=");
        r.append(this.d);
        r.append(", createdAt=");
        r.append(this.e);
        r.append(", partialVoters=");
        r.append(this.f);
        r.append(", _voteCount=");
        r.append(this.g);
        r.append(", _updatedAt=");
        r.append(this.h);
        r.append(", _lastVotedAt=");
        return d.m(r, this.i, ")");
    }
    
    public static final class b
    {
        public static o3 a(final i p0) {
            // 
            // This method could not be decompiled.
            // 
            // Original Bytecode:
            // 
            //     3: astore_1       
            //     4: aload_0        
            //     5: getfield        fc2/i.f:Lcom/sendbird/android/shadow/com/google/gson/internal/LinkedTreeMap;
            //     8: invokevirtual   com/sendbird/android/shadow/com/google/gson/internal/LinkedTreeMap.keySet:()Ljava/util/Set;
            //    11: astore_2       
            //    12: aload_2        
            //    13: ldc             "keySet()"
            //    15: invokestatic    sg2/e.e:(Ljava/lang/Object;Ljava/lang/String;)V
            //    18: aload_1        
            //    19: aload_2        
            //    20: invokestatic    kotlin/collections/CollectionsKt___CollectionsKt.F3:(Ljava/util/Collection;Ljava/util/Collection;)Ljava/util/Set;
            //    23: invokeinterface java/util/Set.isEmpty:()Z
            //    28: ifeq            36
            //    31: aconst_null    
            //    32: astore_0       
            //    33: goto            5376
            //    36: ldc2_w          -1
            //    39: invokestatic    java/lang/Long.valueOf:(J)Ljava/lang/Long;
            //    42: astore_1       
            //    43: aload_0        
            //    44: ldc             "poll_id"
            //    46: invokevirtual   fc2/i.P:(Ljava/lang/String;)Z
            //    49: ifne            55
            //    52: goto            597
            //    55: aload_0        
            //    56: ldc             "poll_id"
            //    58: invokevirtual   fc2/i.L:(Ljava/lang/String;)Lfc2/g;
            //    61: astore_2       
            //    62: aload_2        
            //    63: instanceof      Lfc2/k;
            //    66: ifeq            516
            //    69: aload_0        
            //    70: ldc             "poll_id"
            //    72: invokevirtual   fc2/i.L:(Ljava/lang/String;)Lfc2/g;
            //    75: astore_2       
            //    76: aload_2        
            //    77: ldc             "this[key]"
            //    79: invokestatic    sg2/e.e:(Ljava/lang/Object;Ljava/lang/String;)V
            //    82: ldc             Ljava/lang/Long;.class
            //    84: invokestatic    sg2/h.a:(Ljava/lang/Class;)Lzg2/d;
            //    87: astore_3       
            //    88: aload_3        
            //    89: getstatic       java/lang/Byte.TYPE:Ljava/lang/Class;
            //    92: invokestatic    sg2/h.a:(Ljava/lang/Class;)Lzg2/d;
            //    95: invokestatic    sg2/e.a:(Ljava/lang/Object;Ljava/lang/Object;)Z
            //    98: ifeq            115
            //   101: aload_2        
            //   102: invokevirtual   fc2/g.e:()B
            //   105: invokestatic    java/lang/Byte.valueOf:(B)Ljava/lang/Byte;
            //   108: checkcast       Ljava/lang/Long;
            //   111: astore_2       
            //   112: goto            599
            //   115: aload_3        
            //   116: getstatic       java/lang/Short.TYPE:Ljava/lang/Class;
            //   119: invokestatic    sg2/h.a:(Ljava/lang/Class;)Lzg2/d;
            //   122: invokestatic    sg2/e.a:(Ljava/lang/Object;Ljava/lang/Object;)Z
            //   125: ifeq            142
            //   128: aload_2        
            //   129: invokevirtual   fc2/g.z:()S
            //   132: invokestatic    java/lang/Short.valueOf:(S)Ljava/lang/Short;
            //   135: checkcast       Ljava/lang/Long;
            //   138: astore_2       
            //   139: goto            599
            //   142: aload_3        
            //   143: getstatic       java/lang/Integer.TYPE:Ljava/lang/Class;
            //   146: invokestatic    sg2/h.a:(Ljava/lang/Class;)Lzg2/d;
            //   149: invokestatic    sg2/e.a:(Ljava/lang/Object;Ljava/lang/Object;)Z
            //   152: ifeq            169
            //   155: aload_2        
            //   156: invokevirtual   fc2/g.m:()I
            //   159: invokestatic    java/lang/Integer.valueOf:(I)Ljava/lang/Integer;
            //   162: checkcast       Ljava/lang/Long;
            //   165: astore_2       
            //   166: goto            599
            //   169: aload_3        
            //   170: getstatic       java/lang/Long.TYPE:Ljava/lang/Class;
            //   173: invokestatic    sg2/h.a:(Ljava/lang/Class;)Lzg2/d;
            //   176: invokestatic    sg2/e.a:(Ljava/lang/Object;Ljava/lang/Object;)Z
            //   179: ifeq            193
            //   182: aload_2        
            //   183: invokevirtual   fc2/g.x:()J
            //   186: invokestatic    java/lang/Long.valueOf:(J)Ljava/lang/Long;
            //   189: astore_2       
            //   190: goto            599
            //   193: aload_3        
            //   194: getstatic       java/lang/Float.TYPE:Ljava/lang/Class;
            //   197: invokestatic    sg2/h.a:(Ljava/lang/Class;)Lzg2/d;
            //   200: invokestatic    sg2/e.a:(Ljava/lang/Object;Ljava/lang/Object;)Z
            //   203: ifeq            220
            //   206: aload_2        
            //   207: invokevirtual   fc2/g.l:()F
            //   210: invokestatic    java/lang/Float.valueOf:(F)Ljava/lang/Float;
            //   213: checkcast       Ljava/lang/Long;
            //   216: astore_2       
            //   217: goto            599
            //   220: aload_3        
            //   221: getstatic       java/lang/Double.TYPE:Ljava/lang/Class;
            //   224: invokestatic    sg2/h.a:(Ljava/lang/Class;)Lzg2/d;
            //   227: invokestatic    sg2/e.a:(Ljava/lang/Object;Ljava/lang/Object;)Z
            //   230: ifeq            247
            //   233: aload_2        
            //   234: invokevirtual   fc2/g.k:()D
            //   237: invokestatic    java/lang/Double.valueOf:(D)Ljava/lang/Double;
            //   240: checkcast       Ljava/lang/Long;
            //   243: astore_2       
            //   244: goto            599
            //   247: aload_3        
            //   248: ldc             Ljava/math/BigDecimal;.class
            //   250: invokestatic    sg2/h.a:(Ljava/lang/Class;)Lzg2/d;
            //   253: invokestatic    sg2/e.a:(Ljava/lang/Object;Ljava/lang/Object;)Z
            //   256: ifeq            288
            //   259: aload_2        
            //   260: invokevirtual   fc2/g.a:()Ljava/math/BigDecimal;
            //   263: astore_2       
            //   264: aload_2        
            //   265: ifnull          276
            //   268: aload_2        
            //   269: checkcast       Ljava/lang/Long;
            //   272: astore_2       
            //   273: goto            599
            //   276: new             Ljava/lang/NullPointerException;
            //   279: astore_2       
            //   280: aload_2        
            //   281: ldc             "null cannot be cast to non-null type kotlin.Long"
            //   283: invokespecial   java/lang/NullPointerException.<init>:(Ljava/lang/String;)V
            //   286: aload_2        
            //   287: athrow         
            //   288: aload_3        
            //   289: ldc             Ljava/math/BigInteger;.class
            //   291: invokestatic    sg2/h.a:(Ljava/lang/Class;)Lzg2/d;
            //   294: invokestatic    sg2/e.a:(Ljava/lang/Object;Ljava/lang/Object;)Z
            //   297: ifeq            329
            //   300: aload_2        
            //   301: invokevirtual   fc2/g.c:()Ljava/math/BigInteger;
            //   304: astore_2       
            //   305: aload_2        
            //   306: ifnull          317
            //   309: aload_2        
            //   310: checkcast       Ljava/lang/Long;
            //   313: astore_2       
            //   314: goto            599
            //   317: new             Ljava/lang/NullPointerException;
            //   320: astore_2       
            //   321: aload_2        
            //   322: ldc             "null cannot be cast to non-null type kotlin.Long"
            //   324: invokespecial   java/lang/NullPointerException.<init>:(Ljava/lang/String;)V
            //   327: aload_2        
            //   328: athrow         
            //   329: aload_3        
            //   330: getstatic       java/lang/Character.TYPE:Ljava/lang/Class;
            //   333: invokestatic    sg2/h.a:(Ljava/lang/Class;)Lzg2/d;
            //   336: invokestatic    sg2/e.a:(Ljava/lang/Object;Ljava/lang/Object;)Z
            //   339: ifeq            356
            //   342: aload_2        
            //   343: invokevirtual   fc2/g.i:()C
            //   346: invokestatic    java/lang/Character.valueOf:(C)Ljava/lang/Character;
            //   349: checkcast       Ljava/lang/Long;
            //   352: astore_2       
            //   353: goto            599
            //   356: aload_3        
            //   357: ldc             Ljava/lang/String;.class
            //   359: invokestatic    sg2/h.a:(Ljava/lang/Class;)Lzg2/d;
            //   362: invokestatic    sg2/e.a:(Ljava/lang/Object;Ljava/lang/Object;)Z
            //   365: ifeq            397
            //   368: aload_2        
            //   369: invokevirtual   fc2/g.C:()Ljava/lang/String;
            //   372: astore_2       
            //   373: aload_2        
            //   374: ifnull          385
            //   377: aload_2        
            //   378: checkcast       Ljava/lang/Long;
            //   381: astore_2       
            //   382: goto            599
            //   385: new             Ljava/lang/NullPointerException;
            //   388: astore_2       
            //   389: aload_2        
            //   390: ldc             "null cannot be cast to non-null type kotlin.Long"
            //   392: invokespecial   java/lang/NullPointerException.<init>:(Ljava/lang/String;)V
            //   395: aload_2        
            //   396: athrow         
            //   397: aload_3        
            //   398: getstatic       java/lang/Boolean.TYPE:Ljava/lang/Class;
            //   401: invokestatic    sg2/h.a:(Ljava/lang/Class;)Lzg2/d;
            //   404: invokestatic    sg2/e.a:(Ljava/lang/Object;Ljava/lang/Object;)Z
            //   407: ifeq            424
            //   410: aload_2        
            //   411: invokevirtual   fc2/g.d:()Z
            //   414: invokestatic    java/lang/Boolean.valueOf:(Z)Ljava/lang/Boolean;
            //   417: checkcast       Ljava/lang/Long;
            //   420: astore_2       
            //   421: goto            599
            //   424: aload_3        
            //   425: ldc             Lfc2/i;.class
            //   427: invokestatic    sg2/h.a:(Ljava/lang/Class;)Lzg2/d;
            //   430: invokestatic    sg2/e.a:(Ljava/lang/Object;Ljava/lang/Object;)Z
            //   433: ifeq            447
            //   436: aload_2        
            //   437: invokevirtual   fc2/g.p:()Lfc2/i;
            //   440: checkcast       Ljava/lang/Long;
            //   443: astore_2       
            //   444: goto            599
            //   447: aload_3        
            //   448: ldc             Lfc2/k;.class
            //   450: invokestatic    sg2/h.a:(Ljava/lang/Class;)Lzg2/d;
            //   453: invokestatic    sg2/e.a:(Ljava/lang/Object;Ljava/lang/Object;)Z
            //   456: ifeq            470
            //   459: aload_2        
            //   460: invokevirtual   fc2/g.q:()Lfc2/k;
            //   463: checkcast       Ljava/lang/Long;
            //   466: astore_2       
            //   467: goto            599
            //   470: aload_3        
            //   471: ldc             Lfc2/f;.class
            //   473: invokestatic    sg2/h.a:(Ljava/lang/Class;)Lzg2/d;
            //   476: invokestatic    sg2/e.a:(Ljava/lang/Object;Ljava/lang/Object;)Z
            //   479: ifeq            493
            //   482: aload_2        
            //   483: invokevirtual   fc2/g.n:()Lfc2/f;
            //   486: checkcast       Ljava/lang/Long;
            //   489: astore_2       
            //   490: goto            599
            //   493: aload_3        
            //   494: ldc             Lfc2/h;.class
            //   496: invokestatic    sg2/h.a:(Ljava/lang/Class;)Lzg2/d;
            //   499: invokestatic    sg2/e.a:(Ljava/lang/Object;Ljava/lang/Object;)Z
            //   502: ifeq            597
            //   505: aload_2        
            //   506: invokevirtual   fc2/g.o:()Lfc2/h;
            //   509: checkcast       Ljava/lang/Long;
            //   512: astore_2       
            //   513: goto            599
            //   516: aload_2        
            //   517: instanceof      Lfc2/i;
            //   520: ifeq            554
            //   523: aload_0        
            //   524: ldc             "poll_id"
            //   526: invokevirtual   fc2/i.L:(Ljava/lang/String;)Lfc2/g;
            //   529: astore_2       
            //   530: aload_2        
            //   531: ifnull          542
            //   534: aload_2        
            //   535: checkcast       Ljava/lang/Long;
            //   538: astore_2       
            //   539: goto            599
            //   542: new             Ljava/lang/NullPointerException;
            //   545: astore_2       
            //   546: aload_2        
            //   547: ldc             "null cannot be cast to non-null type kotlin.Long"
            //   549: invokespecial   java/lang/NullPointerException.<init>:(Ljava/lang/String;)V
            //   552: aload_2        
            //   553: athrow         
            //   554: aload_2        
            //   555: instanceof      Lfc2/f;
            //   558: ifeq            597
            //   561: aload_0        
            //   562: ldc             "poll_id"
            //   564: invokevirtual   fc2/i.L:(Ljava/lang/String;)Lfc2/g;
            //   567: astore_2       
            //   568: aload_2        
            //   569: ifnull          580
            //   572: aload_2        
            //   573: checkcast       Ljava/lang/Long;
            //   576: astore_2       
            //   577: goto            599
            //   580: new             Ljava/lang/NullPointerException;
            //   583: astore_2       
            //   584: aload_2        
            //   585: ldc             "null cannot be cast to non-null type kotlin.Long"
            //   587: invokespecial   java/lang/NullPointerException.<init>:(Ljava/lang/String;)V
            //   590: aload_2        
            //   591: athrow         
            //   592: astore_2       
            //   593: aload_2        
            //   594: invokestatic    ec2/a.d:(Ljava/lang/Exception;)V
            //   597: aconst_null    
            //   598: astore_2       
            //   599: aload_2        
            //   600: ifnull          605
            //   603: aload_2        
            //   604: astore_1       
            //   605: aload_1        
            //   606: invokevirtual   java/lang/Number.longValue:()J
            //   609: lstore          4
            //   611: ldc2_w          -1
            //   614: invokestatic    java/lang/Long.valueOf:(J)Ljava/lang/Long;
            //   617: astore_1       
            //   618: aload_0        
            //   619: ldc             "id"
            //   621: invokevirtual   fc2/i.P:(Ljava/lang/String;)Z
            //   624: ifne            630
            //   627: goto            1172
            //   630: aload_0        
            //   631: ldc             "id"
            //   633: invokevirtual   fc2/i.L:(Ljava/lang/String;)Lfc2/g;
            //   636: astore_2       
            //   637: aload_2        
            //   638: instanceof      Lfc2/k;
            //   641: ifeq            1091
            //   644: aload_0        
            //   645: ldc             "id"
            //   647: invokevirtual   fc2/i.L:(Ljava/lang/String;)Lfc2/g;
            //   650: astore_3       
            //   651: aload_3        
            //   652: ldc             "this[key]"
            //   654: invokestatic    sg2/e.e:(Ljava/lang/Object;Ljava/lang/String;)V
            //   657: ldc             Ljava/lang/Long;.class
            //   659: invokestatic    sg2/h.a:(Ljava/lang/Class;)Lzg2/d;
            //   662: astore_2       
            //   663: aload_2        
            //   664: getstatic       java/lang/Byte.TYPE:Ljava/lang/Class;
            //   667: invokestatic    sg2/h.a:(Ljava/lang/Class;)Lzg2/d;
            //   670: invokestatic    sg2/e.a:(Ljava/lang/Object;Ljava/lang/Object;)Z
            //   673: ifeq            690
            //   676: aload_3        
            //   677: invokevirtual   fc2/g.e:()B
            //   680: invokestatic    java/lang/Byte.valueOf:(B)Ljava/lang/Byte;
            //   683: checkcast       Ljava/lang/Long;
            //   686: astore_2       
            //   687: goto            1174
            //   690: aload_2        
            //   691: getstatic       java/lang/Short.TYPE:Ljava/lang/Class;
            //   694: invokestatic    sg2/h.a:(Ljava/lang/Class;)Lzg2/d;
            //   697: invokestatic    sg2/e.a:(Ljava/lang/Object;Ljava/lang/Object;)Z
            //   700: ifeq            717
            //   703: aload_3        
            //   704: invokevirtual   fc2/g.z:()S
            //   707: invokestatic    java/lang/Short.valueOf:(S)Ljava/lang/Short;
            //   710: checkcast       Ljava/lang/Long;
            //   713: astore_2       
            //   714: goto            1174
            //   717: aload_2        
            //   718: getstatic       java/lang/Integer.TYPE:Ljava/lang/Class;
            //   721: invokestatic    sg2/h.a:(Ljava/lang/Class;)Lzg2/d;
            //   724: invokestatic    sg2/e.a:(Ljava/lang/Object;Ljava/lang/Object;)Z
            //   727: ifeq            744
            //   730: aload_3        
            //   731: invokevirtual   fc2/g.m:()I
            //   734: invokestatic    java/lang/Integer.valueOf:(I)Ljava/lang/Integer;
            //   737: checkcast       Ljava/lang/Long;
            //   740: astore_2       
            //   741: goto            1174
            //   744: aload_2        
            //   745: getstatic       java/lang/Long.TYPE:Ljava/lang/Class;
            //   748: invokestatic    sg2/h.a:(Ljava/lang/Class;)Lzg2/d;
            //   751: invokestatic    sg2/e.a:(Ljava/lang/Object;Ljava/lang/Object;)Z
            //   754: ifeq            768
            //   757: aload_3        
            //   758: invokevirtual   fc2/g.x:()J
            //   761: invokestatic    java/lang/Long.valueOf:(J)Ljava/lang/Long;
            //   764: astore_2       
            //   765: goto            1174
            //   768: aload_2        
            //   769: getstatic       java/lang/Float.TYPE:Ljava/lang/Class;
            //   772: invokestatic    sg2/h.a:(Ljava/lang/Class;)Lzg2/d;
            //   775: invokestatic    sg2/e.a:(Ljava/lang/Object;Ljava/lang/Object;)Z
            //   778: ifeq            795
            //   781: aload_3        
            //   782: invokevirtual   fc2/g.l:()F
            //   785: invokestatic    java/lang/Float.valueOf:(F)Ljava/lang/Float;
            //   788: checkcast       Ljava/lang/Long;
            //   791: astore_2       
            //   792: goto            1174
            //   795: aload_2        
            //   796: getstatic       java/lang/Double.TYPE:Ljava/lang/Class;
            //   799: invokestatic    sg2/h.a:(Ljava/lang/Class;)Lzg2/d;
            //   802: invokestatic    sg2/e.a:(Ljava/lang/Object;Ljava/lang/Object;)Z
            //   805: ifeq            822
            //   808: aload_3        
            //   809: invokevirtual   fc2/g.k:()D
            //   812: invokestatic    java/lang/Double.valueOf:(D)Ljava/lang/Double;
            //   815: checkcast       Ljava/lang/Long;
            //   818: astore_2       
            //   819: goto            1174
            //   822: aload_2        
            //   823: ldc             Ljava/math/BigDecimal;.class
            //   825: invokestatic    sg2/h.a:(Ljava/lang/Class;)Lzg2/d;
            //   828: invokestatic    sg2/e.a:(Ljava/lang/Object;Ljava/lang/Object;)Z
            //   831: ifeq            863
            //   834: aload_3        
            //   835: invokevirtual   fc2/g.a:()Ljava/math/BigDecimal;
            //   838: astore_2       
            //   839: aload_2        
            //   840: ifnull          851
            //   843: aload_2        
            //   844: checkcast       Ljava/lang/Long;
            //   847: astore_2       
            //   848: goto            1174
            //   851: new             Ljava/lang/NullPointerException;
            //   854: astore_2       
            //   855: aload_2        
            //   856: ldc             "null cannot be cast to non-null type kotlin.Long"
            //   858: invokespecial   java/lang/NullPointerException.<init>:(Ljava/lang/String;)V
            //   861: aload_2        
            //   862: athrow         
            //   863: aload_2        
            //   864: ldc             Ljava/math/BigInteger;.class
            //   866: invokestatic    sg2/h.a:(Ljava/lang/Class;)Lzg2/d;
            //   869: invokestatic    sg2/e.a:(Ljava/lang/Object;Ljava/lang/Object;)Z
            //   872: ifeq            904
            //   875: aload_3        
            //   876: invokevirtual   fc2/g.c:()Ljava/math/BigInteger;
            //   879: astore_2       
            //   880: aload_2        
            //   881: ifnull          892
            //   884: aload_2        
            //   885: checkcast       Ljava/lang/Long;
            //   888: astore_2       
            //   889: goto            1174
            //   892: new             Ljava/lang/NullPointerException;
            //   895: astore_2       
            //   896: aload_2        
            //   897: ldc             "null cannot be cast to non-null type kotlin.Long"
            //   899: invokespecial   java/lang/NullPointerException.<init>:(Ljava/lang/String;)V
            //   902: aload_2        
            //   903: athrow         
            //   904: aload_2        
            //   905: getstatic       java/lang/Character.TYPE:Ljava/lang/Class;
            //   908: invokestatic    sg2/h.a:(Ljava/lang/Class;)Lzg2/d;
            //   911: invokestatic    sg2/e.a:(Ljava/lang/Object;Ljava/lang/Object;)Z
            //   914: ifeq            931
            //   917: aload_3        
            //   918: invokevirtual   fc2/g.i:()C
            //   921: invokestatic    java/lang/Character.valueOf:(C)Ljava/lang/Character;
            //   924: checkcast       Ljava/lang/Long;
            //   927: astore_2       
            //   928: goto            1174
            //   931: aload_2        
            //   932: ldc             Ljava/lang/String;.class
            //   934: invokestatic    sg2/h.a:(Ljava/lang/Class;)Lzg2/d;
            //   937: invokestatic    sg2/e.a:(Ljava/lang/Object;Ljava/lang/Object;)Z
            //   940: ifeq            972
            //   943: aload_3        
            //   944: invokevirtual   fc2/g.C:()Ljava/lang/String;
            //   947: astore_2       
            //   948: aload_2        
            //   949: ifnull          960
            //   952: aload_2        
            //   953: checkcast       Ljava/lang/Long;
            //   956: astore_2       
            //   957: goto            1174
            //   960: new             Ljava/lang/NullPointerException;
            //   963: astore_2       
            //   964: aload_2        
            //   965: ldc             "null cannot be cast to non-null type kotlin.Long"
            //   967: invokespecial   java/lang/NullPointerException.<init>:(Ljava/lang/String;)V
            //   970: aload_2        
            //   971: athrow         
            //   972: aload_2        
            //   973: getstatic       java/lang/Boolean.TYPE:Ljava/lang/Class;
            //   976: invokestatic    sg2/h.a:(Ljava/lang/Class;)Lzg2/d;
            //   979: invokestatic    sg2/e.a:(Ljava/lang/Object;Ljava/lang/Object;)Z
            //   982: ifeq            999
            //   985: aload_3        
            //   986: invokevirtual   fc2/g.d:()Z
            //   989: invokestatic    java/lang/Boolean.valueOf:(Z)Ljava/lang/Boolean;
            //   992: checkcast       Ljava/lang/Long;
            //   995: astore_2       
            //   996: goto            1174
            //   999: aload_2        
            //  1000: ldc             Lfc2/i;.class
            //  1002: invokestatic    sg2/h.a:(Ljava/lang/Class;)Lzg2/d;
            //  1005: invokestatic    sg2/e.a:(Ljava/lang/Object;Ljava/lang/Object;)Z
            //  1008: ifeq            1022
            //  1011: aload_3        
            //  1012: invokevirtual   fc2/g.p:()Lfc2/i;
            //  1015: checkcast       Ljava/lang/Long;
            //  1018: astore_2       
            //  1019: goto            1174
            //  1022: aload_2        
            //  1023: ldc             Lfc2/k;.class
            //  1025: invokestatic    sg2/h.a:(Ljava/lang/Class;)Lzg2/d;
            //  1028: invokestatic    sg2/e.a:(Ljava/lang/Object;Ljava/lang/Object;)Z
            //  1031: ifeq            1045
            //  1034: aload_3        
            //  1035: invokevirtual   fc2/g.q:()Lfc2/k;
            //  1038: checkcast       Ljava/lang/Long;
            //  1041: astore_2       
            //  1042: goto            1174
            //  1045: aload_2        
            //  1046: ldc             Lfc2/f;.class
            //  1048: invokestatic    sg2/h.a:(Ljava/lang/Class;)Lzg2/d;
            //  1051: invokestatic    sg2/e.a:(Ljava/lang/Object;Ljava/lang/Object;)Z
            //  1054: ifeq            1068
            //  1057: aload_3        
            //  1058: invokevirtual   fc2/g.n:()Lfc2/f;
            //  1061: checkcast       Ljava/lang/Long;
            //  1064: astore_2       
            //  1065: goto            1174
            //  1068: aload_2        
            //  1069: ldc             Lfc2/h;.class
            //  1071: invokestatic    sg2/h.a:(Ljava/lang/Class;)Lzg2/d;
            //  1074: invokestatic    sg2/e.a:(Ljava/lang/Object;Ljava/lang/Object;)Z
            //  1077: ifeq            1172
            //  1080: aload_3        
            //  1081: invokevirtual   fc2/g.o:()Lfc2/h;
            //  1084: checkcast       Ljava/lang/Long;
            //  1087: astore_2       
            //  1088: goto            1174
            //  1091: aload_2        
            //  1092: instanceof      Lfc2/i;
            //  1095: ifeq            1129
            //  1098: aload_0        
            //  1099: ldc             "id"
            //  1101: invokevirtual   fc2/i.L:(Ljava/lang/String;)Lfc2/g;
            //  1104: astore_2       
            //  1105: aload_2        
            //  1106: ifnull          1117
            //  1109: aload_2        
            //  1110: checkcast       Ljava/lang/Long;
            //  1113: astore_2       
            //  1114: goto            1174
            //  1117: new             Ljava/lang/NullPointerException;
            //  1120: astore_2       
            //  1121: aload_2        
            //  1122: ldc             "null cannot be cast to non-null type kotlin.Long"
            //  1124: invokespecial   java/lang/NullPointerException.<init>:(Ljava/lang/String;)V
            //  1127: aload_2        
            //  1128: athrow         
            //  1129: aload_2        
            //  1130: instanceof      Lfc2/f;
            //  1133: ifeq            1172
            //  1136: aload_0        
            //  1137: ldc             "id"
            //  1139: invokevirtual   fc2/i.L:(Ljava/lang/String;)Lfc2/g;
            //  1142: astore_2       
            //  1143: aload_2        
            //  1144: ifnull          1155
            //  1147: aload_2        
            //  1148: checkcast       Ljava/lang/Long;
            //  1151: astore_2       
            //  1152: goto            1174
            //  1155: new             Ljava/lang/NullPointerException;
            //  1158: astore_2       
            //  1159: aload_2        
            //  1160: ldc             "null cannot be cast to non-null type kotlin.Long"
            //  1162: invokespecial   java/lang/NullPointerException.<init>:(Ljava/lang/String;)V
            //  1165: aload_2        
            //  1166: athrow         
            //  1167: astore_2       
            //  1168: aload_2        
            //  1169: invokestatic    ec2/a.d:(Ljava/lang/Exception;)V
            //  1172: aconst_null    
            //  1173: astore_2       
            //  1174: aload_2        
            //  1175: ifnull          1180
            //  1178: aload_2        
            //  1179: astore_1       
            //  1180: aload_1        
            //  1181: invokevirtual   java/lang/Number.longValue:()J
            //  1184: lstore          6
            //  1186: aload_0        
            //  1187: ldc             "text"
            //  1189: invokevirtual   fc2/i.P:(Ljava/lang/String;)Z
            //  1192: ifne            1198
            //  1195: goto            1742
            //  1198: aload_0        
            //  1199: ldc             "text"
            //  1201: invokevirtual   fc2/i.L:(Ljava/lang/String;)Lfc2/g;
            //  1204: astore_2       
            //  1205: aload_2        
            //  1206: instanceof      Lfc2/k;
            //  1209: istore          8
            //  1211: iload           8
            //  1213: ifeq            1661
            //  1216: aload_0        
            //  1217: ldc             "text"
            //  1219: invokevirtual   fc2/i.L:(Ljava/lang/String;)Lfc2/g;
            //  1222: astore_1       
            //  1223: aload_1        
            //  1224: ldc             "this[key]"
            //  1226: invokestatic    sg2/e.e:(Ljava/lang/Object;Ljava/lang/String;)V
            //  1229: ldc             Ljava/lang/String;.class
            //  1231: invokestatic    sg2/h.a:(Ljava/lang/Class;)Lzg2/d;
            //  1234: astore_2       
            //  1235: aload_2        
            //  1236: getstatic       java/lang/Byte.TYPE:Ljava/lang/Class;
            //  1239: invokestatic    sg2/h.a:(Ljava/lang/Class;)Lzg2/d;
            //  1242: invokestatic    sg2/e.a:(Ljava/lang/Object;Ljava/lang/Object;)Z
            //  1245: ifeq            1262
            //  1248: aload_1        
            //  1249: invokevirtual   fc2/g.e:()B
            //  1252: invokestatic    java/lang/Byte.valueOf:(B)Ljava/lang/Byte;
            //  1255: checkcast       Ljava/lang/String;
            //  1258: astore_2       
            //  1259: goto            1744
            //  1262: aload_2        
            //  1263: getstatic       java/lang/Short.TYPE:Ljava/lang/Class;
            //  1266: invokestatic    sg2/h.a:(Ljava/lang/Class;)Lzg2/d;
            //  1269: invokestatic    sg2/e.a:(Ljava/lang/Object;Ljava/lang/Object;)Z
            //  1272: ifeq            1289
            //  1275: aload_1        
            //  1276: invokevirtual   fc2/g.z:()S
            //  1279: invokestatic    java/lang/Short.valueOf:(S)Ljava/lang/Short;
            //  1282: checkcast       Ljava/lang/String;
            //  1285: astore_2       
            //  1286: goto            1744
            //  1289: aload_2        
            //  1290: getstatic       java/lang/Integer.TYPE:Ljava/lang/Class;
            //  1293: invokestatic    sg2/h.a:(Ljava/lang/Class;)Lzg2/d;
            //  1296: invokestatic    sg2/e.a:(Ljava/lang/Object;Ljava/lang/Object;)Z
            //  1299: ifeq            1316
            //  1302: aload_1        
            //  1303: invokevirtual   fc2/g.m:()I
            //  1306: invokestatic    java/lang/Integer.valueOf:(I)Ljava/lang/Integer;
            //  1309: checkcast       Ljava/lang/String;
            //  1312: astore_2       
            //  1313: goto            1744
            //  1316: aload_2        
            //  1317: getstatic       java/lang/Long.TYPE:Ljava/lang/Class;
            //  1320: invokestatic    sg2/h.a:(Ljava/lang/Class;)Lzg2/d;
            //  1323: invokestatic    sg2/e.a:(Ljava/lang/Object;Ljava/lang/Object;)Z
            //  1326: ifeq            1343
            //  1329: aload_1        
            //  1330: invokevirtual   fc2/g.x:()J
            //  1333: invokestatic    java/lang/Long.valueOf:(J)Ljava/lang/Long;
            //  1336: checkcast       Ljava/lang/String;
            //  1339: astore_2       
            //  1340: goto            1744
            //  1343: aload_2        
            //  1344: getstatic       java/lang/Float.TYPE:Ljava/lang/Class;
            //  1347: invokestatic    sg2/h.a:(Ljava/lang/Class;)Lzg2/d;
            //  1350: invokestatic    sg2/e.a:(Ljava/lang/Object;Ljava/lang/Object;)Z
            //  1353: ifeq            1370
            //  1356: aload_1        
            //  1357: invokevirtual   fc2/g.l:()F
            //  1360: invokestatic    java/lang/Float.valueOf:(F)Ljava/lang/Float;
            //  1363: checkcast       Ljava/lang/String;
            //  1366: astore_2       
            //  1367: goto            1744
            //  1370: aload_2        
            //  1371: getstatic       java/lang/Double.TYPE:Ljava/lang/Class;
            //  1374: invokestatic    sg2/h.a:(Ljava/lang/Class;)Lzg2/d;
            //  1377: invokestatic    sg2/e.a:(Ljava/lang/Object;Ljava/lang/Object;)Z
            //  1380: ifeq            1397
            //  1383: aload_1        
            //  1384: invokevirtual   fc2/g.k:()D
            //  1387: invokestatic    java/lang/Double.valueOf:(D)Ljava/lang/Double;
            //  1390: checkcast       Ljava/lang/String;
            //  1393: astore_2       
            //  1394: goto            1744
            //  1397: aload_2        
            //  1398: ldc             Ljava/math/BigDecimal;.class
            //  1400: invokestatic    sg2/h.a:(Ljava/lang/Class;)Lzg2/d;
            //  1403: invokestatic    sg2/e.a:(Ljava/lang/Object;Ljava/lang/Object;)Z
            //  1406: ifeq            1438
            //  1409: aload_1        
            //  1410: invokevirtual   fc2/g.a:()Ljava/math/BigDecimal;
            //  1413: astore_2       
            //  1414: aload_2        
            //  1415: ifnull          1426
            //  1418: aload_2        
            //  1419: checkcast       Ljava/lang/String;
            //  1422: astore_2       
            //  1423: goto            1744
            //  1426: new             Ljava/lang/NullPointerException;
            //  1429: astore_2       
            //  1430: aload_2        
            //  1431: ldc             "null cannot be cast to non-null type kotlin.String"
            //  1433: invokespecial   java/lang/NullPointerException.<init>:(Ljava/lang/String;)V
            //  1436: aload_2        
            //  1437: athrow         
            //  1438: aload_2        
            //  1439: ldc             Ljava/math/BigInteger;.class
            //  1441: invokestatic    sg2/h.a:(Ljava/lang/Class;)Lzg2/d;
            //  1444: invokestatic    sg2/e.a:(Ljava/lang/Object;Ljava/lang/Object;)Z
            //  1447: ifeq            1479
            //  1450: aload_1        
            //  1451: invokevirtual   fc2/g.c:()Ljava/math/BigInteger;
            //  1454: astore_2       
            //  1455: aload_2        
            //  1456: ifnull          1467
            //  1459: aload_2        
            //  1460: checkcast       Ljava/lang/String;
            //  1463: astore_2       
            //  1464: goto            1744
            //  1467: new             Ljava/lang/NullPointerException;
            //  1470: astore_2       
            //  1471: aload_2        
            //  1472: ldc             "null cannot be cast to non-null type kotlin.String"
            //  1474: invokespecial   java/lang/NullPointerException.<init>:(Ljava/lang/String;)V
            //  1477: aload_2        
            //  1478: athrow         
            //  1479: aload_2        
            //  1480: getstatic       java/lang/Character.TYPE:Ljava/lang/Class;
            //  1483: invokestatic    sg2/h.a:(Ljava/lang/Class;)Lzg2/d;
            //  1486: invokestatic    sg2/e.a:(Ljava/lang/Object;Ljava/lang/Object;)Z
            //  1489: ifeq            1506
            //  1492: aload_1        
            //  1493: invokevirtual   fc2/g.i:()C
            //  1496: invokestatic    java/lang/Character.valueOf:(C)Ljava/lang/Character;
            //  1499: checkcast       Ljava/lang/String;
            //  1502: astore_2       
            //  1503: goto            1744
            //  1506: aload_2        
            //  1507: ldc             Ljava/lang/String;.class
            //  1509: invokestatic    sg2/h.a:(Ljava/lang/Class;)Lzg2/d;
            //  1512: invokestatic    sg2/e.a:(Ljava/lang/Object;Ljava/lang/Object;)Z
            //  1515: ifeq            1542
            //  1518: aload_1        
            //  1519: invokevirtual   fc2/g.C:()Ljava/lang/String;
            //  1522: astore_2       
            //  1523: aload_2        
            //  1524: ifnull          1530
            //  1527: goto            1744
            //  1530: new             Ljava/lang/NullPointerException;
            //  1533: astore_2       
            //  1534: aload_2        
            //  1535: ldc             "null cannot be cast to non-null type kotlin.String"
            //  1537: invokespecial   java/lang/NullPointerException.<init>:(Ljava/lang/String;)V
            //  1540: aload_2        
            //  1541: athrow         
            //  1542: aload_2        
            //  1543: getstatic       java/lang/Boolean.TYPE:Ljava/lang/Class;
            //  1546: invokestatic    sg2/h.a:(Ljava/lang/Class;)Lzg2/d;
            //  1549: invokestatic    sg2/e.a:(Ljava/lang/Object;Ljava/lang/Object;)Z
            //  1552: ifeq            1569
            //  1555: aload_1        
            //  1556: invokevirtual   fc2/g.d:()Z
            //  1559: invokestatic    java/lang/Boolean.valueOf:(Z)Ljava/lang/Boolean;
            //  1562: checkcast       Ljava/lang/String;
            //  1565: astore_2       
            //  1566: goto            1744
            //  1569: aload_2        
            //  1570: ldc             Lfc2/i;.class
            //  1572: invokestatic    sg2/h.a:(Ljava/lang/Class;)Lzg2/d;
            //  1575: invokestatic    sg2/e.a:(Ljava/lang/Object;Ljava/lang/Object;)Z
            //  1578: ifeq            1592
            //  1581: aload_1        
            //  1582: invokevirtual   fc2/g.p:()Lfc2/i;
            //  1585: checkcast       Ljava/lang/String;
            //  1588: astore_2       
            //  1589: goto            1744
            //  1592: aload_2        
            //  1593: ldc             Lfc2/k;.class
            //  1595: invokestatic    sg2/h.a:(Ljava/lang/Class;)Lzg2/d;
            //  1598: invokestatic    sg2/e.a:(Ljava/lang/Object;Ljava/lang/Object;)Z
            //  1601: ifeq            1615
            //  1604: aload_1        
            //  1605: invokevirtual   fc2/g.q:()Lfc2/k;
            //  1608: checkcast       Ljava/lang/String;
            //  1611: astore_2       
            //  1612: goto            1744
            //  1615: aload_2        
            //  1616: ldc             Lfc2/f;.class
            //  1618: invokestatic    sg2/h.a:(Ljava/lang/Class;)Lzg2/d;
            //  1621: invokestatic    sg2/e.a:(Ljava/lang/Object;Ljava/lang/Object;)Z
            //  1624: ifeq            1638
            //  1627: aload_1        
            //  1628: invokevirtual   fc2/g.n:()Lfc2/f;
            //  1631: checkcast       Ljava/lang/String;
            //  1634: astore_2       
            //  1635: goto            1744
            //  1638: aload_2        
            //  1639: ldc             Lfc2/h;.class
            //  1641: invokestatic    sg2/h.a:(Ljava/lang/Class;)Lzg2/d;
            //  1644: invokestatic    sg2/e.a:(Ljava/lang/Object;Ljava/lang/Object;)Z
            //  1647: ifeq            1742
            //  1650: aload_1        
            //  1651: invokevirtual   fc2/g.o:()Lfc2/h;
            //  1654: checkcast       Ljava/lang/String;
            //  1657: astore_2       
            //  1658: goto            1744
            //  1661: aload_2        
            //  1662: instanceof      Lfc2/i;
            //  1665: ifeq            1699
            //  1668: aload_0        
            //  1669: ldc             "text"
            //  1671: invokevirtual   fc2/i.L:(Ljava/lang/String;)Lfc2/g;
            //  1674: astore_2       
            //  1675: aload_2        
            //  1676: ifnull          1687
            //  1679: aload_2        
            //  1680: checkcast       Ljava/lang/String;
            //  1683: astore_2       
            //  1684: goto            1744
            //  1687: new             Ljava/lang/NullPointerException;
            //  1690: astore_2       
            //  1691: aload_2        
            //  1692: ldc             "null cannot be cast to non-null type kotlin.String"
            //  1694: invokespecial   java/lang/NullPointerException.<init>:(Ljava/lang/String;)V
            //  1697: aload_2        
            //  1698: athrow         
            //  1699: aload_2        
            //  1700: instanceof      Lfc2/f;
            //  1703: ifeq            1742
            //  1706: aload_0        
            //  1707: ldc             "text"
            //  1709: invokevirtual   fc2/i.L:(Ljava/lang/String;)Lfc2/g;
            //  1712: astore_2       
            //  1713: aload_2        
            //  1714: ifnull          1725
            //  1717: aload_2        
            //  1718: checkcast       Ljava/lang/String;
            //  1721: astore_2       
            //  1722: goto            1744
            //  1725: new             Ljava/lang/NullPointerException;
            //  1728: astore_2       
            //  1729: aload_2        
            //  1730: ldc             "null cannot be cast to non-null type kotlin.String"
            //  1732: invokespecial   java/lang/NullPointerException.<init>:(Ljava/lang/String;)V
            //  1735: aload_2        
            //  1736: athrow         
            //  1737: astore_2       
            //  1738: aload_2        
            //  1739: invokestatic    ec2/a.d:(Ljava/lang/Exception;)V
            //  1742: aconst_null    
            //  1743: astore_2       
            //  1744: aload_2        
            //  1745: ifnull          1753
            //  1748: aload_2        
            //  1749: astore_1       
            //  1750: goto            1756
            //  1753: ldc             "POLL_OPTION_DEFAULT_TEXT"
            //  1755: astore_1       
            //  1756: aload_0        
            //  1757: ldc             "created_by"
            //  1759: invokevirtual   fc2/i.P:(Ljava/lang/String;)Z
            //  1762: ifne            1770
            //  1765: aconst_null    
            //  1766: astore_3       
            //  1767: goto            2226
            //  1770: aload_0        
            //  1771: ldc             "created_by"
            //  1773: invokevirtual   fc2/i.L:(Ljava/lang/String;)Lfc2/g;
            //  1776: astore_2       
            //  1777: aload_2        
            //  1778: instanceof      Lfc2/k;
            //  1781: ifeq            2177
            //  1784: aload_0        
            //  1785: ldc             "created_by"
            //  1787: invokevirtual   fc2/i.L:(Ljava/lang/String;)Lfc2/g;
            //  1790: astore_2       
            //  1791: aload_2        
            //  1792: ldc             "this[key]"
            //  1794: invokestatic    sg2/e.e:(Ljava/lang/Object;Ljava/lang/String;)V
            //  1797: ldc             Ljava/lang/String;.class
            //  1799: invokestatic    sg2/h.a:(Ljava/lang/Class;)Lzg2/d;
            //  1802: astore_3       
            //  1803: aload_3        
            //  1804: getstatic       java/lang/Byte.TYPE:Ljava/lang/Class;
            //  1807: invokestatic    sg2/h.a:(Ljava/lang/Class;)Lzg2/d;
            //  1810: invokestatic    sg2/e.a:(Ljava/lang/Object;Ljava/lang/Object;)Z
            //  1813: ifeq            1830
            //  1816: aload_2        
            //  1817: invokevirtual   fc2/g.e:()B
            //  1820: invokestatic    java/lang/Byte.valueOf:(B)Ljava/lang/Byte;
            //  1823: checkcast       Ljava/lang/String;
            //  1826: astore_2       
            //  1827: goto            2224
            //  1830: aload_3        
            //  1831: getstatic       java/lang/Short.TYPE:Ljava/lang/Class;
            //  1834: invokestatic    sg2/h.a:(Ljava/lang/Class;)Lzg2/d;
            //  1837: invokestatic    sg2/e.a:(Ljava/lang/Object;Ljava/lang/Object;)Z
            //  1840: ifeq            1857
            //  1843: aload_2        
            //  1844: invokevirtual   fc2/g.z:()S
            //  1847: invokestatic    java/lang/Short.valueOf:(S)Ljava/lang/Short;
            //  1850: checkcast       Ljava/lang/String;
            //  1853: astore_2       
            //  1854: goto            2224
            //  1857: aload_3        
            //  1858: getstatic       java/lang/Integer.TYPE:Ljava/lang/Class;
            //  1861: invokestatic    sg2/h.a:(Ljava/lang/Class;)Lzg2/d;
            //  1864: invokestatic    sg2/e.a:(Ljava/lang/Object;Ljava/lang/Object;)Z
            //  1867: ifeq            1884
            //  1870: aload_2        
            //  1871: invokevirtual   fc2/g.m:()I
            //  1874: invokestatic    java/lang/Integer.valueOf:(I)Ljava/lang/Integer;
            //  1877: checkcast       Ljava/lang/String;
            //  1880: astore_2       
            //  1881: goto            2224
            //  1884: aload_3        
            //  1885: getstatic       java/lang/Long.TYPE:Ljava/lang/Class;
            //  1888: invokestatic    sg2/h.a:(Ljava/lang/Class;)Lzg2/d;
            //  1891: invokestatic    sg2/e.a:(Ljava/lang/Object;Ljava/lang/Object;)Z
            //  1894: ifeq            1911
            //  1897: aload_2        
            //  1898: invokevirtual   fc2/g.x:()J
            //  1901: invokestatic    java/lang/Long.valueOf:(J)Ljava/lang/Long;
            //  1904: checkcast       Ljava/lang/String;
            //  1907: astore_2       
            //  1908: goto            2224
            //  1911: aload_3        
            //  1912: getstatic       java/lang/Float.TYPE:Ljava/lang/Class;
            //  1915: invokestatic    sg2/h.a:(Ljava/lang/Class;)Lzg2/d;
            //  1918: invokestatic    sg2/e.a:(Ljava/lang/Object;Ljava/lang/Object;)Z
            //  1921: ifeq            1938
            //  1924: aload_2        
            //  1925: invokevirtual   fc2/g.l:()F
            //  1928: invokestatic    java/lang/Float.valueOf:(F)Ljava/lang/Float;
            //  1931: checkcast       Ljava/lang/String;
            //  1934: astore_2       
            //  1935: goto            2224
            //  1938: aload_3        
            //  1939: getstatic       java/lang/Double.TYPE:Ljava/lang/Class;
            //  1942: invokestatic    sg2/h.a:(Ljava/lang/Class;)Lzg2/d;
            //  1945: invokestatic    sg2/e.a:(Ljava/lang/Object;Ljava/lang/Object;)Z
            //  1948: ifeq            1965
            //  1951: aload_2        
            //  1952: invokevirtual   fc2/g.k:()D
            //  1955: invokestatic    java/lang/Double.valueOf:(D)Ljava/lang/Double;
            //  1958: checkcast       Ljava/lang/String;
            //  1961: astore_2       
            //  1962: goto            2224
            //  1965: aload_3        
            //  1966: ldc             Ljava/math/BigDecimal;.class
            //  1968: invokestatic    sg2/h.a:(Ljava/lang/Class;)Lzg2/d;
            //  1971: invokestatic    sg2/e.a:(Ljava/lang/Object;Ljava/lang/Object;)Z
            //  1974: ifeq            1988
            //  1977: aload_2        
            //  1978: invokevirtual   fc2/g.a:()Ljava/math/BigDecimal;
            //  1981: checkcast       Ljava/lang/String;
            //  1984: astore_2       
            //  1985: goto            2224
            //  1988: aload_3        
            //  1989: ldc             Ljava/math/BigInteger;.class
            //  1991: invokestatic    sg2/h.a:(Ljava/lang/Class;)Lzg2/d;
            //  1994: invokestatic    sg2/e.a:(Ljava/lang/Object;Ljava/lang/Object;)Z
            //  1997: ifeq            2011
            //  2000: aload_2        
            //  2001: invokevirtual   fc2/g.c:()Ljava/math/BigInteger;
            //  2004: checkcast       Ljava/lang/String;
            //  2007: astore_2       
            //  2008: goto            2224
            //  2011: aload_3        
            //  2012: getstatic       java/lang/Character.TYPE:Ljava/lang/Class;
            //  2015: invokestatic    sg2/h.a:(Ljava/lang/Class;)Lzg2/d;
            //  2018: invokestatic    sg2/e.a:(Ljava/lang/Object;Ljava/lang/Object;)Z
            //  2021: ifeq            2038
            //  2024: aload_2        
            //  2025: invokevirtual   fc2/g.i:()C
            //  2028: invokestatic    java/lang/Character.valueOf:(C)Ljava/lang/Character;
            //  2031: checkcast       Ljava/lang/String;
            //  2034: astore_2       
            //  2035: goto            2224
            //  2038: aload_3        
            //  2039: ldc             Ljava/lang/String;.class
            //  2041: invokestatic    sg2/h.a:(Ljava/lang/Class;)Lzg2/d;
            //  2044: invokestatic    sg2/e.a:(Ljava/lang/Object;Ljava/lang/Object;)Z
            //  2047: ifeq            2058
            //  2050: aload_2        
            //  2051: invokevirtual   fc2/g.C:()Ljava/lang/String;
            //  2054: astore_2       
            //  2055: goto            2224
            //  2058: aload_3        
            //  2059: getstatic       java/lang/Boolean.TYPE:Ljava/lang/Class;
            //  2062: invokestatic    sg2/h.a:(Ljava/lang/Class;)Lzg2/d;
            //  2065: invokestatic    sg2/e.a:(Ljava/lang/Object;Ljava/lang/Object;)Z
            //  2068: ifeq            2085
            //  2071: aload_2        
            //  2072: invokevirtual   fc2/g.d:()Z
            //  2075: invokestatic    java/lang/Boolean.valueOf:(Z)Ljava/lang/Boolean;
            //  2078: checkcast       Ljava/lang/String;
            //  2081: astore_2       
            //  2082: goto            2224
            //  2085: aload_3        
            //  2086: ldc             Lfc2/i;.class
            //  2088: invokestatic    sg2/h.a:(Ljava/lang/Class;)Lzg2/d;
            //  2091: invokestatic    sg2/e.a:(Ljava/lang/Object;Ljava/lang/Object;)Z
            //  2094: ifeq            2108
            //  2097: aload_2        
            //  2098: invokevirtual   fc2/g.p:()Lfc2/i;
            //  2101: checkcast       Ljava/lang/String;
            //  2104: astore_2       
            //  2105: goto            2224
            //  2108: aload_3        
            //  2109: ldc             Lfc2/k;.class
            //  2111: invokestatic    sg2/h.a:(Ljava/lang/Class;)Lzg2/d;
            //  2114: invokestatic    sg2/e.a:(Ljava/lang/Object;Ljava/lang/Object;)Z
            //  2117: ifeq            2131
            //  2120: aload_2        
            //  2121: invokevirtual   fc2/g.q:()Lfc2/k;
            //  2124: checkcast       Ljava/lang/String;
            //  2127: astore_2       
            //  2128: goto            2224
            //  2131: aload_3        
            //  2132: ldc             Lfc2/f;.class
            //  2134: invokestatic    sg2/h.a:(Ljava/lang/Class;)Lzg2/d;
            //  2137: invokestatic    sg2/e.a:(Ljava/lang/Object;Ljava/lang/Object;)Z
            //  2140: ifeq            2154
            //  2143: aload_2        
            //  2144: invokevirtual   fc2/g.n:()Lfc2/f;
            //  2147: checkcast       Ljava/lang/String;
            //  2150: astore_2       
            //  2151: goto            2224
            //  2154: aload_3        
            //  2155: ldc             Lfc2/h;.class
            //  2157: invokestatic    sg2/h.a:(Ljava/lang/Class;)Lzg2/d;
            //  2160: invokestatic    sg2/e.a:(Ljava/lang/Object;Ljava/lang/Object;)Z
            //  2163: ifeq            2222
            //  2166: aload_2        
            //  2167: invokevirtual   fc2/g.o:()Lfc2/h;
            //  2170: checkcast       Ljava/lang/String;
            //  2173: astore_2       
            //  2174: goto            2224
            //  2177: aload_2        
            //  2178: instanceof      Lfc2/i;
            //  2181: ifeq            2197
            //  2184: aload_0        
            //  2185: ldc             "created_by"
            //  2187: invokevirtual   fc2/i.L:(Ljava/lang/String;)Lfc2/g;
            //  2190: checkcast       Ljava/lang/String;
            //  2193: astore_2       
            //  2194: goto            2224
            //  2197: aload_2        
            //  2198: instanceof      Lfc2/f;
            //  2201: ifeq            2222
            //  2204: aload_0        
            //  2205: ldc             "created_by"
            //  2207: invokevirtual   fc2/i.L:(Ljava/lang/String;)Lfc2/g;
            //  2210: checkcast       Ljava/lang/String;
            //  2213: astore_2       
            //  2214: goto            2224
            //  2217: astore_2       
            //  2218: aload_2        
            //  2219: invokestatic    ec2/a.d:(Ljava/lang/Exception;)V
            //  2222: aconst_null    
            //  2223: astore_2       
            //  2224: aload_2        
            //  2225: astore_3       
            //  2226: ldc2_w          -1
            //  2229: invokestatic    java/lang/Long.valueOf:(J)Ljava/lang/Long;
            //  2232: astore          9
            //  2234: aload_0        
            //  2235: ldc             "created_at"
            //  2237: invokevirtual   fc2/i.P:(Ljava/lang/String;)Z
            //  2240: ifne            2246
            //  2243: goto            2805
            //  2246: aload_0        
            //  2247: ldc             "created_at"
            //  2249: invokevirtual   fc2/i.L:(Ljava/lang/String;)Lfc2/g;
            //  2252: astore_2       
            //  2253: aload_2        
            //  2254: instanceof      Lfc2/k;
            //  2257: ifeq            2724
            //  2260: aload_0        
            //  2261: ldc             "created_at"
            //  2263: invokevirtual   fc2/i.L:(Ljava/lang/String;)Lfc2/g;
            //  2266: astore          10
            //  2268: aload           10
            //  2270: ldc             "this[key]"
            //  2272: invokestatic    sg2/e.e:(Ljava/lang/Object;Ljava/lang/String;)V
            //  2275: ldc             Ljava/lang/Long;.class
            //  2277: invokestatic    sg2/h.a:(Ljava/lang/Class;)Lzg2/d;
            //  2280: astore_2       
            //  2281: aload_2        
            //  2282: getstatic       java/lang/Byte.TYPE:Ljava/lang/Class;
            //  2285: invokestatic    sg2/h.a:(Ljava/lang/Class;)Lzg2/d;
            //  2288: invokestatic    sg2/e.a:(Ljava/lang/Object;Ljava/lang/Object;)Z
            //  2291: ifeq            2309
            //  2294: aload           10
            //  2296: invokevirtual   fc2/g.e:()B
            //  2299: invokestatic    java/lang/Byte.valueOf:(B)Ljava/lang/Byte;
            //  2302: checkcast       Ljava/lang/Long;
            //  2305: astore_2       
            //  2306: goto            2807
            //  2309: aload_2        
            //  2310: getstatic       java/lang/Short.TYPE:Ljava/lang/Class;
            //  2313: invokestatic    sg2/h.a:(Ljava/lang/Class;)Lzg2/d;
            //  2316: invokestatic    sg2/e.a:(Ljava/lang/Object;Ljava/lang/Object;)Z
            //  2319: ifeq            2337
            //  2322: aload           10
            //  2324: invokevirtual   fc2/g.z:()S
            //  2327: invokestatic    java/lang/Short.valueOf:(S)Ljava/lang/Short;
            //  2330: checkcast       Ljava/lang/Long;
            //  2333: astore_2       
            //  2334: goto            2807
            //  2337: aload_2        
            //  2338: getstatic       java/lang/Integer.TYPE:Ljava/lang/Class;
            //  2341: invokestatic    sg2/h.a:(Ljava/lang/Class;)Lzg2/d;
            //  2344: invokestatic    sg2/e.a:(Ljava/lang/Object;Ljava/lang/Object;)Z
            //  2347: ifeq            2365
            //  2350: aload           10
            //  2352: invokevirtual   fc2/g.m:()I
            //  2355: invokestatic    java/lang/Integer.valueOf:(I)Ljava/lang/Integer;
            //  2358: checkcast       Ljava/lang/Long;
            //  2361: astore_2       
            //  2362: goto            2807
            //  2365: aload_2        
            //  2366: getstatic       java/lang/Long.TYPE:Ljava/lang/Class;
            //  2369: invokestatic    sg2/h.a:(Ljava/lang/Class;)Lzg2/d;
            //  2372: invokestatic    sg2/e.a:(Ljava/lang/Object;Ljava/lang/Object;)Z
            //  2375: ifeq            2390
            //  2378: aload           10
            //  2380: invokevirtual   fc2/g.x:()J
            //  2383: invokestatic    java/lang/Long.valueOf:(J)Ljava/lang/Long;
            //  2386: astore_2       
            //  2387: goto            2807
            //  2390: aload_2        
            //  2391: getstatic       java/lang/Float.TYPE:Ljava/lang/Class;
            //  2394: invokestatic    sg2/h.a:(Ljava/lang/Class;)Lzg2/d;
            //  2397: invokestatic    sg2/e.a:(Ljava/lang/Object;Ljava/lang/Object;)Z
            //  2400: ifeq            2418
            //  2403: aload           10
            //  2405: invokevirtual   fc2/g.l:()F
            //  2408: invokestatic    java/lang/Float.valueOf:(F)Ljava/lang/Float;
            //  2411: checkcast       Ljava/lang/Long;
            //  2414: astore_2       
            //  2415: goto            2807
            //  2418: aload_2        
            //  2419: getstatic       java/lang/Double.TYPE:Ljava/lang/Class;
            //  2422: invokestatic    sg2/h.a:(Ljava/lang/Class;)Lzg2/d;
            //  2425: invokestatic    sg2/e.a:(Ljava/lang/Object;Ljava/lang/Object;)Z
            //  2428: ifeq            2446
            //  2431: aload           10
            //  2433: invokevirtual   fc2/g.k:()D
            //  2436: invokestatic    java/lang/Double.valueOf:(D)Ljava/lang/Double;
            //  2439: checkcast       Ljava/lang/Long;
            //  2442: astore_2       
            //  2443: goto            2807
            //  2446: aload_2        
            //  2447: ldc             Ljava/math/BigDecimal;.class
            //  2449: invokestatic    sg2/h.a:(Ljava/lang/Class;)Lzg2/d;
            //  2452: invokestatic    sg2/e.a:(Ljava/lang/Object;Ljava/lang/Object;)Z
            //  2455: ifeq            2488
            //  2458: aload           10
            //  2460: invokevirtual   fc2/g.a:()Ljava/math/BigDecimal;
            //  2463: astore_2       
            //  2464: aload_2        
            //  2465: ifnull          2476
            //  2468: aload_2        
            //  2469: checkcast       Ljava/lang/Long;
            //  2472: astore_2       
            //  2473: goto            2807
            //  2476: new             Ljava/lang/NullPointerException;
            //  2479: astore_2       
            //  2480: aload_2        
            //  2481: ldc             "null cannot be cast to non-null type kotlin.Long"
            //  2483: invokespecial   java/lang/NullPointerException.<init>:(Ljava/lang/String;)V
            //  2486: aload_2        
            //  2487: athrow         
            //  2488: aload_2        
            //  2489: ldc             Ljava/math/BigInteger;.class
            //  2491: invokestatic    sg2/h.a:(Ljava/lang/Class;)Lzg2/d;
            //  2494: invokestatic    sg2/e.a:(Ljava/lang/Object;Ljava/lang/Object;)Z
            //  2497: ifeq            2530
            //  2500: aload           10
            //  2502: invokevirtual   fc2/g.c:()Ljava/math/BigInteger;
            //  2505: astore_2       
            //  2506: aload_2        
            //  2507: ifnull          2518
            //  2510: aload_2        
            //  2511: checkcast       Ljava/lang/Long;
            //  2514: astore_2       
            //  2515: goto            2807
            //  2518: new             Ljava/lang/NullPointerException;
            //  2521: astore_2       
            //  2522: aload_2        
            //  2523: ldc             "null cannot be cast to non-null type kotlin.Long"
            //  2525: invokespecial   java/lang/NullPointerException.<init>:(Ljava/lang/String;)V
            //  2528: aload_2        
            //  2529: athrow         
            //  2530: aload_2        
            //  2531: getstatic       java/lang/Character.TYPE:Ljava/lang/Class;
            //  2534: invokestatic    sg2/h.a:(Ljava/lang/Class;)Lzg2/d;
            //  2537: invokestatic    sg2/e.a:(Ljava/lang/Object;Ljava/lang/Object;)Z
            //  2540: ifeq            2558
            //  2543: aload           10
            //  2545: invokevirtual   fc2/g.i:()C
            //  2548: invokestatic    java/lang/Character.valueOf:(C)Ljava/lang/Character;
            //  2551: checkcast       Ljava/lang/Long;
            //  2554: astore_2       
            //  2555: goto            2807
            //  2558: aload_2        
            //  2559: ldc             Ljava/lang/String;.class
            //  2561: invokestatic    sg2/h.a:(Ljava/lang/Class;)Lzg2/d;
            //  2564: invokestatic    sg2/e.a:(Ljava/lang/Object;Ljava/lang/Object;)Z
            //  2567: ifeq            2600
            //  2570: aload           10
            //  2572: invokevirtual   fc2/g.C:()Ljava/lang/String;
            //  2575: astore_2       
            //  2576: aload_2        
            //  2577: ifnull          2588
            //  2580: aload_2        
            //  2581: checkcast       Ljava/lang/Long;
            //  2584: astore_2       
            //  2585: goto            2807
            //  2588: new             Ljava/lang/NullPointerException;
            //  2591: astore_2       
            //  2592: aload_2        
            //  2593: ldc             "null cannot be cast to non-null type kotlin.Long"
            //  2595: invokespecial   java/lang/NullPointerException.<init>:(Ljava/lang/String;)V
            //  2598: aload_2        
            //  2599: athrow         
            //  2600: aload_2        
            //  2601: getstatic       java/lang/Boolean.TYPE:Ljava/lang/Class;
            //  2604: invokestatic    sg2/h.a:(Ljava/lang/Class;)Lzg2/d;
            //  2607: invokestatic    sg2/e.a:(Ljava/lang/Object;Ljava/lang/Object;)Z
            //  2610: ifeq            2628
            //  2613: aload           10
            //  2615: invokevirtual   fc2/g.d:()Z
            //  2618: invokestatic    java/lang/Boolean.valueOf:(Z)Ljava/lang/Boolean;
            //  2621: checkcast       Ljava/lang/Long;
            //  2624: astore_2       
            //  2625: goto            2807
            //  2628: aload_2        
            //  2629: ldc             Lfc2/i;.class
            //  2631: invokestatic    sg2/h.a:(Ljava/lang/Class;)Lzg2/d;
            //  2634: invokestatic    sg2/e.a:(Ljava/lang/Object;Ljava/lang/Object;)Z
            //  2637: ifeq            2652
            //  2640: aload           10
            //  2642: invokevirtual   fc2/g.p:()Lfc2/i;
            //  2645: checkcast       Ljava/lang/Long;
            //  2648: astore_2       
            //  2649: goto            2807
            //  2652: aload_2        
            //  2653: ldc             Lfc2/k;.class
            //  2655: invokestatic    sg2/h.a:(Ljava/lang/Class;)Lzg2/d;
            //  2658: invokestatic    sg2/e.a:(Ljava/lang/Object;Ljava/lang/Object;)Z
            //  2661: ifeq            2676
            //  2664: aload           10
            //  2666: invokevirtual   fc2/g.q:()Lfc2/k;
            //  2669: checkcast       Ljava/lang/Long;
            //  2672: astore_2       
            //  2673: goto            2807
            //  2676: aload_2        
            //  2677: ldc             Lfc2/f;.class
            //  2679: invokestatic    sg2/h.a:(Ljava/lang/Class;)Lzg2/d;
            //  2682: invokestatic    sg2/e.a:(Ljava/lang/Object;Ljava/lang/Object;)Z
            //  2685: ifeq            2700
            //  2688: aload           10
            //  2690: invokevirtual   fc2/g.n:()Lfc2/f;
            //  2693: checkcast       Ljava/lang/Long;
            //  2696: astore_2       
            //  2697: goto            2807
            //  2700: aload_2        
            //  2701: ldc             Lfc2/h;.class
            //  2703: invokestatic    sg2/h.a:(Ljava/lang/Class;)Lzg2/d;
            //  2706: invokestatic    sg2/e.a:(Ljava/lang/Object;Ljava/lang/Object;)Z
            //  2709: ifeq            2805
            //  2712: aload           10
            //  2714: invokevirtual   fc2/g.o:()Lfc2/h;
            //  2717: checkcast       Ljava/lang/Long;
            //  2720: astore_2       
            //  2721: goto            2807
            //  2724: aload_2        
            //  2725: instanceof      Lfc2/i;
            //  2728: ifeq            2762
            //  2731: aload_0        
            //  2732: ldc             "created_at"
            //  2734: invokevirtual   fc2/i.L:(Ljava/lang/String;)Lfc2/g;
            //  2737: astore_2       
            //  2738: aload_2        
            //  2739: ifnull          2750
            //  2742: aload_2        
            //  2743: checkcast       Ljava/lang/Long;
            //  2746: astore_2       
            //  2747: goto            2807
            //  2750: new             Ljava/lang/NullPointerException;
            //  2753: astore_2       
            //  2754: aload_2        
            //  2755: ldc             "null cannot be cast to non-null type kotlin.Long"
            //  2757: invokespecial   java/lang/NullPointerException.<init>:(Ljava/lang/String;)V
            //  2760: aload_2        
            //  2761: athrow         
            //  2762: aload_2        
            //  2763: instanceof      Lfc2/f;
            //  2766: ifeq            2805
            //  2769: aload_0        
            //  2770: ldc             "created_at"
            //  2772: invokevirtual   fc2/i.L:(Ljava/lang/String;)Lfc2/g;
            //  2775: astore_2       
            //  2776: aload_2        
            //  2777: ifnull          2788
            //  2780: aload_2        
            //  2781: checkcast       Ljava/lang/Long;
            //  2784: astore_2       
            //  2785: goto            2807
            //  2788: new             Ljava/lang/NullPointerException;
            //  2791: astore_2       
            //  2792: aload_2        
            //  2793: ldc             "null cannot be cast to non-null type kotlin.Long"
            //  2795: invokespecial   java/lang/NullPointerException.<init>:(Ljava/lang/String;)V
            //  2798: aload_2        
            //  2799: athrow         
            //  2800: astore_2       
            //  2801: aload_2        
            //  2802: invokestatic    ec2/a.d:(Ljava/lang/Exception;)V
            //  2805: aconst_null    
            //  2806: astore_2       
            //  2807: aload_2        
            //  2808: ifnull          2814
            //  2811: aload_2        
            //  2812: astore          9
            //  2814: aload           9
            //  2816: invokevirtual   java/lang/Number.longValue:()J
            //  2819: lstore          11
            //  2821: aload_0        
            //  2822: ldc             "partial_voter_list"
            //  2824: invokevirtual   fc2/i.P:(Ljava/lang/String;)Z
            //  2827: ifne            2833
            //  2830: goto            3396
            //  2833: aload_0        
            //  2834: ldc             "partial_voter_list"
            //  2836: invokevirtual   fc2/i.L:(Ljava/lang/String;)Lfc2/g;
            //  2839: astore_2       
            //  2840: aload_2        
            //  2841: instanceof      Lfc2/k;
            //  2844: istore          8
            //  2846: iload           8
            //  2848: ifeq            3315
            //  2851: aload_0        
            //  2852: ldc             "partial_voter_list"
            //  2854: invokevirtual   fc2/i.L:(Ljava/lang/String;)Lfc2/g;
            //  2857: astore          9
            //  2859: aload           9
            //  2861: ldc             "this[key]"
            //  2863: invokestatic    sg2/e.e:(Ljava/lang/Object;Ljava/lang/String;)V
            //  2866: ldc             Lfc2/f;.class
            //  2868: invokestatic    sg2/h.a:(Ljava/lang/Class;)Lzg2/d;
            //  2871: astore_2       
            //  2872: aload_2        
            //  2873: getstatic       java/lang/Byte.TYPE:Ljava/lang/Class;
            //  2876: invokestatic    sg2/h.a:(Ljava/lang/Class;)Lzg2/d;
            //  2879: invokestatic    sg2/e.a:(Ljava/lang/Object;Ljava/lang/Object;)Z
            //  2882: ifeq            2900
            //  2885: aload           9
            //  2887: invokevirtual   fc2/g.e:()B
            //  2890: invokestatic    java/lang/Byte.valueOf:(B)Ljava/lang/Byte;
            //  2893: checkcast       Lfc2/f;
            //  2896: astore_2       
            //  2897: goto            3398
            //  2900: aload_2        
            //  2901: getstatic       java/lang/Short.TYPE:Ljava/lang/Class;
            //  2904: invokestatic    sg2/h.a:(Ljava/lang/Class;)Lzg2/d;
            //  2907: invokestatic    sg2/e.a:(Ljava/lang/Object;Ljava/lang/Object;)Z
            //  2910: ifeq            2928
            //  2913: aload           9
            //  2915: invokevirtual   fc2/g.z:()S
            //  2918: invokestatic    java/lang/Short.valueOf:(S)Ljava/lang/Short;
            //  2921: checkcast       Lfc2/f;
            //  2924: astore_2       
            //  2925: goto            3398
            //  2928: aload_2        
            //  2929: getstatic       java/lang/Integer.TYPE:Ljava/lang/Class;
            //  2932: invokestatic    sg2/h.a:(Ljava/lang/Class;)Lzg2/d;
            //  2935: invokestatic    sg2/e.a:(Ljava/lang/Object;Ljava/lang/Object;)Z
            //  2938: ifeq            2956
            //  2941: aload           9
            //  2943: invokevirtual   fc2/g.m:()I
            //  2946: invokestatic    java/lang/Integer.valueOf:(I)Ljava/lang/Integer;
            //  2949: checkcast       Lfc2/f;
            //  2952: astore_2       
            //  2953: goto            3398
            //  2956: aload_2        
            //  2957: getstatic       java/lang/Long.TYPE:Ljava/lang/Class;
            //  2960: invokestatic    sg2/h.a:(Ljava/lang/Class;)Lzg2/d;
            //  2963: invokestatic    sg2/e.a:(Ljava/lang/Object;Ljava/lang/Object;)Z
            //  2966: ifeq            2984
            //  2969: aload           9
            //  2971: invokevirtual   fc2/g.x:()J
            //  2974: invokestatic    java/lang/Long.valueOf:(J)Ljava/lang/Long;
            //  2977: checkcast       Lfc2/f;
            //  2980: astore_2       
            //  2981: goto            3398
            //  2984: aload_2        
            //  2985: getstatic       java/lang/Float.TYPE:Ljava/lang/Class;
            //  2988: invokestatic    sg2/h.a:(Ljava/lang/Class;)Lzg2/d;
            //  2991: invokestatic    sg2/e.a:(Ljava/lang/Object;Ljava/lang/Object;)Z
            //  2994: ifeq            3012
            //  2997: aload           9
            //  2999: invokevirtual   fc2/g.l:()F
            //  3002: invokestatic    java/lang/Float.valueOf:(F)Ljava/lang/Float;
            //  3005: checkcast       Lfc2/f;
            //  3008: astore_2       
            //  3009: goto            3398
            //  3012: aload_2        
            //  3013: getstatic       java/lang/Double.TYPE:Ljava/lang/Class;
            //  3016: invokestatic    sg2/h.a:(Ljava/lang/Class;)Lzg2/d;
            //  3019: invokestatic    sg2/e.a:(Ljava/lang/Object;Ljava/lang/Object;)Z
            //  3022: ifeq            3040
            //  3025: aload           9
            //  3027: invokevirtual   fc2/g.k:()D
            //  3030: invokestatic    java/lang/Double.valueOf:(D)Ljava/lang/Double;
            //  3033: checkcast       Lfc2/f;
            //  3036: astore_2       
            //  3037: goto            3398
            //  3040: aload_2        
            //  3041: ldc             Ljava/math/BigDecimal;.class
            //  3043: invokestatic    sg2/h.a:(Ljava/lang/Class;)Lzg2/d;
            //  3046: invokestatic    sg2/e.a:(Ljava/lang/Object;Ljava/lang/Object;)Z
            //  3049: ifeq            3082
            //  3052: aload           9
            //  3054: invokevirtual   fc2/g.a:()Ljava/math/BigDecimal;
            //  3057: astore_2       
            //  3058: aload_2        
            //  3059: ifnull          3070
            //  3062: aload_2        
            //  3063: checkcast       Lfc2/f;
            //  3066: astore_2       
            //  3067: goto            3398
            //  3070: new             Ljava/lang/NullPointerException;
            //  3073: astore_2       
            //  3074: aload_2        
            //  3075: ldc             "null cannot be cast to non-null type com.sendbird.android.shadow.com.google.gson.JsonArray"
            //  3077: invokespecial   java/lang/NullPointerException.<init>:(Ljava/lang/String;)V
            //  3080: aload_2        
            //  3081: athrow         
            //  3082: aload_2        
            //  3083: ldc             Ljava/math/BigInteger;.class
            //  3085: invokestatic    sg2/h.a:(Ljava/lang/Class;)Lzg2/d;
            //  3088: invokestatic    sg2/e.a:(Ljava/lang/Object;Ljava/lang/Object;)Z
            //  3091: ifeq            3124
            //  3094: aload           9
            //  3096: invokevirtual   fc2/g.c:()Ljava/math/BigInteger;
            //  3099: astore_2       
            //  3100: aload_2        
            //  3101: ifnull          3112
            //  3104: aload_2        
            //  3105: checkcast       Lfc2/f;
            //  3108: astore_2       
            //  3109: goto            3398
            //  3112: new             Ljava/lang/NullPointerException;
            //  3115: astore_2       
            //  3116: aload_2        
            //  3117: ldc             "null cannot be cast to non-null type com.sendbird.android.shadow.com.google.gson.JsonArray"
            //  3119: invokespecial   java/lang/NullPointerException.<init>:(Ljava/lang/String;)V
            //  3122: aload_2        
            //  3123: athrow         
            //  3124: aload_2        
            //  3125: getstatic       java/lang/Character.TYPE:Ljava/lang/Class;
            //  3128: invokestatic    sg2/h.a:(Ljava/lang/Class;)Lzg2/d;
            //  3131: invokestatic    sg2/e.a:(Ljava/lang/Object;Ljava/lang/Object;)Z
            //  3134: ifeq            3152
            //  3137: aload           9
            //  3139: invokevirtual   fc2/g.i:()C
            //  3142: invokestatic    java/lang/Character.valueOf:(C)Ljava/lang/Character;
            //  3145: checkcast       Lfc2/f;
            //  3148: astore_2       
            //  3149: goto            3398
            //  3152: aload_2        
            //  3153: ldc             Ljava/lang/String;.class
            //  3155: invokestatic    sg2/h.a:(Ljava/lang/Class;)Lzg2/d;
            //  3158: invokestatic    sg2/e.a:(Ljava/lang/Object;Ljava/lang/Object;)Z
            //  3161: ifeq            3194
            //  3164: aload           9
            //  3166: invokevirtual   fc2/g.C:()Ljava/lang/String;
            //  3169: astore_2       
            //  3170: aload_2        
            //  3171: ifnull          3182
            //  3174: aload_2        
            //  3175: checkcast       Lfc2/f;
            //  3178: astore_2       
            //  3179: goto            3398
            //  3182: new             Ljava/lang/NullPointerException;
            //  3185: astore_2       
            //  3186: aload_2        
            //  3187: ldc             "null cannot be cast to non-null type com.sendbird.android.shadow.com.google.gson.JsonArray"
            //  3189: invokespecial   java/lang/NullPointerException.<init>:(Ljava/lang/String;)V
            //  3192: aload_2        
            //  3193: athrow         
            //  3194: aload_2        
            //  3195: getstatic       java/lang/Boolean.TYPE:Ljava/lang/Class;
            //  3198: invokestatic    sg2/h.a:(Ljava/lang/Class;)Lzg2/d;
            //  3201: invokestatic    sg2/e.a:(Ljava/lang/Object;Ljava/lang/Object;)Z
            //  3204: ifeq            3222
            //  3207: aload           9
            //  3209: invokevirtual   fc2/g.d:()Z
            //  3212: invokestatic    java/lang/Boolean.valueOf:(Z)Ljava/lang/Boolean;
            //  3215: checkcast       Lfc2/f;
            //  3218: astore_2       
            //  3219: goto            3398
            //  3222: aload_2        
            //  3223: ldc             Lfc2/i;.class
            //  3225: invokestatic    sg2/h.a:(Ljava/lang/Class;)Lzg2/d;
            //  3228: invokestatic    sg2/e.a:(Ljava/lang/Object;Ljava/lang/Object;)Z
            //  3231: ifeq            3246
            //  3234: aload           9
            //  3236: invokevirtual   fc2/g.p:()Lfc2/i;
            //  3239: checkcast       Lfc2/f;
            //  3242: astore_2       
            //  3243: goto            3398
            //  3246: aload_2        
            //  3247: ldc             Lfc2/k;.class
            //  3249: invokestatic    sg2/h.a:(Ljava/lang/Class;)Lzg2/d;
            //  3252: invokestatic    sg2/e.a:(Ljava/lang/Object;Ljava/lang/Object;)Z
            //  3255: ifeq            3270
            //  3258: aload           9
            //  3260: invokevirtual   fc2/g.q:()Lfc2/k;
            //  3263: checkcast       Lfc2/f;
            //  3266: astore_2       
            //  3267: goto            3398
            //  3270: aload_2        
            //  3271: ldc             Lfc2/f;.class
            //  3273: invokestatic    sg2/h.a:(Ljava/lang/Class;)Lzg2/d;
            //  3276: invokestatic    sg2/e.a:(Ljava/lang/Object;Ljava/lang/Object;)Z
            //  3279: ifeq            3291
            //  3282: aload           9
            //  3284: invokevirtual   fc2/g.n:()Lfc2/f;
            //  3287: astore_2       
            //  3288: goto            3398
            //  3291: aload_2        
            //  3292: ldc             Lfc2/h;.class
            //  3294: invokestatic    sg2/h.a:(Ljava/lang/Class;)Lzg2/d;
            //  3297: invokestatic    sg2/e.a:(Ljava/lang/Object;Ljava/lang/Object;)Z
            //  3300: ifeq            3396
            //  3303: aload           9
            //  3305: invokevirtual   fc2/g.o:()Lfc2/h;
            //  3308: checkcast       Lfc2/f;
            //  3311: astore_2       
            //  3312: goto            3398
            //  3315: aload_2        
            //  3316: instanceof      Lfc2/i;
            //  3319: ifeq            3353
            //  3322: aload_0        
            //  3323: ldc             "partial_voter_list"
            //  3325: invokevirtual   fc2/i.L:(Ljava/lang/String;)Lfc2/g;
            //  3328: astore_2       
            //  3329: aload_2        
            //  3330: ifnull          3341
            //  3333: aload_2        
            //  3334: checkcast       Lfc2/f;
            //  3337: astore_2       
            //  3338: goto            3398
            //  3341: new             Ljava/lang/NullPointerException;
            //  3344: astore_2       
            //  3345: aload_2        
            //  3346: ldc             "null cannot be cast to non-null type com.sendbird.android.shadow.com.google.gson.JsonArray"
            //  3348: invokespecial   java/lang/NullPointerException.<init>:(Ljava/lang/String;)V
            //  3351: aload_2        
            //  3352: athrow         
            //  3353: aload_2        
            //  3354: instanceof      Lfc2/f;
            //  3357: ifeq            3396
            //  3360: aload_0        
            //  3361: ldc             "partial_voter_list"
            //  3363: invokevirtual   fc2/i.L:(Ljava/lang/String;)Lfc2/g;
            //  3366: astore_2       
            //  3367: aload_2        
            //  3368: ifnull          3379
            //  3371: aload_2        
            //  3372: checkcast       Lfc2/f;
            //  3375: astore_2       
            //  3376: goto            3398
            //  3379: new             Ljava/lang/NullPointerException;
            //  3382: astore_2       
            //  3383: aload_2        
            //  3384: ldc             "null cannot be cast to non-null type com.sendbird.android.shadow.com.google.gson.JsonArray"
            //  3386: invokespecial   java/lang/NullPointerException.<init>:(Ljava/lang/String;)V
            //  3389: aload_2        
            //  3390: athrow         
            //  3391: astore_2       
            //  3392: aload_2        
            //  3393: invokestatic    ec2/a.d:(Ljava/lang/Exception;)V
            //  3396: aconst_null    
            //  3397: astore_2       
            //  3398: aload_2        
            //  3399: ifnull          3552
            //  3402: new             Ljava/util/ArrayList;
            //  3405: dup            
            //  3406: invokespecial   java/util/ArrayList.<init>:()V
            //  3409: astore          9
            //  3411: aload_2        
            //  3412: invokevirtual   fc2/f.iterator:()Ljava/util/Iterator;
            //  3415: astore_2       
            //  3416: aload_2        
            //  3417: invokeinterface java/util/Iterator.hasNext:()Z
            //  3422: ifeq            3466
            //  3425: aload_2        
            //  3426: invokeinterface java/util/Iterator.next:()Ljava/lang/Object;
            //  3431: astore          10
            //  3433: aload           10
            //  3435: checkcast       Lfc2/g;
            //  3438: astore          13
            //  3440: aload           13
            //  3442: ldc             "it"
            //  3444: invokestatic    sg2/e.e:(Ljava/lang/Object;Ljava/lang/String;)V
            //  3447: aload           13
            //  3449: invokevirtual   fc2/g.D:()Z
            //  3452: ifeq            3416
            //  3455: aload           9
            //  3457: aload           10
            //  3459: invokevirtual   java/util/ArrayList.add:(Ljava/lang/Object;)Z
            //  3462: pop            
            //  3463: goto            3416
            //  3466: new             Ljava/util/ArrayList;
            //  3469: dup            
            //  3470: invokespecial   java/util/ArrayList.<init>:()V
            //  3473: astore          10
            //  3475: aload           9
            //  3477: invokevirtual   java/util/ArrayList.iterator:()Ljava/util/Iterator;
            //  3480: astore          13
            //  3482: aload           10
            //  3484: astore          9
            //  3486: aload           13
            //  3488: invokeinterface java/util/Iterator.hasNext:()Z
            //  3493: ifeq            3555
            //  3496: aload           13
            //  3498: invokeinterface java/util/Iterator.next:()Ljava/lang/Object;
            //  3503: checkcast       Lfc2/g;
            //  3506: astore          9
            //  3508: new             Lcom/sendbird/android/User;
            //  3511: astore_2       
            //  3512: aload           9
            //  3514: ldc             "it"
            //  3516: invokestatic    sg2/e.e:(Ljava/lang/Object;Ljava/lang/String;)V
            //  3519: aload_2        
            //  3520: aload           9
            //  3522: invokevirtual   fc2/g.p:()Lfc2/i;
            //  3525: invokespecial   com/sendbird/android/User.<init>:(Lfc2/g;)V
            //  3528: goto            3538
            //  3531: astore_2       
            //  3532: aload_2        
            //  3533: invokestatic    ec2/a.d:(Ljava/lang/Exception;)V
            //  3536: aconst_null    
            //  3537: astore_2       
            //  3538: aload_2        
            //  3539: ifnull          3482
            //  3542: aload           10
            //  3544: aload_2        
            //  3545: invokevirtual   java/util/ArrayList.add:(Ljava/lang/Object;)Z
            //  3548: pop            
            //  3549: goto            3482
            //  3552: aconst_null    
            //  3553: astore          9
            //  3555: ldc2_w          -1
            //  3558: invokestatic    java/lang/Long.valueOf:(J)Ljava/lang/Long;
            //  3561: astore          10
            //  3563: aload_0        
            //  3564: ldc_w           "vote_count"
            //  3567: invokevirtual   fc2/i.P:(Ljava/lang/String;)Z
            //  3570: ifne            3576
            //  3573: goto            4139
            //  3576: aload_0        
            //  3577: ldc_w           "vote_count"
            //  3580: invokevirtual   fc2/i.L:(Ljava/lang/String;)Lfc2/g;
            //  3583: astore_2       
            //  3584: aload_2        
            //  3585: instanceof      Lfc2/k;
            //  3588: ifeq            4056
            //  3591: aload_0        
            //  3592: ldc_w           "vote_count"
            //  3595: invokevirtual   fc2/i.L:(Ljava/lang/String;)Lfc2/g;
            //  3598: astore          13
            //  3600: aload           13
            //  3602: ldc             "this[key]"
            //  3604: invokestatic    sg2/e.e:(Ljava/lang/Object;Ljava/lang/String;)V
            //  3607: ldc             Ljava/lang/Long;.class
            //  3609: invokestatic    sg2/h.a:(Ljava/lang/Class;)Lzg2/d;
            //  3612: astore_2       
            //  3613: aload_2        
            //  3614: getstatic       java/lang/Byte.TYPE:Ljava/lang/Class;
            //  3617: invokestatic    sg2/h.a:(Ljava/lang/Class;)Lzg2/d;
            //  3620: invokestatic    sg2/e.a:(Ljava/lang/Object;Ljava/lang/Object;)Z
            //  3623: ifeq            3641
            //  3626: aload           13
            //  3628: invokevirtual   fc2/g.e:()B
            //  3631: invokestatic    java/lang/Byte.valueOf:(B)Ljava/lang/Byte;
            //  3634: checkcast       Ljava/lang/Long;
            //  3637: astore_2       
            //  3638: goto            4141
            //  3641: aload_2        
            //  3642: getstatic       java/lang/Short.TYPE:Ljava/lang/Class;
            //  3645: invokestatic    sg2/h.a:(Ljava/lang/Class;)Lzg2/d;
            //  3648: invokestatic    sg2/e.a:(Ljava/lang/Object;Ljava/lang/Object;)Z
            //  3651: ifeq            3669
            //  3654: aload           13
            //  3656: invokevirtual   fc2/g.z:()S
            //  3659: invokestatic    java/lang/Short.valueOf:(S)Ljava/lang/Short;
            //  3662: checkcast       Ljava/lang/Long;
            //  3665: astore_2       
            //  3666: goto            4141
            //  3669: aload_2        
            //  3670: getstatic       java/lang/Integer.TYPE:Ljava/lang/Class;
            //  3673: invokestatic    sg2/h.a:(Ljava/lang/Class;)Lzg2/d;
            //  3676: invokestatic    sg2/e.a:(Ljava/lang/Object;Ljava/lang/Object;)Z
            //  3679: ifeq            3697
            //  3682: aload           13
            //  3684: invokevirtual   fc2/g.m:()I
            //  3687: invokestatic    java/lang/Integer.valueOf:(I)Ljava/lang/Integer;
            //  3690: checkcast       Ljava/lang/Long;
            //  3693: astore_2       
            //  3694: goto            4141
            //  3697: aload_2        
            //  3698: getstatic       java/lang/Long.TYPE:Ljava/lang/Class;
            //  3701: invokestatic    sg2/h.a:(Ljava/lang/Class;)Lzg2/d;
            //  3704: invokestatic    sg2/e.a:(Ljava/lang/Object;Ljava/lang/Object;)Z
            //  3707: ifeq            3722
            //  3710: aload           13
            //  3712: invokevirtual   fc2/g.x:()J
            //  3715: invokestatic    java/lang/Long.valueOf:(J)Ljava/lang/Long;
            //  3718: astore_2       
            //  3719: goto            4141
            //  3722: aload_2        
            //  3723: getstatic       java/lang/Float.TYPE:Ljava/lang/Class;
            //  3726: invokestatic    sg2/h.a:(Ljava/lang/Class;)Lzg2/d;
            //  3729: invokestatic    sg2/e.a:(Ljava/lang/Object;Ljava/lang/Object;)Z
            //  3732: ifeq            3750
            //  3735: aload           13
            //  3737: invokevirtual   fc2/g.l:()F
            //  3740: invokestatic    java/lang/Float.valueOf:(F)Ljava/lang/Float;
            //  3743: checkcast       Ljava/lang/Long;
            //  3746: astore_2       
            //  3747: goto            4141
            //  3750: aload_2        
            //  3751: getstatic       java/lang/Double.TYPE:Ljava/lang/Class;
            //  3754: invokestatic    sg2/h.a:(Ljava/lang/Class;)Lzg2/d;
            //  3757: invokestatic    sg2/e.a:(Ljava/lang/Object;Ljava/lang/Object;)Z
            //  3760: ifeq            3778
            //  3763: aload           13
            //  3765: invokevirtual   fc2/g.k:()D
            //  3768: invokestatic    java/lang/Double.valueOf:(D)Ljava/lang/Double;
            //  3771: checkcast       Ljava/lang/Long;
            //  3774: astore_2       
            //  3775: goto            4141
            //  3778: aload_2        
            //  3779: ldc             Ljava/math/BigDecimal;.class
            //  3781: invokestatic    sg2/h.a:(Ljava/lang/Class;)Lzg2/d;
            //  3784: invokestatic    sg2/e.a:(Ljava/lang/Object;Ljava/lang/Object;)Z
            //  3787: ifeq            3820
            //  3790: aload           13
            //  3792: invokevirtual   fc2/g.a:()Ljava/math/BigDecimal;
            //  3795: astore_2       
            //  3796: aload_2        
            //  3797: ifnull          3808
            //  3800: aload_2        
            //  3801: checkcast       Ljava/lang/Long;
            //  3804: astore_2       
            //  3805: goto            4141
            //  3808: new             Ljava/lang/NullPointerException;
            //  3811: astore_2       
            //  3812: aload_2        
            //  3813: ldc             "null cannot be cast to non-null type kotlin.Long"
            //  3815: invokespecial   java/lang/NullPointerException.<init>:(Ljava/lang/String;)V
            //  3818: aload_2        
            //  3819: athrow         
            //  3820: aload_2        
            //  3821: ldc             Ljava/math/BigInteger;.class
            //  3823: invokestatic    sg2/h.a:(Ljava/lang/Class;)Lzg2/d;
            //  3826: invokestatic    sg2/e.a:(Ljava/lang/Object;Ljava/lang/Object;)Z
            //  3829: ifeq            3862
            //  3832: aload           13
            //  3834: invokevirtual   fc2/g.c:()Ljava/math/BigInteger;
            //  3837: astore_2       
            //  3838: aload_2        
            //  3839: ifnull          3850
            //  3842: aload_2        
            //  3843: checkcast       Ljava/lang/Long;
            //  3846: astore_2       
            //  3847: goto            4141
            //  3850: new             Ljava/lang/NullPointerException;
            //  3853: astore_2       
            //  3854: aload_2        
            //  3855: ldc             "null cannot be cast to non-null type kotlin.Long"
            //  3857: invokespecial   java/lang/NullPointerException.<init>:(Ljava/lang/String;)V
            //  3860: aload_2        
            //  3861: athrow         
            //  3862: aload_2        
            //  3863: getstatic       java/lang/Character.TYPE:Ljava/lang/Class;
            //  3866: invokestatic    sg2/h.a:(Ljava/lang/Class;)Lzg2/d;
            //  3869: invokestatic    sg2/e.a:(Ljava/lang/Object;Ljava/lang/Object;)Z
            //  3872: ifeq            3890
            //  3875: aload           13
            //  3877: invokevirtual   fc2/g.i:()C
            //  3880: invokestatic    java/lang/Character.valueOf:(C)Ljava/lang/Character;
            //  3883: checkcast       Ljava/lang/Long;
            //  3886: astore_2       
            //  3887: goto            4141
            //  3890: aload_2        
            //  3891: ldc             Ljava/lang/String;.class
            //  3893: invokestatic    sg2/h.a:(Ljava/lang/Class;)Lzg2/d;
            //  3896: invokestatic    sg2/e.a:(Ljava/lang/Object;Ljava/lang/Object;)Z
            //  3899: ifeq            3932
            //  3902: aload           13
            //  3904: invokevirtual   fc2/g.C:()Ljava/lang/String;
            //  3907: astore_2       
            //  3908: aload_2        
            //  3909: ifnull          3920
            //  3912: aload_2        
            //  3913: checkcast       Ljava/lang/Long;
            //  3916: astore_2       
            //  3917: goto            4141
            //  3920: new             Ljava/lang/NullPointerException;
            //  3923: astore_2       
            //  3924: aload_2        
            //  3925: ldc             "null cannot be cast to non-null type kotlin.Long"
            //  3927: invokespecial   java/lang/NullPointerException.<init>:(Ljava/lang/String;)V
            //  3930: aload_2        
            //  3931: athrow         
            //  3932: aload_2        
            //  3933: getstatic       java/lang/Boolean.TYPE:Ljava/lang/Class;
            //  3936: invokestatic    sg2/h.a:(Ljava/lang/Class;)Lzg2/d;
            //  3939: invokestatic    sg2/e.a:(Ljava/lang/Object;Ljava/lang/Object;)Z
            //  3942: ifeq            3960
            //  3945: aload           13
            //  3947: invokevirtual   fc2/g.d:()Z
            //  3950: invokestatic    java/lang/Boolean.valueOf:(Z)Ljava/lang/Boolean;
            //  3953: checkcast       Ljava/lang/Long;
            //  3956: astore_2       
            //  3957: goto            4141
            //  3960: aload_2        
            //  3961: ldc             Lfc2/i;.class
            //  3963: invokestatic    sg2/h.a:(Ljava/lang/Class;)Lzg2/d;
            //  3966: invokestatic    sg2/e.a:(Ljava/lang/Object;Ljava/lang/Object;)Z
            //  3969: ifeq            3984
            //  3972: aload           13
            //  3974: invokevirtual   fc2/g.p:()Lfc2/i;
            //  3977: checkcast       Ljava/lang/Long;
            //  3980: astore_2       
            //  3981: goto            4141
            //  3984: aload_2        
            //  3985: ldc             Lfc2/k;.class
            //  3987: invokestatic    sg2/h.a:(Ljava/lang/Class;)Lzg2/d;
            //  3990: invokestatic    sg2/e.a:(Ljava/lang/Object;Ljava/lang/Object;)Z
            //  3993: ifeq            4008
            //  3996: aload           13
            //  3998: invokevirtual   fc2/g.q:()Lfc2/k;
            //  4001: checkcast       Ljava/lang/Long;
            //  4004: astore_2       
            //  4005: goto            4141
            //  4008: aload_2        
            //  4009: ldc             Lfc2/f;.class
            //  4011: invokestatic    sg2/h.a:(Ljava/lang/Class;)Lzg2/d;
            //  4014: invokestatic    sg2/e.a:(Ljava/lang/Object;Ljava/lang/Object;)Z
            //  4017: ifeq            4032
            //  4020: aload           13
            //  4022: invokevirtual   fc2/g.n:()Lfc2/f;
            //  4025: checkcast       Ljava/lang/Long;
            //  4028: astore_2       
            //  4029: goto            4141
            //  4032: aload_2        
            //  4033: ldc             Lfc2/h;.class
            //  4035: invokestatic    sg2/h.a:(Ljava/lang/Class;)Lzg2/d;
            //  4038: invokestatic    sg2/e.a:(Ljava/lang/Object;Ljava/lang/Object;)Z
            //  4041: ifeq            4139
            //  4044: aload           13
            //  4046: invokevirtual   fc2/g.o:()Lfc2/h;
            //  4049: checkcast       Ljava/lang/Long;
            //  4052: astore_2       
            //  4053: goto            4141
            //  4056: aload_2        
            //  4057: instanceof      Lfc2/i;
            //  4060: ifeq            4095
            //  4063: aload_0        
            //  4064: ldc_w           "vote_count"
            //  4067: invokevirtual   fc2/i.L:(Ljava/lang/String;)Lfc2/g;
            //  4070: astore_2       
            //  4071: aload_2        
            //  4072: ifnull          4083
            //  4075: aload_2        
            //  4076: checkcast       Ljava/lang/Long;
            //  4079: astore_2       
            //  4080: goto            4141
            //  4083: new             Ljava/lang/NullPointerException;
            //  4086: astore_2       
            //  4087: aload_2        
            //  4088: ldc             "null cannot be cast to non-null type kotlin.Long"
            //  4090: invokespecial   java/lang/NullPointerException.<init>:(Ljava/lang/String;)V
            //  4093: aload_2        
            //  4094: athrow         
            //  4095: aload_2        
            //  4096: instanceof      Lfc2/f;
            //  4099: ifeq            4139
            //  4102: aload_0        
            //  4103: ldc_w           "vote_count"
            //  4106: invokevirtual   fc2/i.L:(Ljava/lang/String;)Lfc2/g;
            //  4109: astore_2       
            //  4110: aload_2        
            //  4111: ifnull          4122
            //  4114: aload_2        
            //  4115: checkcast       Ljava/lang/Long;
            //  4118: astore_2       
            //  4119: goto            4141
            //  4122: new             Ljava/lang/NullPointerException;
            //  4125: astore_2       
            //  4126: aload_2        
            //  4127: ldc             "null cannot be cast to non-null type kotlin.Long"
            //  4129: invokespecial   java/lang/NullPointerException.<init>:(Ljava/lang/String;)V
            //  4132: aload_2        
            //  4133: athrow         
            //  4134: astore_2       
            //  4135: aload_2        
            //  4136: invokestatic    ec2/a.d:(Ljava/lang/Exception;)V
            //  4139: aconst_null    
            //  4140: astore_2       
            //  4141: aload_2        
            //  4142: ifnull          4148
            //  4145: aload_2        
            //  4146: astore          10
            //  4148: aload           10
            //  4150: invokevirtual   java/lang/Number.longValue:()J
            //  4153: lstore          14
            //  4155: ldc2_w          -1
            //  4158: invokestatic    java/lang/Long.valueOf:(J)Ljava/lang/Long;
            //  4161: astore          10
            //  4163: aload_0        
            //  4164: ldc_w           "updated_at"
            //  4167: invokevirtual   fc2/i.P:(Ljava/lang/String;)Z
            //  4170: ifne            4176
            //  4173: goto            4739
            //  4176: aload_0        
            //  4177: ldc_w           "updated_at"
            //  4180: invokevirtual   fc2/i.L:(Ljava/lang/String;)Lfc2/g;
            //  4183: astore_2       
            //  4184: aload_2        
            //  4185: instanceof      Lfc2/k;
            //  4188: ifeq            4656
            //  4191: aload_0        
            //  4192: ldc_w           "updated_at"
            //  4195: invokevirtual   fc2/i.L:(Ljava/lang/String;)Lfc2/g;
            //  4198: astore          13
            //  4200: aload           13
            //  4202: ldc             "this[key]"
            //  4204: invokestatic    sg2/e.e:(Ljava/lang/Object;Ljava/lang/String;)V
            //  4207: ldc             Ljava/lang/Long;.class
            //  4209: invokestatic    sg2/h.a:(Ljava/lang/Class;)Lzg2/d;
            //  4212: astore_2       
            //  4213: aload_2        
            //  4214: getstatic       java/lang/Byte.TYPE:Ljava/lang/Class;
            //  4217: invokestatic    sg2/h.a:(Ljava/lang/Class;)Lzg2/d;
            //  4220: invokestatic    sg2/e.a:(Ljava/lang/Object;Ljava/lang/Object;)Z
            //  4223: ifeq            4241
            //  4226: aload           13
            //  4228: invokevirtual   fc2/g.e:()B
            //  4231: invokestatic    java/lang/Byte.valueOf:(B)Ljava/lang/Byte;
            //  4234: checkcast       Ljava/lang/Long;
            //  4237: astore_2       
            //  4238: goto            4741
            //  4241: aload_2        
            //  4242: getstatic       java/lang/Short.TYPE:Ljava/lang/Class;
            //  4245: invokestatic    sg2/h.a:(Ljava/lang/Class;)Lzg2/d;
            //  4248: invokestatic    sg2/e.a:(Ljava/lang/Object;Ljava/lang/Object;)Z
            //  4251: ifeq            4269
            //  4254: aload           13
            //  4256: invokevirtual   fc2/g.z:()S
            //  4259: invokestatic    java/lang/Short.valueOf:(S)Ljava/lang/Short;
            //  4262: checkcast       Ljava/lang/Long;
            //  4265: astore_2       
            //  4266: goto            4741
            //  4269: aload_2        
            //  4270: getstatic       java/lang/Integer.TYPE:Ljava/lang/Class;
            //  4273: invokestatic    sg2/h.a:(Ljava/lang/Class;)Lzg2/d;
            //  4276: invokestatic    sg2/e.a:(Ljava/lang/Object;Ljava/lang/Object;)Z
            //  4279: ifeq            4297
            //  4282: aload           13
            //  4284: invokevirtual   fc2/g.m:()I
            //  4287: invokestatic    java/lang/Integer.valueOf:(I)Ljava/lang/Integer;
            //  4290: checkcast       Ljava/lang/Long;
            //  4293: astore_2       
            //  4294: goto            4741
            //  4297: aload_2        
            //  4298: getstatic       java/lang/Long.TYPE:Ljava/lang/Class;
            //  4301: invokestatic    sg2/h.a:(Ljava/lang/Class;)Lzg2/d;
            //  4304: invokestatic    sg2/e.a:(Ljava/lang/Object;Ljava/lang/Object;)Z
            //  4307: ifeq            4322
            //  4310: aload           13
            //  4312: invokevirtual   fc2/g.x:()J
            //  4315: invokestatic    java/lang/Long.valueOf:(J)Ljava/lang/Long;
            //  4318: astore_2       
            //  4319: goto            4741
            //  4322: aload_2        
            //  4323: getstatic       java/lang/Float.TYPE:Ljava/lang/Class;
            //  4326: invokestatic    sg2/h.a:(Ljava/lang/Class;)Lzg2/d;
            //  4329: invokestatic    sg2/e.a:(Ljava/lang/Object;Ljava/lang/Object;)Z
            //  4332: ifeq            4350
            //  4335: aload           13
            //  4337: invokevirtual   fc2/g.l:()F
            //  4340: invokestatic    java/lang/Float.valueOf:(F)Ljava/lang/Float;
            //  4343: checkcast       Ljava/lang/Long;
            //  4346: astore_2       
            //  4347: goto            4741
            //  4350: aload_2        
            //  4351: getstatic       java/lang/Double.TYPE:Ljava/lang/Class;
            //  4354: invokestatic    sg2/h.a:(Ljava/lang/Class;)Lzg2/d;
            //  4357: invokestatic    sg2/e.a:(Ljava/lang/Object;Ljava/lang/Object;)Z
            //  4360: ifeq            4378
            //  4363: aload           13
            //  4365: invokevirtual   fc2/g.k:()D
            //  4368: invokestatic    java/lang/Double.valueOf:(D)Ljava/lang/Double;
            //  4371: checkcast       Ljava/lang/Long;
            //  4374: astore_2       
            //  4375: goto            4741
            //  4378: aload_2        
            //  4379: ldc             Ljava/math/BigDecimal;.class
            //  4381: invokestatic    sg2/h.a:(Ljava/lang/Class;)Lzg2/d;
            //  4384: invokestatic    sg2/e.a:(Ljava/lang/Object;Ljava/lang/Object;)Z
            //  4387: ifeq            4420
            //  4390: aload           13
            //  4392: invokevirtual   fc2/g.a:()Ljava/math/BigDecimal;
            //  4395: astore_2       
            //  4396: aload_2        
            //  4397: ifnull          4408
            //  4400: aload_2        
            //  4401: checkcast       Ljava/lang/Long;
            //  4404: astore_2       
            //  4405: goto            4741
            //  4408: new             Ljava/lang/NullPointerException;
            //  4411: astore_2       
            //  4412: aload_2        
            //  4413: ldc             "null cannot be cast to non-null type kotlin.Long"
            //  4415: invokespecial   java/lang/NullPointerException.<init>:(Ljava/lang/String;)V
            //  4418: aload_2        
            //  4419: athrow         
            //  4420: aload_2        
            //  4421: ldc             Ljava/math/BigInteger;.class
            //  4423: invokestatic    sg2/h.a:(Ljava/lang/Class;)Lzg2/d;
            //  4426: invokestatic    sg2/e.a:(Ljava/lang/Object;Ljava/lang/Object;)Z
            //  4429: ifeq            4462
            //  4432: aload           13
            //  4434: invokevirtual   fc2/g.c:()Ljava/math/BigInteger;
            //  4437: astore_2       
            //  4438: aload_2        
            //  4439: ifnull          4450
            //  4442: aload_2        
            //  4443: checkcast       Ljava/lang/Long;
            //  4446: astore_2       
            //  4447: goto            4741
            //  4450: new             Ljava/lang/NullPointerException;
            //  4453: astore_2       
            //  4454: aload_2        
            //  4455: ldc             "null cannot be cast to non-null type kotlin.Long"
            //  4457: invokespecial   java/lang/NullPointerException.<init>:(Ljava/lang/String;)V
            //  4460: aload_2        
            //  4461: athrow         
            //  4462: aload_2        
            //  4463: getstatic       java/lang/Character.TYPE:Ljava/lang/Class;
            //  4466: invokestatic    sg2/h.a:(Ljava/lang/Class;)Lzg2/d;
            //  4469: invokestatic    sg2/e.a:(Ljava/lang/Object;Ljava/lang/Object;)Z
            //  4472: ifeq            4490
            //  4475: aload           13
            //  4477: invokevirtual   fc2/g.i:()C
            //  4480: invokestatic    java/lang/Character.valueOf:(C)Ljava/lang/Character;
            //  4483: checkcast       Ljava/lang/Long;
            //  4486: astore_2       
            //  4487: goto            4741
            //  4490: aload_2        
            //  4491: ldc             Ljava/lang/String;.class
            //  4493: invokestatic    sg2/h.a:(Ljava/lang/Class;)Lzg2/d;
            //  4496: invokestatic    sg2/e.a:(Ljava/lang/Object;Ljava/lang/Object;)Z
            //  4499: ifeq            4532
            //  4502: aload           13
            //  4504: invokevirtual   fc2/g.C:()Ljava/lang/String;
            //  4507: astore_2       
            //  4508: aload_2        
            //  4509: ifnull          4520
            //  4512: aload_2        
            //  4513: checkcast       Ljava/lang/Long;
            //  4516: astore_2       
            //  4517: goto            4741
            //  4520: new             Ljava/lang/NullPointerException;
            //  4523: astore_2       
            //  4524: aload_2        
            //  4525: ldc             "null cannot be cast to non-null type kotlin.Long"
            //  4527: invokespecial   java/lang/NullPointerException.<init>:(Ljava/lang/String;)V
            //  4530: aload_2        
            //  4531: athrow         
            //  4532: aload_2        
            //  4533: getstatic       java/lang/Boolean.TYPE:Ljava/lang/Class;
            //  4536: invokestatic    sg2/h.a:(Ljava/lang/Class;)Lzg2/d;
            //  4539: invokestatic    sg2/e.a:(Ljava/lang/Object;Ljava/lang/Object;)Z
            //  4542: ifeq            4560
            //  4545: aload           13
            //  4547: invokevirtual   fc2/g.d:()Z
            //  4550: invokestatic    java/lang/Boolean.valueOf:(Z)Ljava/lang/Boolean;
            //  4553: checkcast       Ljava/lang/Long;
            //  4556: astore_2       
            //  4557: goto            4741
            //  4560: aload_2        
            //  4561: ldc             Lfc2/i;.class
            //  4563: invokestatic    sg2/h.a:(Ljava/lang/Class;)Lzg2/d;
            //  4566: invokestatic    sg2/e.a:(Ljava/lang/Object;Ljava/lang/Object;)Z
            //  4569: ifeq            4584
            //  4572: aload           13
            //  4574: invokevirtual   fc2/g.p:()Lfc2/i;
            //  4577: checkcast       Ljava/lang/Long;
            //  4580: astore_2       
            //  4581: goto            4741
            //  4584: aload_2        
            //  4585: ldc             Lfc2/k;.class
            //  4587: invokestatic    sg2/h.a:(Ljava/lang/Class;)Lzg2/d;
            //  4590: invokestatic    sg2/e.a:(Ljava/lang/Object;Ljava/lang/Object;)Z
            //  4593: ifeq            4608
            //  4596: aload           13
            //  4598: invokevirtual   fc2/g.q:()Lfc2/k;
            //  4601: checkcast       Ljava/lang/Long;
            //  4604: astore_2       
            //  4605: goto            4741
            //  4608: aload_2        
            //  4609: ldc             Lfc2/f;.class
            //  4611: invokestatic    sg2/h.a:(Ljava/lang/Class;)Lzg2/d;
            //  4614: invokestatic    sg2/e.a:(Ljava/lang/Object;Ljava/lang/Object;)Z
            //  4617: ifeq            4632
            //  4620: aload           13
            //  4622: invokevirtual   fc2/g.n:()Lfc2/f;
            //  4625: checkcast       Ljava/lang/Long;
            //  4628: astore_2       
            //  4629: goto            4741
            //  4632: aload_2        
            //  4633: ldc             Lfc2/h;.class
            //  4635: invokestatic    sg2/h.a:(Ljava/lang/Class;)Lzg2/d;
            //  4638: invokestatic    sg2/e.a:(Ljava/lang/Object;Ljava/lang/Object;)Z
            //  4641: ifeq            4739
            //  4644: aload           13
            //  4646: invokevirtual   fc2/g.o:()Lfc2/h;
            //  4649: checkcast       Ljava/lang/Long;
            //  4652: astore_2       
            //  4653: goto            4741
            //  4656: aload_2        
            //  4657: instanceof      Lfc2/i;
            //  4660: ifeq            4695
            //  4663: aload_0        
            //  4664: ldc_w           "updated_at"
            //  4667: invokevirtual   fc2/i.L:(Ljava/lang/String;)Lfc2/g;
            //  4670: astore_2       
            //  4671: aload_2        
            //  4672: ifnull          4683
            //  4675: aload_2        
            //  4676: checkcast       Ljava/lang/Long;
            //  4679: astore_2       
            //  4680: goto            4741
            //  4683: new             Ljava/lang/NullPointerException;
            //  4686: astore_2       
            //  4687: aload_2        
            //  4688: ldc             "null cannot be cast to non-null type kotlin.Long"
            //  4690: invokespecial   java/lang/NullPointerException.<init>:(Ljava/lang/String;)V
            //  4693: aload_2        
            //  4694: athrow         
            //  4695: aload_2        
            //  4696: instanceof      Lfc2/f;
            //  4699: ifeq            4739
            //  4702: aload_0        
            //  4703: ldc_w           "updated_at"
            //  4706: invokevirtual   fc2/i.L:(Ljava/lang/String;)Lfc2/g;
            //  4709: astore_2       
            //  4710: aload_2        
            //  4711: ifnull          4722
            //  4714: aload_2        
            //  4715: checkcast       Ljava/lang/Long;
            //  4718: astore_2       
            //  4719: goto            4741
            //  4722: new             Ljava/lang/NullPointerException;
            //  4725: astore_2       
            //  4726: aload_2        
            //  4727: ldc             "null cannot be cast to non-null type kotlin.Long"
            //  4729: invokespecial   java/lang/NullPointerException.<init>:(Ljava/lang/String;)V
            //  4732: aload_2        
            //  4733: athrow         
            //  4734: astore_2       
            //  4735: aload_2        
            //  4736: invokestatic    ec2/a.d:(Ljava/lang/Exception;)V
            //  4739: aconst_null    
            //  4740: astore_2       
            //  4741: aload_2        
            //  4742: ifnull          4748
            //  4745: aload_2        
            //  4746: astore          10
            //  4748: aload           10
            //  4750: invokevirtual   java/lang/Number.longValue:()J
            //  4753: lstore          16
            //  4755: ldc2_w          -1
            //  4758: invokestatic    java/lang/Long.valueOf:(J)Ljava/lang/Long;
            //  4761: astore_2       
            //  4762: aload_0        
            //  4763: ldc_w           "ts"
            //  4766: invokevirtual   fc2/i.P:(Ljava/lang/String;)Z
            //  4769: ifne            4775
            //  4772: goto            5342
            //  4775: aload_0        
            //  4776: ldc_w           "ts"
            //  4779: invokevirtual   fc2/i.L:(Ljava/lang/String;)Lfc2/g;
            //  4782: astore          10
            //  4784: aload           10
            //  4786: instanceof      Lfc2/k;
            //  4789: ifeq            5257
            //  4792: aload_0        
            //  4793: ldc_w           "ts"
            //  4796: invokevirtual   fc2/i.L:(Ljava/lang/String;)Lfc2/g;
            //  4799: astore          10
            //  4801: aload           10
            //  4803: ldc             "this[key]"
            //  4805: invokestatic    sg2/e.e:(Ljava/lang/Object;Ljava/lang/String;)V
            //  4808: ldc             Ljava/lang/Long;.class
            //  4810: invokestatic    sg2/h.a:(Ljava/lang/Class;)Lzg2/d;
            //  4813: astore_0       
            //  4814: aload_0        
            //  4815: getstatic       java/lang/Byte.TYPE:Ljava/lang/Class;
            //  4818: invokestatic    sg2/h.a:(Ljava/lang/Class;)Lzg2/d;
            //  4821: invokestatic    sg2/e.a:(Ljava/lang/Object;Ljava/lang/Object;)Z
            //  4824: ifeq            4842
            //  4827: aload           10
            //  4829: invokevirtual   fc2/g.e:()B
            //  4832: invokestatic    java/lang/Byte.valueOf:(B)Ljava/lang/Byte;
            //  4835: checkcast       Ljava/lang/Long;
            //  4838: astore_0       
            //  4839: goto            5344
            //  4842: aload_0        
            //  4843: getstatic       java/lang/Short.TYPE:Ljava/lang/Class;
            //  4846: invokestatic    sg2/h.a:(Ljava/lang/Class;)Lzg2/d;
            //  4849: invokestatic    sg2/e.a:(Ljava/lang/Object;Ljava/lang/Object;)Z
            //  4852: ifeq            4870
            //  4855: aload           10
            //  4857: invokevirtual   fc2/g.z:()S
            //  4860: invokestatic    java/lang/Short.valueOf:(S)Ljava/lang/Short;
            //  4863: checkcast       Ljava/lang/Long;
            //  4866: astore_0       
            //  4867: goto            5344
            //  4870: aload_0        
            //  4871: getstatic       java/lang/Integer.TYPE:Ljava/lang/Class;
            //  4874: invokestatic    sg2/h.a:(Ljava/lang/Class;)Lzg2/d;
            //  4877: invokestatic    sg2/e.a:(Ljava/lang/Object;Ljava/lang/Object;)Z
            //  4880: ifeq            4898
            //  4883: aload           10
            //  4885: invokevirtual   fc2/g.m:()I
            //  4888: invokestatic    java/lang/Integer.valueOf:(I)Ljava/lang/Integer;
            //  4891: checkcast       Ljava/lang/Long;
            //  4894: astore_0       
            //  4895: goto            5344
            //  4898: aload_0        
            //  4899: getstatic       java/lang/Long.TYPE:Ljava/lang/Class;
            //  4902: invokestatic    sg2/h.a:(Ljava/lang/Class;)Lzg2/d;
            //  4905: invokestatic    sg2/e.a:(Ljava/lang/Object;Ljava/lang/Object;)Z
            //  4908: ifeq            4923
            //  4911: aload           10
            //  4913: invokevirtual   fc2/g.x:()J
            //  4916: invokestatic    java/lang/Long.valueOf:(J)Ljava/lang/Long;
            //  4919: astore_0       
            //  4920: goto            5344
            //  4923: aload_0        
            //  4924: getstatic       java/lang/Float.TYPE:Ljava/lang/Class;
            //  4927: invokestatic    sg2/h.a:(Ljava/lang/Class;)Lzg2/d;
            //  4930: invokestatic    sg2/e.a:(Ljava/lang/Object;Ljava/lang/Object;)Z
            //  4933: ifeq            4951
            //  4936: aload           10
            //  4938: invokevirtual   fc2/g.l:()F
            //  4941: invokestatic    java/lang/Float.valueOf:(F)Ljava/lang/Float;
            //  4944: checkcast       Ljava/lang/Long;
            //  4947: astore_0       
            //  4948: goto            5344
            //  4951: aload_0        
            //  4952: getstatic       java/lang/Double.TYPE:Ljava/lang/Class;
            //  4955: invokestatic    sg2/h.a:(Ljava/lang/Class;)Lzg2/d;
            //  4958: invokestatic    sg2/e.a:(Ljava/lang/Object;Ljava/lang/Object;)Z
            //  4961: ifeq            4979
            //  4964: aload           10
            //  4966: invokevirtual   fc2/g.k:()D
            //  4969: invokestatic    java/lang/Double.valueOf:(D)Ljava/lang/Double;
            //  4972: checkcast       Ljava/lang/Long;
            //  4975: astore_0       
            //  4976: goto            5344
            //  4979: aload_0        
            //  4980: ldc             Ljava/math/BigDecimal;.class
            //  4982: invokestatic    sg2/h.a:(Ljava/lang/Class;)Lzg2/d;
            //  4985: invokestatic    sg2/e.a:(Ljava/lang/Object;Ljava/lang/Object;)Z
            //  4988: ifeq            5021
            //  4991: aload           10
            //  4993: invokevirtual   fc2/g.a:()Ljava/math/BigDecimal;
            //  4996: astore_0       
            //  4997: aload_0        
            //  4998: ifnull          5009
            //  5001: aload_0        
            //  5002: checkcast       Ljava/lang/Long;
            //  5005: astore_0       
            //  5006: goto            5344
            //  5009: new             Ljava/lang/NullPointerException;
            //  5012: astore_0       
            //  5013: aload_0        
            //  5014: ldc             "null cannot be cast to non-null type kotlin.Long"
            //  5016: invokespecial   java/lang/NullPointerException.<init>:(Ljava/lang/String;)V
            //  5019: aload_0        
            //  5020: athrow         
            //  5021: aload_0        
            //  5022: ldc             Ljava/math/BigInteger;.class
            //  5024: invokestatic    sg2/h.a:(Ljava/lang/Class;)Lzg2/d;
            //  5027: invokestatic    sg2/e.a:(Ljava/lang/Object;Ljava/lang/Object;)Z
            //  5030: ifeq            5063
            //  5033: aload           10
            //  5035: invokevirtual   fc2/g.c:()Ljava/math/BigInteger;
            //  5038: astore_0       
            //  5039: aload_0        
            //  5040: ifnull          5051
            //  5043: aload_0        
            //  5044: checkcast       Ljava/lang/Long;
            //  5047: astore_0       
            //  5048: goto            5344
            //  5051: new             Ljava/lang/NullPointerException;
            //  5054: astore_0       
            //  5055: aload_0        
            //  5056: ldc             "null cannot be cast to non-null type kotlin.Long"
            //  5058: invokespecial   java/lang/NullPointerException.<init>:(Ljava/lang/String;)V
            //  5061: aload_0        
            //  5062: athrow         
            //  5063: aload_0        
            //  5064: getstatic       java/lang/Character.TYPE:Ljava/lang/Class;
            //  5067: invokestatic    sg2/h.a:(Ljava/lang/Class;)Lzg2/d;
            //  5070: invokestatic    sg2/e.a:(Ljava/lang/Object;Ljava/lang/Object;)Z
            //  5073: ifeq            5091
            //  5076: aload           10
            //  5078: invokevirtual   fc2/g.i:()C
            //  5081: invokestatic    java/lang/Character.valueOf:(C)Ljava/lang/Character;
            //  5084: checkcast       Ljava/lang/Long;
            //  5087: astore_0       
            //  5088: goto            5344
            //  5091: aload_0        
            //  5092: ldc             Ljava/lang/String;.class
            //  5094: invokestatic    sg2/h.a:(Ljava/lang/Class;)Lzg2/d;
            //  5097: invokestatic    sg2/e.a:(Ljava/lang/Object;Ljava/lang/Object;)Z
            //  5100: ifeq            5133
            //  5103: aload           10
            //  5105: invokevirtual   fc2/g.C:()Ljava/lang/String;
            //  5108: astore_0       
            //  5109: aload_0        
            //  5110: ifnull          5121
            //  5113: aload_0        
            //  5114: checkcast       Ljava/lang/Long;
            //  5117: astore_0       
            //  5118: goto            5344
            //  5121: new             Ljava/lang/NullPointerException;
            //  5124: astore_0       
            //  5125: aload_0        
            //  5126: ldc             "null cannot be cast to non-null type kotlin.Long"
            //  5128: invokespecial   java/lang/NullPointerException.<init>:(Ljava/lang/String;)V
            //  5131: aload_0        
            //  5132: athrow         
            //  5133: aload_0        
            //  5134: getstatic       java/lang/Boolean.TYPE:Ljava/lang/Class;
            //  5137: invokestatic    sg2/h.a:(Ljava/lang/Class;)Lzg2/d;
            //  5140: invokestatic    sg2/e.a:(Ljava/lang/Object;Ljava/lang/Object;)Z
            //  5143: ifeq            5161
            //  5146: aload           10
            //  5148: invokevirtual   fc2/g.d:()Z
            //  5151: invokestatic    java/lang/Boolean.valueOf:(Z)Ljava/lang/Boolean;
            //  5154: checkcast       Ljava/lang/Long;
            //  5157: astore_0       
            //  5158: goto            5344
            //  5161: aload_0        
            //  5162: ldc             Lfc2/i;.class
            //  5164: invokestatic    sg2/h.a:(Ljava/lang/Class;)Lzg2/d;
            //  5167: invokestatic    sg2/e.a:(Ljava/lang/Object;Ljava/lang/Object;)Z
            //  5170: ifeq            5185
            //  5173: aload           10
            //  5175: invokevirtual   fc2/g.p:()Lfc2/i;
            //  5178: checkcast       Ljava/lang/Long;
            //  5181: astore_0       
            //  5182: goto            5344
            //  5185: aload_0        
            //  5186: ldc             Lfc2/k;.class
            //  5188: invokestatic    sg2/h.a:(Ljava/lang/Class;)Lzg2/d;
            //  5191: invokestatic    sg2/e.a:(Ljava/lang/Object;Ljava/lang/Object;)Z
            //  5194: ifeq            5209
            //  5197: aload           10
            //  5199: invokevirtual   fc2/g.q:()Lfc2/k;
            //  5202: checkcast       Ljava/lang/Long;
            //  5205: astore_0       
            //  5206: goto            5344
            //  5209: aload_0        
            //  5210: ldc             Lfc2/f;.class
            //  5212: invokestatic    sg2/h.a:(Ljava/lang/Class;)Lzg2/d;
            //  5215: invokestatic    sg2/e.a:(Ljava/lang/Object;Ljava/lang/Object;)Z
            //  5218: ifeq            5233
            //  5221: aload           10
            //  5223: invokevirtual   fc2/g.n:()Lfc2/f;
            //  5226: checkcast       Ljava/lang/Long;
            //  5229: astore_0       
            //  5230: goto            5344
            //  5233: aload_0        
            //  5234: ldc             Lfc2/h;.class
            //  5236: invokestatic    sg2/h.a:(Ljava/lang/Class;)Lzg2/d;
            //  5239: invokestatic    sg2/e.a:(Ljava/lang/Object;Ljava/lang/Object;)Z
            //  5242: ifeq            5342
            //  5245: aload           10
            //  5247: invokevirtual   fc2/g.o:()Lfc2/h;
            //  5250: checkcast       Ljava/lang/Long;
            //  5253: astore_0       
            //  5254: goto            5344
            //  5257: aload           10
            //  5259: instanceof      Lfc2/i;
            //  5262: ifeq            5297
            //  5265: aload_0        
            //  5266: ldc_w           "ts"
            //  5269: invokevirtual   fc2/i.L:(Ljava/lang/String;)Lfc2/g;
            //  5272: astore_0       
            //  5273: aload_0        
            //  5274: ifnull          5285
            //  5277: aload_0        
            //  5278: checkcast       Ljava/lang/Long;
            //  5281: astore_0       
            //  5282: goto            5344
            //  5285: new             Ljava/lang/NullPointerException;
            //  5288: astore_0       
            //  5289: aload_0        
            //  5290: ldc             "null cannot be cast to non-null type kotlin.Long"
            //  5292: invokespecial   java/lang/NullPointerException.<init>:(Ljava/lang/String;)V
            //  5295: aload_0        
            //  5296: athrow         
            //  5297: aload           10
            //  5299: instanceof      Lfc2/f;
            //  5302: ifeq            5342
            //  5305: aload_0        
            //  5306: ldc_w           "ts"
            //  5309: invokevirtual   fc2/i.L:(Ljava/lang/String;)Lfc2/g;
            //  5312: astore_0       
            //  5313: aload_0        
            //  5314: ifnull          5325
            //  5317: aload_0        
            //  5318: checkcast       Ljava/lang/Long;
            //  5321: astore_0       
            //  5322: goto            5344
            //  5325: new             Ljava/lang/NullPointerException;
            //  5328: astore_0       
            //  5329: aload_0        
            //  5330: ldc             "null cannot be cast to non-null type kotlin.Long"
            //  5332: invokespecial   java/lang/NullPointerException.<init>:(Ljava/lang/String;)V
            //  5335: aload_0        
            //  5336: athrow         
            //  5337: astore_0       
            //  5338: aload_0        
            //  5339: invokestatic    ec2/a.d:(Ljava/lang/Exception;)V
            //  5342: aconst_null    
            //  5343: astore_0       
            //  5344: aload_0        
            //  5345: ifnull          5350
            //  5348: aload_0        
            //  5349: astore_2       
            //  5350: new             Lcom/sendbird/android/o3;
            //  5353: dup            
            //  5354: lload           4
            //  5356: lload           6
            //  5358: aload_1        
            //  5359: aload_3        
            //  5360: lload           11
            //  5362: aload           9
            //  5364: lload           14
            //  5366: lload           16
            //  5368: aload_2        
            //  5369: invokevirtual   java/lang/Number.longValue:()J
            //  5372: invokespecial   com/sendbird/android/o3.<init>:(JJLjava/lang/String;Ljava/lang/String;JLjava/util/ArrayList;JJJ)V
            //  5375: astore_0       
            //  5376: aload_0        
            //  5377: areturn        
            //  5378: astore_2       
            //  5379: goto            597
            //  5382: astore_2       
            //  5383: goto            1172
            //  5386: astore_2       
            //  5387: goto            1742
            //  5390: astore_2       
            //  5391: goto            2222
            //  5394: astore_2       
            //  5395: goto            2805
            //  5398: astore_2       
            //  5399: goto            3396
            //  5402: astore_2       
            //  5403: goto            4139
            //  5406: astore_2       
            //  5407: goto            4739
            //  5410: astore_0       
            //  5411: goto            5342
            //    Exceptions:
            //  Try           Handler
            //  Start  End    Start  End    Type                                    
            //  -----  -----  -----  -----  ----------------------------------------
            //  55     82     592    597    Ljava/lang/Exception;
            //  82     112    5378   5382   Ljava/lang/Exception;
            //  115    139    5378   5382   Ljava/lang/Exception;
            //  142    166    5378   5382   Ljava/lang/Exception;
            //  169    190    5378   5382   Ljava/lang/Exception;
            //  193    217    5378   5382   Ljava/lang/Exception;
            //  220    244    5378   5382   Ljava/lang/Exception;
            //  247    264    5378   5382   Ljava/lang/Exception;
            //  268    273    5378   5382   Ljava/lang/Exception;
            //  276    288    5378   5382   Ljava/lang/Exception;
            //  288    305    5378   5382   Ljava/lang/Exception;
            //  309    314    5378   5382   Ljava/lang/Exception;
            //  317    329    5378   5382   Ljava/lang/Exception;
            //  329    353    5378   5382   Ljava/lang/Exception;
            //  356    373    5378   5382   Ljava/lang/Exception;
            //  377    382    5378   5382   Ljava/lang/Exception;
            //  385    397    5378   5382   Ljava/lang/Exception;
            //  397    421    5378   5382   Ljava/lang/Exception;
            //  424    444    5378   5382   Ljava/lang/Exception;
            //  447    467    5378   5382   Ljava/lang/Exception;
            //  470    490    5378   5382   Ljava/lang/Exception;
            //  493    513    5378   5382   Ljava/lang/Exception;
            //  516    530    592    597    Ljava/lang/Exception;
            //  534    539    592    597    Ljava/lang/Exception;
            //  542    554    592    597    Ljava/lang/Exception;
            //  554    568    592    597    Ljava/lang/Exception;
            //  572    577    592    597    Ljava/lang/Exception;
            //  580    592    592    597    Ljava/lang/Exception;
            //  630    657    1167   1172   Ljava/lang/Exception;
            //  657    687    5382   5386   Ljava/lang/Exception;
            //  690    714    5382   5386   Ljava/lang/Exception;
            //  717    741    5382   5386   Ljava/lang/Exception;
            //  744    765    5382   5386   Ljava/lang/Exception;
            //  768    792    5382   5386   Ljava/lang/Exception;
            //  795    819    5382   5386   Ljava/lang/Exception;
            //  822    839    5382   5386   Ljava/lang/Exception;
            //  843    848    5382   5386   Ljava/lang/Exception;
            //  851    863    5382   5386   Ljava/lang/Exception;
            //  863    880    5382   5386   Ljava/lang/Exception;
            //  884    889    5382   5386   Ljava/lang/Exception;
            //  892    904    5382   5386   Ljava/lang/Exception;
            //  904    928    5382   5386   Ljava/lang/Exception;
            //  931    948    5382   5386   Ljava/lang/Exception;
            //  952    957    5382   5386   Ljava/lang/Exception;
            //  960    972    5382   5386   Ljava/lang/Exception;
            //  972    996    5382   5386   Ljava/lang/Exception;
            //  999    1019   5382   5386   Ljava/lang/Exception;
            //  1022   1042   5382   5386   Ljava/lang/Exception;
            //  1045   1065   5382   5386   Ljava/lang/Exception;
            //  1068   1088   5382   5386   Ljava/lang/Exception;
            //  1091   1105   1167   1172   Ljava/lang/Exception;
            //  1109   1114   1167   1172   Ljava/lang/Exception;
            //  1117   1129   1167   1172   Ljava/lang/Exception;
            //  1129   1143   1167   1172   Ljava/lang/Exception;
            //  1147   1152   1167   1172   Ljava/lang/Exception;
            //  1155   1167   1167   1172   Ljava/lang/Exception;
            //  1198   1211   1737   1742   Ljava/lang/Exception;
            //  1216   1229   1737   1742   Ljava/lang/Exception;
            //  1229   1259   5386   5390   Ljava/lang/Exception;
            //  1262   1286   5386   5390   Ljava/lang/Exception;
            //  1289   1313   5386   5390   Ljava/lang/Exception;
            //  1316   1340   5386   5390   Ljava/lang/Exception;
            //  1343   1367   5386   5390   Ljava/lang/Exception;
            //  1370   1394   5386   5390   Ljava/lang/Exception;
            //  1397   1414   5386   5390   Ljava/lang/Exception;
            //  1418   1423   5386   5390   Ljava/lang/Exception;
            //  1426   1438   5386   5390   Ljava/lang/Exception;
            //  1438   1455   5386   5390   Ljava/lang/Exception;
            //  1459   1464   5386   5390   Ljava/lang/Exception;
            //  1467   1479   5386   5390   Ljava/lang/Exception;
            //  1479   1503   5386   5390   Ljava/lang/Exception;
            //  1506   1523   5386   5390   Ljava/lang/Exception;
            //  1530   1542   5386   5390   Ljava/lang/Exception;
            //  1542   1566   5386   5390   Ljava/lang/Exception;
            //  1569   1589   5386   5390   Ljava/lang/Exception;
            //  1592   1612   5386   5390   Ljava/lang/Exception;
            //  1615   1635   5386   5390   Ljava/lang/Exception;
            //  1638   1658   5386   5390   Ljava/lang/Exception;
            //  1661   1675   1737   1742   Ljava/lang/Exception;
            //  1679   1684   1737   1742   Ljava/lang/Exception;
            //  1687   1699   1737   1742   Ljava/lang/Exception;
            //  1699   1713   1737   1742   Ljava/lang/Exception;
            //  1717   1722   1737   1742   Ljava/lang/Exception;
            //  1725   1737   1737   1742   Ljava/lang/Exception;
            //  1770   1797   2217   2222   Ljava/lang/Exception;
            //  1797   1827   5390   5394   Ljava/lang/Exception;
            //  1830   1854   5390   5394   Ljava/lang/Exception;
            //  1857   1881   5390   5394   Ljava/lang/Exception;
            //  1884   1908   5390   5394   Ljava/lang/Exception;
            //  1911   1935   5390   5394   Ljava/lang/Exception;
            //  1938   1962   5390   5394   Ljava/lang/Exception;
            //  1965   1985   5390   5394   Ljava/lang/Exception;
            //  1988   2008   5390   5394   Ljava/lang/Exception;
            //  2011   2035   5390   5394   Ljava/lang/Exception;
            //  2038   2055   5390   5394   Ljava/lang/Exception;
            //  2058   2082   5390   5394   Ljava/lang/Exception;
            //  2085   2105   5390   5394   Ljava/lang/Exception;
            //  2108   2128   5390   5394   Ljava/lang/Exception;
            //  2131   2151   5390   5394   Ljava/lang/Exception;
            //  2154   2174   5390   5394   Ljava/lang/Exception;
            //  2177   2194   2217   2222   Ljava/lang/Exception;
            //  2197   2214   2217   2222   Ljava/lang/Exception;
            //  2246   2275   2800   2805   Ljava/lang/Exception;
            //  2275   2306   5394   5398   Ljava/lang/Exception;
            //  2309   2334   5394   5398   Ljava/lang/Exception;
            //  2337   2362   5394   5398   Ljava/lang/Exception;
            //  2365   2387   5394   5398   Ljava/lang/Exception;
            //  2390   2415   5394   5398   Ljava/lang/Exception;
            //  2418   2443   5394   5398   Ljava/lang/Exception;
            //  2446   2464   5394   5398   Ljava/lang/Exception;
            //  2468   2473   5394   5398   Ljava/lang/Exception;
            //  2476   2488   5394   5398   Ljava/lang/Exception;
            //  2488   2506   5394   5398   Ljava/lang/Exception;
            //  2510   2515   5394   5398   Ljava/lang/Exception;
            //  2518   2530   5394   5398   Ljava/lang/Exception;
            //  2530   2555   5394   5398   Ljava/lang/Exception;
            //  2558   2576   5394   5398   Ljava/lang/Exception;
            //  2580   2585   5394   5398   Ljava/lang/Exception;
            //  2588   2600   5394   5398   Ljava/lang/Exception;
            //  2600   2625   5394   5398   Ljava/lang/Exception;
            //  2628   2649   5394   5398   Ljava/lang/Exception;
            //  2652   2673   5394   5398   Ljava/lang/Exception;
            //  2676   2697   5394   5398   Ljava/lang/Exception;
            //  2700   2721   5394   5398   Ljava/lang/Exception;
            //  2724   2738   2800   2805   Ljava/lang/Exception;
            //  2742   2747   2800   2805   Ljava/lang/Exception;
            //  2750   2762   2800   2805   Ljava/lang/Exception;
            //  2762   2776   2800   2805   Ljava/lang/Exception;
            //  2780   2785   2800   2805   Ljava/lang/Exception;
            //  2788   2800   2800   2805   Ljava/lang/Exception;
            //  2833   2846   3391   3396   Ljava/lang/Exception;
            //  2851   2866   3391   3396   Ljava/lang/Exception;
            //  2866   2897   5398   5402   Ljava/lang/Exception;
            //  2900   2925   5398   5402   Ljava/lang/Exception;
            //  2928   2953   5398   5402   Ljava/lang/Exception;
            //  2956   2981   5398   5402   Ljava/lang/Exception;
            //  2984   3009   5398   5402   Ljava/lang/Exception;
            //  3012   3037   5398   5402   Ljava/lang/Exception;
            //  3040   3058   5398   5402   Ljava/lang/Exception;
            //  3062   3067   5398   5402   Ljava/lang/Exception;
            //  3070   3082   5398   5402   Ljava/lang/Exception;
            //  3082   3100   5398   5402   Ljava/lang/Exception;
            //  3104   3109   5398   5402   Ljava/lang/Exception;
            //  3112   3124   5398   5402   Ljava/lang/Exception;
            //  3124   3149   5398   5402   Ljava/lang/Exception;
            //  3152   3170   5398   5402   Ljava/lang/Exception;
            //  3174   3179   5398   5402   Ljava/lang/Exception;
            //  3182   3194   5398   5402   Ljava/lang/Exception;
            //  3194   3219   5398   5402   Ljava/lang/Exception;
            //  3222   3243   5398   5402   Ljava/lang/Exception;
            //  3246   3267   5398   5402   Ljava/lang/Exception;
            //  3270   3288   5398   5402   Ljava/lang/Exception;
            //  3291   3312   5398   5402   Ljava/lang/Exception;
            //  3315   3329   3391   3396   Ljava/lang/Exception;
            //  3333   3338   3391   3396   Ljava/lang/Exception;
            //  3341   3353   3391   3396   Ljava/lang/Exception;
            //  3353   3367   3391   3396   Ljava/lang/Exception;
            //  3371   3376   3391   3396   Ljava/lang/Exception;
            //  3379   3391   3391   3396   Ljava/lang/Exception;
            //  3508   3528   3531   3538   Lcom/sendbird/android/SendBirdException;
            //  3576   3607   4134   4139   Ljava/lang/Exception;
            //  3607   3638   5402   5406   Ljava/lang/Exception;
            //  3641   3666   5402   5406   Ljava/lang/Exception;
            //  3669   3694   5402   5406   Ljava/lang/Exception;
            //  3697   3719   5402   5406   Ljava/lang/Exception;
            //  3722   3747   5402   5406   Ljava/lang/Exception;
            //  3750   3775   5402   5406   Ljava/lang/Exception;
            //  3778   3796   5402   5406   Ljava/lang/Exception;
            //  3800   3805   5402   5406   Ljava/lang/Exception;
            //  3808   3820   5402   5406   Ljava/lang/Exception;
            //  3820   3838   5402   5406   Ljava/lang/Exception;
            //  3842   3847   5402   5406   Ljava/lang/Exception;
            //  3850   3862   5402   5406   Ljava/lang/Exception;
            //  3862   3887   5402   5406   Ljava/lang/Exception;
            //  3890   3908   5402   5406   Ljava/lang/Exception;
            //  3912   3917   5402   5406   Ljava/lang/Exception;
            //  3920   3932   5402   5406   Ljava/lang/Exception;
            //  3932   3957   5402   5406   Ljava/lang/Exception;
            //  3960   3981   5402   5406   Ljava/lang/Exception;
            //  3984   4005   5402   5406   Ljava/lang/Exception;
            //  4008   4029   5402   5406   Ljava/lang/Exception;
            //  4032   4053   5402   5406   Ljava/lang/Exception;
            //  4056   4071   4134   4139   Ljava/lang/Exception;
            //  4075   4080   4134   4139   Ljava/lang/Exception;
            //  4083   4095   4134   4139   Ljava/lang/Exception;
            //  4095   4110   4134   4139   Ljava/lang/Exception;
            //  4114   4119   4134   4139   Ljava/lang/Exception;
            //  4122   4134   4134   4139   Ljava/lang/Exception;
            //  4176   4207   4734   4739   Ljava/lang/Exception;
            //  4207   4238   5406   5410   Ljava/lang/Exception;
            //  4241   4266   5406   5410   Ljava/lang/Exception;
            //  4269   4294   5406   5410   Ljava/lang/Exception;
            //  4297   4319   5406   5410   Ljava/lang/Exception;
            //  4322   4347   5406   5410   Ljava/lang/Exception;
            //  4350   4375   5406   5410   Ljava/lang/Exception;
            //  4378   4396   5406   5410   Ljava/lang/Exception;
            //  4400   4405   5406   5410   Ljava/lang/Exception;
            //  4408   4420   5406   5410   Ljava/lang/Exception;
            //  4420   4438   5406   5410   Ljava/lang/Exception;
            //  4442   4447   5406   5410   Ljava/lang/Exception;
            //  4450   4462   5406   5410   Ljava/lang/Exception;
            //  4462   4487   5406   5410   Ljava/lang/Exception;
            //  4490   4508   5406   5410   Ljava/lang/Exception;
            //  4512   4517   5406   5410   Ljava/lang/Exception;
            //  4520   4532   5406   5410   Ljava/lang/Exception;
            //  4532   4557   5406   5410   Ljava/lang/Exception;
            //  4560   4581   5406   5410   Ljava/lang/Exception;
            //  4584   4605   5406   5410   Ljava/lang/Exception;
            //  4608   4629   5406   5410   Ljava/lang/Exception;
            //  4632   4653   5406   5410   Ljava/lang/Exception;
            //  4656   4671   4734   4739   Ljava/lang/Exception;
            //  4675   4680   4734   4739   Ljava/lang/Exception;
            //  4683   4695   4734   4739   Ljava/lang/Exception;
            //  4695   4710   4734   4739   Ljava/lang/Exception;
            //  4714   4719   4734   4739   Ljava/lang/Exception;
            //  4722   4734   4734   4739   Ljava/lang/Exception;
            //  4775   4808   5337   5342   Ljava/lang/Exception;
            //  4808   4839   5410   5414   Ljava/lang/Exception;
            //  4842   4867   5410   5414   Ljava/lang/Exception;
            //  4870   4895   5410   5414   Ljava/lang/Exception;
            //  4898   4920   5410   5414   Ljava/lang/Exception;
            //  4923   4948   5410   5414   Ljava/lang/Exception;
            //  4951   4976   5410   5414   Ljava/lang/Exception;
            //  4979   4997   5410   5414   Ljava/lang/Exception;
            //  5001   5006   5410   5414   Ljava/lang/Exception;
            //  5009   5021   5410   5414   Ljava/lang/Exception;
            //  5021   5039   5410   5414   Ljava/lang/Exception;
            //  5043   5048   5410   5414   Ljava/lang/Exception;
            //  5051   5063   5410   5414   Ljava/lang/Exception;
            //  5063   5088   5410   5414   Ljava/lang/Exception;
            //  5091   5109   5410   5414   Ljava/lang/Exception;
            //  5113   5118   5410   5414   Ljava/lang/Exception;
            //  5121   5133   5410   5414   Ljava/lang/Exception;
            //  5133   5158   5410   5414   Ljava/lang/Exception;
            //  5161   5182   5410   5414   Ljava/lang/Exception;
            //  5185   5206   5410   5414   Ljava/lang/Exception;
            //  5209   5230   5410   5414   Ljava/lang/Exception;
            //  5233   5254   5410   5414   Ljava/lang/Exception;
            //  5257   5273   5337   5342   Ljava/lang/Exception;
            //  5277   5282   5337   5342   Ljava/lang/Exception;
            //  5285   5297   5337   5342   Ljava/lang/Exception;
            //  5297   5313   5337   5342   Ljava/lang/Exception;
            //  5317   5322   5337   5342   Ljava/lang/Exception;
            //  5325   5337   5337   5342   Ljava/lang/Exception;
            // 
            // The error that occurred was:
            // 
            // java.lang.IndexOutOfBoundsException: Index: 2448, Size: 2448
            //     at java.util.ArrayList.rangeCheck(Unknown Source)
            //     at java.util.ArrayList.get(Unknown Source)
            //     at com.strobel.decompiler.ast.AstBuilder.convertToAst(AstBuilder.java:3362)
            //     at com.strobel.decompiler.ast.AstBuilder.build(AstBuilder.java:112)
            //     at com.strobel.decompiler.languages.java.ast.AstMethodBodyBuilder.createMethodBody(AstMethodBodyBuilder.java:203)
            //     at com.strobel.decompiler.languages.java.ast.AstMethodBodyBuilder.createMethodBody(AstMethodBodyBuilder.java:93)
            //     at com.strobel.decompiler.languages.java.ast.AstBuilder.createMethodBody(AstBuilder.java:868)
            //     at com.strobel.decompiler.languages.java.ast.AstBuilder.createMethod(AstBuilder.java:761)
            //     at com.strobel.decompiler.languages.java.ast.AstBuilder.addTypeMembers(AstBuilder.java:638)
            //     at com.strobel.decompiler.languages.java.ast.AstBuilder.createTypeCore(AstBuilder.java:605)
            //     at com.strobel.decompiler.languages.java.ast.AstBuilder.createTypeNoCache(AstBuilder.java:195)
            //     at com.strobel.decompiler.languages.java.ast.AstBuilder.addTypeMembers(AstBuilder.java:662)
            //     at com.strobel.decompiler.languages.java.ast.AstBuilder.createTypeCore(AstBuilder.java:605)
            //     at com.strobel.decompiler.languages.java.ast.AstBuilder.createTypeNoCache(AstBuilder.java:195)
            //     at com.strobel.decompiler.languages.java.ast.AstBuilder.createType(AstBuilder.java:162)
            //     at com.strobel.decompiler.languages.java.ast.AstBuilder.addType(AstBuilder.java:137)
            //     at com.strobel.decompiler.languages.java.JavaLanguage.buildAst(JavaLanguage.java:71)
            //     at com.strobel.decompiler.languages.java.JavaLanguage.decompileType(JavaLanguage.java:59)
            //     at com.strobel.decompiler.DecompilerDriver.decompileType(DecompilerDriver.java:333)
            //     at com.strobel.decompiler.DecompilerDriver.decompileJar(DecompilerDriver.java:254)
            //     at com.strobel.decompiler.DecompilerDriver.main(DecompilerDriver.java:129)
            // 
            throw new IllegalStateException("An error occurred while decompiling this method.");
        }
    }
}
