// 
// Decompiled by Procyon v0.6.0
// 

package kd2;

import qd2.f;
import com.tonyodev.fetch2.downloader.ParallelFileDownloaderImpl;

public final class d implements Runnable
{
    public final ParallelFileDownloaderImpl f;
    public final f g;
    
    public d(final ParallelFileDownloaderImpl f, final f g) {
        this.f = f;
        this.g = g;
    }
    
    @Override
    public final void run() {
        // 
        // This method could not be decompiled.
        // 
        // Original Bytecode:
        // 
        //     3: astore          15
        //     5: aload           15
        //     7: ldc             "Thread.currentThread()"
        //     9: invokestatic    ng2/e.b:(Ljava/lang/Object;Ljava/lang/String;)V
        //    12: new             Ljava/lang/StringBuilder;
        //    15: astore          14
        //    17: aload           14
        //    19: invokespecial   java/lang/StringBuilder.<init>:()V
        //    22: aload           14
        //    24: aload_0        
        //    25: getfield        kd2/d.f:Lcom/tonyodev/fetch2/downloader/ParallelFileDownloaderImpl;
        //    28: invokevirtual   com/tonyodev/fetch2/downloader/ParallelFileDownloaderImpl.e:()Lcom/tonyodev/fetch2/database/DownloadInfo;
        //    31: invokevirtual   com/tonyodev/fetch2/database/DownloadInfo.getNamespace:()Ljava/lang/String;
        //    34: invokevirtual   java/lang/StringBuilder.append:(Ljava/lang/String;)Ljava/lang/StringBuilder;
        //    37: pop            
        //    38: aload           14
        //    40: bipush          45
        //    42: invokevirtual   java/lang/StringBuilder.append:(C)Ljava/lang/StringBuilder;
        //    45: pop            
        //    46: aload           14
        //    48: aload_0        
        //    49: getfield        kd2/d.f:Lcom/tonyodev/fetch2/downloader/ParallelFileDownloaderImpl;
        //    52: invokevirtual   com/tonyodev/fetch2/downloader/ParallelFileDownloaderImpl.e:()Lcom/tonyodev/fetch2/database/DownloadInfo;
        //    55: invokevirtual   com/tonyodev/fetch2/database/DownloadInfo.getId:()I
        //    58: invokevirtual   java/lang/StringBuilder.append:(I)Ljava/lang/StringBuilder;
        //    61: pop            
        //    62: aload           14
        //    64: ldc             "-Slice-"
        //    66: invokevirtual   java/lang/StringBuilder.append:(Ljava/lang/String;)Ljava/lang/StringBuilder;
        //    69: pop            
        //    70: aload           14
        //    72: aload_0        
        //    73: getfield        kd2/d.g:Lqd2/f;
        //    76: getfield        qd2/f.b:I
        //    79: invokevirtual   java/lang/StringBuilder.append:(I)Ljava/lang/StringBuilder;
        //    82: pop            
        //    83: aload           15
        //    85: aload           14
        //    87: invokevirtual   java/lang/StringBuilder.toString:()Ljava/lang/String;
        //    90: invokevirtual   java/lang/Thread.setName:(Ljava/lang/String;)V
        //    93: new             Lcom/tonyodev/fetch2core/DownloadBlockInfo;
        //    96: dup            
        //    97: invokespecial   com/tonyodev/fetch2core/DownloadBlockInfo.<init>:()V
        //   100: astore          21
        //   102: aload           21
        //   104: aload_0        
        //   105: getfield        kd2/d.g:Lqd2/f;
        //   108: getfield        qd2/f.a:I
        //   111: invokevirtual   com/tonyodev/fetch2core/DownloadBlockInfo.setDownloadId:(I)V
        //   114: aload           21
        //   116: aload_0        
        //   117: getfield        kd2/d.g:Lqd2/f;
        //   120: getfield        qd2/f.b:I
        //   123: invokevirtual   com/tonyodev/fetch2core/DownloadBlockInfo.setBlockPosition:(I)V
        //   126: aload           21
        //   128: aload_0        
        //   129: getfield        kd2/d.g:Lqd2/f;
        //   132: getfield        qd2/f.e:J
        //   135: invokevirtual   com/tonyodev/fetch2core/DownloadBlockInfo.setDownloadedBytes:(J)V
        //   138: aload           21
        //   140: aload_0        
        //   141: getfield        kd2/d.g:Lqd2/f;
        //   144: getfield        qd2/f.c:J
        //   147: invokevirtual   com/tonyodev/fetch2core/DownloadBlockInfo.setStartByte:(J)V
        //   150: aload           21
        //   152: aload_0        
        //   153: getfield        kd2/d.g:Lqd2/f;
        //   156: getfield        qd2/f.d:J
        //   159: invokevirtual   com/tonyodev/fetch2core/DownloadBlockInfo.setEndByte:(J)V
        //   162: aload_0        
        //   163: getfield        kd2/d.f:Lcom/tonyodev/fetch2/downloader/ParallelFileDownloaderImpl;
        //   166: invokevirtual   com/tonyodev/fetch2/downloader/ParallelFileDownloaderImpl.e:()Lcom/tonyodev/fetch2/database/DownloadInfo;
        //   169: astore          15
        //   171: aload_0        
        //   172: getfield        kd2/d.g:Lqd2/f;
        //   175: astore          14
        //   177: aload           15
        //   179: aload           14
        //   181: getfield        qd2/f.c:J
        //   184: aload           14
        //   186: getfield        qd2/f.e:J
        //   189: ladd           
        //   190: lconst_0       
        //   191: aconst_null    
        //   192: aload           14
        //   194: getfield        qd2/f.b:I
        //   197: iconst_1       
        //   198: iadd           
        //   199: bipush          12
        //   201: invokestatic    mg/d0.W:(Lcom/tonyodev/fetch2/Download;JJLjava/lang/String;II)Lcom/tonyodev/fetch2core/Downloader$b;
        //   204: astore          23
        //   206: aconst_null    
        //   207: astore          14
        //   209: aconst_null    
        //   210: astore          17
        //   212: aconst_null    
        //   213: astore          15
        //   215: aconst_null    
        //   216: astore          20
        //   218: aload_0        
        //   219: getfield        kd2/d.g:Lqd2/f;
        //   222: astore          16
        //   224: aload           16
        //   226: getfield        qd2/f.a:I
        //   229: aload           16
        //   231: getfield        qd2/f.b:I
        //   234: aload_0        
        //   235: getfield        kd2/d.f:Lcom/tonyodev/fetch2/downloader/ParallelFileDownloaderImpl;
        //   238: getfield        com/tonyodev/fetch2/downloader/ParallelFileDownloaderImpl.E:Ljava/lang/String;
        //   241: invokestatic    mg/d0.O:(IILjava/lang/String;)Ljava/lang/String;
        //   244: invokestatic    oy0/b.r:(Ljava/lang/String;)Ljava/io/File;
        //   247: astore          16
        //   249: new             Ljava/io/RandomAccessFile;
        //   252: astore          18
        //   254: aload           18
        //   256: aload           16
        //   258: ldc             "rw"
        //   260: invokespecial   java/io/RandomAccessFile.<init>:(Ljava/io/File;Ljava/lang/String;)V
        //   263: aload           20
        //   265: astore          16
        //   267: aload           17
        //   269: astore          15
        //   271: aload           18
        //   273: astore          19
        //   275: aload_0        
        //   276: getfield        kd2/d.f:Lcom/tonyodev/fetch2/downloader/ParallelFileDownloaderImpl;
        //   279: astore          14
        //   281: aload           20
        //   283: astore          16
        //   285: aload           17
        //   287: astore          15
        //   289: aload           18
        //   291: astore          19
        //   293: aload           14
        //   295: getfield        com/tonyodev/fetch2/downloader/ParallelFileDownloaderImpl.z:Lcom/tonyodev/fetch2core/Downloader;
        //   298: aload           23
        //   300: aload           14
        //   302: getfield        com/tonyodev/fetch2/downloader/ParallelFileDownloaderImpl.x:Lcom/tonyodev/fetch2/downloader/ParallelFileDownloaderImpl$a;
        //   305: invokeinterface com/tonyodev/fetch2core/Downloader.N:(Lcom/tonyodev/fetch2core/Downloader$b;Lqd2/h;)Lcom/tonyodev/fetch2core/Downloader$a;
        //   310: astore          17
        //   312: aload           17
        //   314: astore          14
        //   316: aload           14
        //   318: astore          16
        //   320: aload           14
        //   322: astore          15
        //   324: aload           18
        //   326: astore          19
        //   328: aload_0        
        //   329: getfield        kd2/d.f:Lcom/tonyodev/fetch2/downloader/ParallelFileDownloaderImpl;
        //   332: getfield        com/tonyodev/fetch2/downloader/ParallelFileDownloaderImpl.g:Z
        //   335: ifne            1422
        //   338: aload           14
        //   340: astore          16
        //   342: aload           14
        //   344: astore          15
        //   346: aload           18
        //   348: astore          19
        //   350: aload_0        
        //   351: getfield        kd2/d.f:Lcom/tonyodev/fetch2/downloader/ParallelFileDownloaderImpl;
        //   354: getfield        com/tonyodev/fetch2/downloader/ParallelFileDownloaderImpl.f:Z
        //   357: ifne            1422
        //   360: aload           14
        //   362: ifnull          1422
        //   365: aload           14
        //   367: astore          16
        //   369: aload           14
        //   371: astore          15
        //   373: aload           18
        //   375: astore          19
        //   377: aload           14
        //   379: getfield        com/tonyodev/fetch2core/Downloader$a.b:Z
        //   382: iconst_1       
        //   383: if_icmpne       1422
        //   386: aload           14
        //   388: astore          16
        //   390: aload           14
        //   392: astore          15
        //   394: aload           18
        //   396: astore          19
        //   398: new             Lkotlin/jvm/internal/Ref$LongRef;
        //   401: astore          22
        //   403: aload           14
        //   405: astore          16
        //   407: aload           14
        //   409: astore          15
        //   411: aload           18
        //   413: astore          19
        //   415: aload           22
        //   417: invokespecial   kotlin/jvm/internal/Ref$LongRef.<init>:()V
        //   420: aload           14
        //   422: astore          16
        //   424: aload           14
        //   426: astore          15
        //   428: aload           18
        //   430: astore          19
        //   432: aload_0        
        //   433: getfield        kd2/d.f:Lcom/tonyodev/fetch2/downloader/ParallelFileDownloaderImpl;
        //   436: getfield        com/tonyodev/fetch2/downloader/ParallelFileDownloaderImpl.z:Lcom/tonyodev/fetch2core/Downloader;
        //   439: aload           23
        //   441: invokeinterface com/tonyodev/fetch2core/Downloader.u:(Lcom/tonyodev/fetch2core/Downloader$b;)V
        //   446: aload           14
        //   448: astore          16
        //   450: aload           14
        //   452: astore          15
        //   454: aload           18
        //   456: astore          19
        //   458: sipush          8192
        //   461: newarray        B
        //   463: astore          23
        //   465: aload           14
        //   467: astore          16
        //   469: aload           14
        //   471: astore          15
        //   473: aload           18
        //   475: astore          19
        //   477: aload           14
        //   479: getfield        com/tonyodev/fetch2core/Downloader$a.d:Ljava/io/InputStream;
        //   482: astore          20
        //   484: aload           20
        //   486: ifnull          516
        //   489: aload           14
        //   491: astore          16
        //   493: aload           14
        //   495: astore          15
        //   497: aload           18
        //   499: astore          19
        //   501: aload           20
        //   503: aload           23
        //   505: iconst_0       
        //   506: sipush          8192
        //   509: invokevirtual   java/io/InputStream.read:([BII)I
        //   512: istore_1       
        //   513: goto            518
        //   516: iconst_m1      
        //   517: istore_1       
        //   518: aload           14
        //   520: astore          16
        //   522: aload           14
        //   524: astore          15
        //   526: aload           18
        //   528: astore          19
        //   530: aload_0        
        //   531: getfield        kd2/d.g:Lqd2/f;
        //   534: astore          20
        //   536: aload           14
        //   538: astore          16
        //   540: aload           14
        //   542: astore          15
        //   544: aload           18
        //   546: astore          19
        //   548: aload           20
        //   550: getfield        qd2/f.d:J
        //   553: lstore          4
        //   555: lload           4
        //   557: lconst_1       
        //   558: lcmp           
        //   559: ifge            568
        //   562: lconst_0       
        //   563: lstore          4
        //   565: goto            568
        //   568: aload           17
        //   570: astore          14
        //   572: aload           14
        //   574: astore          16
        //   576: aload           14
        //   578: astore          15
        //   580: lload           4
        //   582: aload           20
        //   584: getfield        qd2/f.c:J
        //   587: aload           20
        //   589: getfield        qd2/f.e:J
        //   592: ladd           
        //   593: lsub           
        //   594: lstore          6
        //   596: aload           14
        //   598: astore          16
        //   600: aload           14
        //   602: astore          15
        //   604: invokestatic    java/lang/System.nanoTime:()J
        //   607: lstore          8
        //   609: aload           14
        //   611: astore          16
        //   613: aload           14
        //   615: astore          15
        //   617: new             Lkotlin/jvm/internal/Ref$IntRef;
        //   620: astore          24
        //   622: aload           14
        //   624: astore          16
        //   626: aload           14
        //   628: astore          15
        //   630: aload           24
        //   632: invokespecial   kotlin/jvm/internal/Ref$IntRef.<init>:()V
        //   635: aload           14
        //   637: astore          16
        //   639: aload           14
        //   641: astore          15
        //   643: new             Lkotlin/jvm/internal/Ref$LongRef;
        //   646: astore          20
        //   648: aload           14
        //   650: astore          16
        //   652: aload           14
        //   654: astore          15
        //   656: aload           20
        //   658: invokespecial   kotlin/jvm/internal/Ref$LongRef.<init>:()V
        //   661: lload           4
        //   663: lstore          10
        //   665: lload           6
        //   667: lstore          4
        //   669: aload           14
        //   671: astore          16
        //   673: aload           14
        //   675: astore          15
        //   677: aload_0        
        //   678: getfield        kd2/d.f:Lcom/tonyodev/fetch2/downloader/ParallelFileDownloaderImpl;
        //   681: getfield        com/tonyodev/fetch2/downloader/ParallelFileDownloaderImpl.l:Z
        //   684: ifne            694
        //   687: lload           4
        //   689: lconst_0       
        //   690: lcmp           
        //   691: ifle            1397
        //   694: iload_1        
        //   695: iconst_m1      
        //   696: if_icmpeq       1397
        //   699: aload           14
        //   701: astore          16
        //   703: aload           14
        //   705: astore          15
        //   707: aload_0        
        //   708: getfield        kd2/d.f:Lcom/tonyodev/fetch2/downloader/ParallelFileDownloaderImpl;
        //   711: getfield        com/tonyodev/fetch2/downloader/ParallelFileDownloaderImpl.f:Z
        //   714: ifne            1397
        //   717: aload           14
        //   719: astore          16
        //   721: aload           14
        //   723: astore          15
        //   725: aload_0        
        //   726: getfield        kd2/d.f:Lcom/tonyodev/fetch2/downloader/ParallelFileDownloaderImpl;
        //   729: getfield        com/tonyodev/fetch2/downloader/ParallelFileDownloaderImpl.g:Z
        //   732: ifne            1397
        //   735: aload           14
        //   737: astore          16
        //   739: aload           14
        //   741: astore          15
        //   743: aload_0        
        //   744: getfield        kd2/d.f:Lcom/tonyodev/fetch2/downloader/ParallelFileDownloaderImpl;
        //   747: getfield        com/tonyodev/fetch2/downloader/ParallelFileDownloaderImpl.l:Z
        //   750: ifne            773
        //   753: iload_1        
        //   754: i2l            
        //   755: lload           4
        //   757: lcmp           
        //   758: ifgt            764
        //   761: goto            773
        //   764: lload           4
        //   766: l2i            
        //   767: istore_1       
        //   768: iconst_m1      
        //   769: istore_2       
        //   770: goto            775
        //   773: iload_1        
        //   774: istore_2       
        //   775: aload           14
        //   777: astore          16
        //   779: aload           14
        //   781: astore          15
        //   783: aload           24
        //   785: iload_1        
        //   786: putfield        kotlin/jvm/internal/Ref$IntRef.element:I
        //   789: aload           14
        //   791: astore          16
        //   793: aload           14
        //   795: astore          15
        //   797: aload_0        
        //   798: getfield        kd2/d.g:Lqd2/f;
        //   801: astore          17
        //   803: aload           14
        //   805: astore          16
        //   807: aload           14
        //   809: astore          15
        //   811: aload           17
        //   813: getfield        qd2/f.c:J
        //   816: lstore          6
        //   818: aload           20
        //   820: lload           6
        //   822: aload           17
        //   824: getfield        qd2/f.e:J
        //   827: ladd           
        //   828: putfield        kotlin/jvm/internal/Ref$LongRef.element:J
        //   831: aload_0        
        //   832: getfield        kd2/d.f:Lcom/tonyodev/fetch2/downloader/ParallelFileDownloaderImpl;
        //   835: getfield        com/tonyodev/fetch2/downloader/ParallelFileDownloaderImpl.s:Ljava/lang/Object;
        //   838: astore          25
        //   840: aload           25
        //   842: monitorenter   
        //   843: aload_0        
        //   844: getfield        kd2/d.f:Lcom/tonyodev/fetch2/downloader/ParallelFileDownloaderImpl;
        //   847: getfield        com/tonyodev/fetch2/downloader/ParallelFileDownloaderImpl.f:Z
        //   850: ifne            1128
        //   853: aload_0        
        //   854: getfield        kd2/d.f:Lcom/tonyodev/fetch2/downloader/ParallelFileDownloaderImpl;
        //   857: getfield        com/tonyodev/fetch2/downloader/ParallelFileDownloaderImpl.g:Z
        //   860: ifne            1128
        //   863: aload_0        
        //   864: getfield        kd2/d.f:Lcom/tonyodev/fetch2/downloader/ParallelFileDownloaderImpl;
        //   867: getfield        com/tonyodev/fetch2/downloader/ParallelFileDownloaderImpl.v:Lqd2/j;
        //   870: astore          15
        //   872: aload           15
        //   874: ifnull          887
        //   877: aload           15
        //   879: aload           20
        //   881: getfield        kotlin/jvm/internal/Ref$LongRef.element:J
        //   884: invokevirtual   qd2/j.h:(J)V
        //   887: aload_0        
        //   888: getfield        kd2/d.f:Lcom/tonyodev/fetch2/downloader/ParallelFileDownloaderImpl;
        //   891: getfield        com/tonyodev/fetch2/downloader/ParallelFileDownloaderImpl.v:Lqd2/j;
        //   894: astore          15
        //   896: aload           15
        //   898: ifnull          913
        //   901: aload           15
        //   903: aload           23
        //   905: aload           24
        //   907: getfield        kotlin/jvm/internal/Ref$IntRef.element:I
        //   910: invokevirtual   qd2/j.j:([BI)V
        //   913: aload_0        
        //   914: getfield        kd2/d.f:Lcom/tonyodev/fetch2/downloader/ParallelFileDownloaderImpl;
        //   917: getfield        com/tonyodev/fetch2/downloader/ParallelFileDownloaderImpl.f:Z
        //   920: ifne            1016
        //   923: aload_0        
        //   924: getfield        kd2/d.f:Lcom/tonyodev/fetch2/downloader/ParallelFileDownloaderImpl;
        //   927: getfield        com/tonyodev/fetch2/downloader/ParallelFileDownloaderImpl.g:Z
        //   930: ifne            1016
        //   933: aload_0        
        //   934: getfield        kd2/d.g:Lqd2/f;
        //   937: astore          15
        //   939: aload           15
        //   941: getfield        qd2/f.e:J
        //   944: lstore          6
        //   946: aload           24
        //   948: getfield        kotlin/jvm/internal/Ref$IntRef.element:I
        //   951: istore_1       
        //   952: iload_1        
        //   953: i2l            
        //   954: lstore          12
        //   956: aload           15
        //   958: lload           6
        //   960: lload           12
        //   962: ladd           
        //   963: putfield        qd2/f.e:J
        //   966: aload           18
        //   968: lconst_0       
        //   969: invokevirtual   java/io/RandomAccessFile.seek:(J)V
        //   972: aload           18
        //   974: lconst_0       
        //   975: invokevirtual   java/io/RandomAccessFile.setLength:(J)V
        //   978: aload           18
        //   980: aload_0        
        //   981: getfield        kd2/d.g:Lqd2/f;
        //   984: getfield        qd2/f.e:J
        //   987: invokevirtual   java/io/RandomAccessFile.writeLong:(J)V
        //   990: aload_0        
        //   991: getfield        kd2/d.f:Lcom/tonyodev/fetch2/downloader/ParallelFileDownloaderImpl;
        //   994: astore          15
        //   996: aload           15
        //   998: aload           15
        //  1000: getfield        com/tonyodev/fetch2/downloader/ParallelFileDownloaderImpl.j:J
        //  1003: aload           24
        //  1005: getfield        kotlin/jvm/internal/Ref$IntRef.element:I
        //  1008: i2l            
        //  1009: ladd           
        //  1010: putfield        com/tonyodev/fetch2/downloader/ParallelFileDownloaderImpl.j:J
        //  1013: goto            1016
        //  1016: invokestatic    java/lang/System.nanoTime:()J
        //  1019: lstore          12
        //  1021: aload           22
        //  1023: lload           12
        //  1025: putfield        kotlin/jvm/internal/Ref$LongRef.element:J
        //  1028: lload           8
        //  1030: lstore          6
        //  1032: lload           8
        //  1034: lload           12
        //  1036: aload_0        
        //  1037: getfield        kd2/d.f:Lcom/tonyodev/fetch2/downloader/ParallelFileDownloaderImpl;
        //  1040: getfield        com/tonyodev/fetch2/downloader/ParallelFileDownloaderImpl.A:J
        //  1043: invokestatic    oy0/b.A:(JJJ)Z
        //  1046: ifeq            1132
        //  1049: aload_0        
        //  1050: getfield        kd2/d.f:Lcom/tonyodev/fetch2/downloader/ParallelFileDownloaderImpl;
        //  1053: getfield        com/tonyodev/fetch2/downloader/ParallelFileDownloaderImpl.f:Z
        //  1056: ifne            1120
        //  1059: aload_0        
        //  1060: getfield        kd2/d.f:Lcom/tonyodev/fetch2/downloader/ParallelFileDownloaderImpl;
        //  1063: getfield        com/tonyodev/fetch2/downloader/ParallelFileDownloaderImpl.g:Z
        //  1066: ifne            1120
        //  1069: aload           21
        //  1071: aload_0        
        //  1072: getfield        kd2/d.g:Lqd2/f;
        //  1075: getfield        qd2/f.e:J
        //  1078: invokevirtual   com/tonyodev/fetch2core/DownloadBlockInfo.setDownloadedBytes:(J)V
        //  1081: aload_0        
        //  1082: getfield        kd2/d.f:Lcom/tonyodev/fetch2/downloader/ParallelFileDownloaderImpl;
        //  1085: astore          15
        //  1087: aload           15
        //  1089: getfield        com/tonyodev/fetch2/downloader/ParallelFileDownloaderImpl.h:Lkd2/c$a;
        //  1092: astore          16
        //  1094: aload           16
        //  1096: ifnull          1120
        //  1099: aload           16
        //  1101: aload           15
        //  1103: invokevirtual   com/tonyodev/fetch2/downloader/ParallelFileDownloaderImpl.e:()Lcom/tonyodev/fetch2/database/DownloadInfo;
        //  1106: aload           21
        //  1108: aload_0        
        //  1109: getfield        kd2/d.f:Lcom/tonyodev/fetch2/downloader/ParallelFileDownloaderImpl;
        //  1112: getfield        com/tonyodev/fetch2/downloader/ParallelFileDownloaderImpl.w:I
        //  1115: invokeinterface kd2/c$a.a:(Lcom/tonyodev/fetch2/database/DownloadInfo;Lcom/tonyodev/fetch2core/DownloadBlockInfo;I)V
        //  1120: invokestatic    java/lang/System.nanoTime:()J
        //  1123: lstore          6
        //  1125: goto            1132
        //  1128: lload           8
        //  1130: lstore          6
        //  1132: getstatic       cg2/j.a:Lcg2/j;
        //  1135: astore          15
        //  1137: aload           25
        //  1139: monitorexit    
        //  1140: aload_0        
        //  1141: getfield        kd2/d.f:Lcom/tonyodev/fetch2/downloader/ParallelFileDownloaderImpl;
        //  1144: getfield        com/tonyodev/fetch2/downloader/ParallelFileDownloaderImpl.f:Z
        //  1147: ifne            1303
        //  1150: aload_0        
        //  1151: getfield        kd2/d.f:Lcom/tonyodev/fetch2/downloader/ParallelFileDownloaderImpl;
        //  1154: getfield        com/tonyodev/fetch2/downloader/ParallelFileDownloaderImpl.g:Z
        //  1157: istore_3       
        //  1158: iload_3        
        //  1159: ifne            1303
        //  1162: iload_2        
        //  1163: iconst_m1      
        //  1164: if_icmpeq       1300
        //  1167: aload           14
        //  1169: astore          17
        //  1171: aload           17
        //  1173: astore          16
        //  1175: aload           17
        //  1177: astore          15
        //  1179: aload           18
        //  1181: astore          19
        //  1183: aload           17
        //  1185: getfield        com/tonyodev/fetch2core/Downloader$a.d:Ljava/io/InputStream;
        //  1188: astore          25
        //  1190: aload           25
        //  1192: ifnull          1222
        //  1195: aload           17
        //  1197: astore          16
        //  1199: aload           17
        //  1201: astore          15
        //  1203: aload           18
        //  1205: astore          19
        //  1207: aload           25
        //  1209: aload           23
        //  1211: iconst_0       
        //  1212: sipush          8192
        //  1215: invokevirtual   java/io/InputStream.read:([BII)I
        //  1218: istore_1       
        //  1219: goto            1224
        //  1222: iconst_m1      
        //  1223: istore_1       
        //  1224: aload           17
        //  1226: astore          16
        //  1228: aload           17
        //  1230: astore          15
        //  1232: aload           18
        //  1234: astore          19
        //  1236: aload_0        
        //  1237: getfield        kd2/d.f:Lcom/tonyodev/fetch2/downloader/ParallelFileDownloaderImpl;
        //  1240: getfield        com/tonyodev/fetch2/downloader/ParallelFileDownloaderImpl.l:Z
        //  1243: ifne            1295
        //  1246: aload           17
        //  1248: astore          16
        //  1250: aload           17
        //  1252: astore          15
        //  1254: aload           18
        //  1256: astore          19
        //  1258: aload_0        
        //  1259: getfield        kd2/d.g:Lqd2/f;
        //  1262: astore          25
        //  1264: aload           17
        //  1266: astore          16
        //  1268: aload           17
        //  1270: astore          15
        //  1272: aload           18
        //  1274: astore          19
        //  1276: lload           10
        //  1278: aload           25
        //  1280: getfield        qd2/f.c:J
        //  1283: aload           25
        //  1285: getfield        qd2/f.e:J
        //  1288: ladd           
        //  1289: lsub           
        //  1290: lstore          4
        //  1292: goto            1305
        //  1295: iload_1        
        //  1296: istore_2       
        //  1297: goto            1303
        //  1300: goto            1303
        //  1303: iload_2        
        //  1304: istore_1       
        //  1305: lload           6
        //  1307: lstore          8
        //  1309: goto            669
        //  1312: astore          16
        //  1314: aload           14
        //  1316: astore          15
        //  1318: aload           16
        //  1320: astore          14
        //  1322: goto            2029
        //  1325: astore          17
        //  1327: goto            1825
        //  1330: astore          17
        //  1332: aload           14
        //  1334: astore          15
        //  1336: goto            1345
        //  1339: astore          17
        //  1341: aload           14
        //  1343: astore          15
        //  1345: aload           14
        //  1347: astore          16
        //  1349: aload           14
        //  1351: astore          15
        //  1353: aload           18
        //  1355: astore          19
        //  1357: aload           25
        //  1359: monitorexit    
        //  1360: aload           14
        //  1362: astore          16
        //  1364: aload           14
        //  1366: astore          15
        //  1368: aload           18
        //  1370: astore          19
        //  1372: aload           17
        //  1374: athrow         
        //  1375: astore          15
        //  1377: aload           14
        //  1379: astore          16
        //  1381: aload           15
        //  1383: astore          14
        //  1385: aload           16
        //  1387: astore          15
        //  1389: goto            2029
        //  1392: astore          17
        //  1394: goto            1825
        //  1397: aload           14
        //  1399: astore          17
        //  1401: goto            1754
        //  1404: astore          14
        //  1406: aload           16
        //  1408: astore          15
        //  1410: goto            2029
        //  1413: astore          17
        //  1415: aload           15
        //  1417: astore          14
        //  1419: goto            1825
        //  1422: aload           14
        //  1424: ifnonnull       1525
        //  1427: aload           14
        //  1429: astore          16
        //  1431: aload           14
        //  1433: astore          15
        //  1435: aload           18
        //  1437: astore          19
        //  1439: aload_0        
        //  1440: getfield        kd2/d.f:Lcom/tonyodev/fetch2/downloader/ParallelFileDownloaderImpl;
        //  1443: getfield        com/tonyodev/fetch2/downloader/ParallelFileDownloaderImpl.f:Z
        //  1446: ifne            1525
        //  1449: aload           14
        //  1451: astore          16
        //  1453: aload           14
        //  1455: astore          15
        //  1457: aload           18
        //  1459: astore          19
        //  1461: aload_0        
        //  1462: getfield        kd2/d.f:Lcom/tonyodev/fetch2/downloader/ParallelFileDownloaderImpl;
        //  1465: getfield        com/tonyodev/fetch2/downloader/ParallelFileDownloaderImpl.g:Z
        //  1468: ifeq            1474
        //  1471: goto            1525
        //  1474: aload           14
        //  1476: astore          16
        //  1478: aload           14
        //  1480: astore          15
        //  1482: aload           18
        //  1484: astore          19
        //  1486: new             Lcom/tonyodev/fetch2/exception/FetchException;
        //  1489: astore          17
        //  1491: aload           14
        //  1493: astore          16
        //  1495: aload           14
        //  1497: astore          15
        //  1499: aload           18
        //  1501: astore          19
        //  1503: aload           17
        //  1505: ldc             "empty_response_body"
        //  1507: invokespecial   com/tonyodev/fetch2/exception/FetchException.<init>:(Ljava/lang/String;)V
        //  1510: aload           14
        //  1512: astore          16
        //  1514: aload           14
        //  1516: astore          15
        //  1518: aload           18
        //  1520: astore          19
        //  1522: aload           17
        //  1524: athrow         
        //  1525: aload           14
        //  1527: ifnull          1648
        //  1530: aload           14
        //  1532: astore          16
        //  1534: aload           14
        //  1536: astore          15
        //  1538: aload           18
        //  1540: astore          19
        //  1542: aload           14
        //  1544: getfield        com/tonyodev/fetch2core/Downloader$a.b:Z
        //  1547: ifne            1648
        //  1550: aload           14
        //  1552: astore          16
        //  1554: aload           14
        //  1556: astore          15
        //  1558: aload           18
        //  1560: astore          19
        //  1562: aload_0        
        //  1563: getfield        kd2/d.f:Lcom/tonyodev/fetch2/downloader/ParallelFileDownloaderImpl;
        //  1566: getfield        com/tonyodev/fetch2/downloader/ParallelFileDownloaderImpl.f:Z
        //  1569: ifne            1648
        //  1572: aload           14
        //  1574: astore          16
        //  1576: aload           14
        //  1578: astore          15
        //  1580: aload           18
        //  1582: astore          19
        //  1584: aload_0        
        //  1585: getfield        kd2/d.f:Lcom/tonyodev/fetch2/downloader/ParallelFileDownloaderImpl;
        //  1588: getfield        com/tonyodev/fetch2/downloader/ParallelFileDownloaderImpl.g:Z
        //  1591: ifeq            1597
        //  1594: goto            1648
        //  1597: aload           14
        //  1599: astore          16
        //  1601: aload           14
        //  1603: astore          15
        //  1605: aload           18
        //  1607: astore          19
        //  1609: new             Lcom/tonyodev/fetch2/exception/FetchException;
        //  1612: astore          17
        //  1614: aload           14
        //  1616: astore          16
        //  1618: aload           14
        //  1620: astore          15
        //  1622: aload           18
        //  1624: astore          19
        //  1626: aload           17
        //  1628: ldc             "request_not_successful"
        //  1630: invokespecial   com/tonyodev/fetch2/exception/FetchException.<init>:(Ljava/lang/String;)V
        //  1633: aload           14
        //  1635: astore          16
        //  1637: aload           14
        //  1639: astore          15
        //  1641: aload           18
        //  1643: astore          19
        //  1645: aload           17
        //  1647: athrow         
        //  1648: aload           14
        //  1650: astore          17
        //  1652: aload           14
        //  1654: astore          16
        //  1656: aload           14
        //  1658: astore          15
        //  1660: aload           18
        //  1662: astore          19
        //  1664: aload_0        
        //  1665: getfield        kd2/d.f:Lcom/tonyodev/fetch2/downloader/ParallelFileDownloaderImpl;
        //  1668: getfield        com/tonyodev/fetch2/downloader/ParallelFileDownloaderImpl.f:Z
        //  1671: ifne            1754
        //  1674: aload           14
        //  1676: astore          16
        //  1678: aload           14
        //  1680: astore          15
        //  1682: aload           18
        //  1684: astore          19
        //  1686: aload_0        
        //  1687: getfield        kd2/d.f:Lcom/tonyodev/fetch2/downloader/ParallelFileDownloaderImpl;
        //  1690: getfield        com/tonyodev/fetch2/downloader/ParallelFileDownloaderImpl.g:Z
        //  1693: ifeq            1703
        //  1696: aload           14
        //  1698: astore          17
        //  1700: goto            1754
        //  1703: aload           14
        //  1705: astore          16
        //  1707: aload           14
        //  1709: astore          15
        //  1711: aload           18
        //  1713: astore          19
        //  1715: new             Lcom/tonyodev/fetch2/exception/FetchException;
        //  1718: astore          17
        //  1720: aload           14
        //  1722: astore          16
        //  1724: aload           14
        //  1726: astore          15
        //  1728: aload           18
        //  1730: astore          19
        //  1732: aload           17
        //  1734: ldc             "unknown"
        //  1736: invokespecial   com/tonyodev/fetch2/exception/FetchException.<init>:(Ljava/lang/String;)V
        //  1739: aload           14
        //  1741: astore          16
        //  1743: aload           14
        //  1745: astore          15
        //  1747: aload           18
        //  1749: astore          19
        //  1751: aload           17
        //  1753: athrow         
        //  1754: aload           17
        //  1756: ifnull          1795
        //  1759: aload_0        
        //  1760: getfield        kd2/d.f:Lcom/tonyodev/fetch2/downloader/ParallelFileDownloaderImpl;
        //  1763: getfield        com/tonyodev/fetch2/downloader/ParallelFileDownloaderImpl.z:Lcom/tonyodev/fetch2core/Downloader;
        //  1766: aload           17
        //  1768: invokeinterface com/tonyodev/fetch2core/Downloader.e:(Lcom/tonyodev/fetch2core/Downloader$a;)V
        //  1773: goto            1795
        //  1776: astore          14
        //  1778: aload_0        
        //  1779: getfield        kd2/d.f:Lcom/tonyodev/fetch2/downloader/ParallelFileDownloaderImpl;
        //  1782: getfield        com/tonyodev/fetch2/downloader/ParallelFileDownloaderImpl.B:Lqd2/i;
        //  1785: ldc_w           "FileDownloader"
        //  1788: aload           14
        //  1790: invokeinterface qd2/i.b:(Ljava/lang/String;Ljava/lang/Exception;)V
        //  1795: aload           18
        //  1797: invokevirtual   java/io/RandomAccessFile.close:()V
        //  1800: goto            2015
        //  1803: astore          17
        //  1805: aload           16
        //  1807: astore          14
        //  1809: goto            1825
        //  1812: astore          14
        //  1814: aconst_null    
        //  1815: astore          18
        //  1817: goto            2029
        //  1820: astore          17
        //  1822: aconst_null    
        //  1823: astore          18
        //  1825: aload           14
        //  1827: astore          15
        //  1829: aload           18
        //  1831: astore          19
        //  1833: aload_0        
        //  1834: getfield        kd2/d.f:Lcom/tonyodev/fetch2/downloader/ParallelFileDownloaderImpl;
        //  1837: getfield        com/tonyodev/fetch2/downloader/ParallelFileDownloaderImpl.B:Lqd2/i;
        //  1840: astore          16
        //  1842: aload           14
        //  1844: astore          15
        //  1846: aload           18
        //  1848: astore          19
        //  1850: new             Ljava/lang/StringBuilder;
        //  1853: astore          20
        //  1855: aload           14
        //  1857: astore          15
        //  1859: aload           18
        //  1861: astore          19
        //  1863: aload           20
        //  1865: invokespecial   java/lang/StringBuilder.<init>:()V
        //  1868: aload           14
        //  1870: astore          15
        //  1872: aload           18
        //  1874: astore          19
        //  1876: aload           20
        //  1878: ldc_w           "FileDownloader downloads slice "
        //  1881: invokevirtual   java/lang/StringBuilder.append:(Ljava/lang/String;)Ljava/lang/StringBuilder;
        //  1884: pop            
        //  1885: aload           14
        //  1887: astore          15
        //  1889: aload           18
        //  1891: astore          19
        //  1893: aload           20
        //  1895: aload_0        
        //  1896: getfield        kd2/d.g:Lqd2/f;
        //  1899: invokevirtual   java/lang/StringBuilder.append:(Ljava/lang/Object;)Ljava/lang/StringBuilder;
        //  1902: pop            
        //  1903: aload           14
        //  1905: astore          15
        //  1907: aload           18
        //  1909: astore          19
        //  1911: aload           16
        //  1913: aload           20
        //  1915: invokevirtual   java/lang/StringBuilder.toString:()Ljava/lang/String;
        //  1918: aload           17
        //  1920: invokeinterface qd2/i.b:(Ljava/lang/String;Ljava/lang/Exception;)V
        //  1925: aload           14
        //  1927: astore          15
        //  1929: aload           18
        //  1931: astore          19
        //  1933: aload_0        
        //  1934: getfield        kd2/d.f:Lcom/tonyodev/fetch2/downloader/ParallelFileDownloaderImpl;
        //  1937: aload           17
        //  1939: putfield        com/tonyodev/fetch2/downloader/ParallelFileDownloaderImpl.t:Ljava/lang/Throwable;
        //  1942: aload           14
        //  1944: ifnull          1983
        //  1947: aload_0        
        //  1948: getfield        kd2/d.f:Lcom/tonyodev/fetch2/downloader/ParallelFileDownloaderImpl;
        //  1951: getfield        com/tonyodev/fetch2/downloader/ParallelFileDownloaderImpl.z:Lcom/tonyodev/fetch2core/Downloader;
        //  1954: aload           14
        //  1956: invokeinterface com/tonyodev/fetch2core/Downloader.e:(Lcom/tonyodev/fetch2core/Downloader$a;)V
        //  1961: goto            1983
        //  1964: astore          14
        //  1966: aload_0        
        //  1967: getfield        kd2/d.f:Lcom/tonyodev/fetch2/downloader/ParallelFileDownloaderImpl;
        //  1970: getfield        com/tonyodev/fetch2/downloader/ParallelFileDownloaderImpl.B:Lqd2/i;
        //  1973: ldc_w           "FileDownloader"
        //  1976: aload           14
        //  1978: invokeinterface qd2/i.b:(Ljava/lang/String;Ljava/lang/Exception;)V
        //  1983: aload           18
        //  1985: ifnull          2015
        //  1988: aload           18
        //  1990: invokevirtual   java/io/RandomAccessFile.close:()V
        //  1993: goto            2015
        //  1996: astore          14
        //  1998: aload_0        
        //  1999: getfield        kd2/d.f:Lcom/tonyodev/fetch2/downloader/ParallelFileDownloaderImpl;
        //  2002: getfield        com/tonyodev/fetch2/downloader/ParallelFileDownloaderImpl.B:Lqd2/i;
        //  2005: ldc_w           "FileDownloader"
        //  2008: aload           14
        //  2010: invokeinterface qd2/i.b:(Ljava/lang/String;Ljava/lang/Exception;)V
        //  2015: aload_0        
        //  2016: getfield        kd2/d.f:Lcom/tonyodev/fetch2/downloader/ParallelFileDownloaderImpl;
        //  2019: invokestatic    com/tonyodev/fetch2/downloader/ParallelFileDownloaderImpl.a:(Lcom/tonyodev/fetch2/downloader/ParallelFileDownloaderImpl;)V
        //  2022: return         
        //  2023: astore          14
        //  2025: aload           19
        //  2027: astore          18
        //  2029: aload           15
        //  2031: ifnull          2070
        //  2034: aload_0        
        //  2035: getfield        kd2/d.f:Lcom/tonyodev/fetch2/downloader/ParallelFileDownloaderImpl;
        //  2038: getfield        com/tonyodev/fetch2/downloader/ParallelFileDownloaderImpl.z:Lcom/tonyodev/fetch2core/Downloader;
        //  2041: aload           15
        //  2043: invokeinterface com/tonyodev/fetch2core/Downloader.e:(Lcom/tonyodev/fetch2core/Downloader$a;)V
        //  2048: goto            2070
        //  2051: astore          15
        //  2053: aload_0        
        //  2054: getfield        kd2/d.f:Lcom/tonyodev/fetch2/downloader/ParallelFileDownloaderImpl;
        //  2057: getfield        com/tonyodev/fetch2/downloader/ParallelFileDownloaderImpl.B:Lqd2/i;
        //  2060: ldc_w           "FileDownloader"
        //  2063: aload           15
        //  2065: invokeinterface qd2/i.b:(Ljava/lang/String;Ljava/lang/Exception;)V
        //  2070: aload           18
        //  2072: ifnull          2102
        //  2075: aload           18
        //  2077: invokevirtual   java/io/RandomAccessFile.close:()V
        //  2080: goto            2102
        //  2083: astore          15
        //  2085: aload_0        
        //  2086: getfield        kd2/d.f:Lcom/tonyodev/fetch2/downloader/ParallelFileDownloaderImpl;
        //  2089: getfield        com/tonyodev/fetch2/downloader/ParallelFileDownloaderImpl.B:Lqd2/i;
        //  2092: ldc_w           "FileDownloader"
        //  2095: aload           15
        //  2097: invokeinterface qd2/i.b:(Ljava/lang/String;Ljava/lang/Exception;)V
        //  2102: aload_0        
        //  2103: getfield        kd2/d.f:Lcom/tonyodev/fetch2/downloader/ParallelFileDownloaderImpl;
        //  2106: invokestatic    com/tonyodev/fetch2/downloader/ParallelFileDownloaderImpl.a:(Lcom/tonyodev/fetch2/downloader/ParallelFileDownloaderImpl;)V
        //  2109: aload           14
        //  2111: athrow         
        //  2112: astore          14
        //  2114: goto            93
        //    Exceptions:
        //  Try           Handler
        //  Start  End    Start  End    Type                 
        //  -----  -----  -----  -----  ---------------------
        //  0      93     2112   2117   Ljava/lang/Exception;
        //  218    263    1820   1825   Ljava/lang/Exception;
        //  218    263    1812   1820   Any
        //  275    281    1803   1812   Ljava/lang/Exception;
        //  275    281    2023   2029   Any
        //  293    312    1803   1812   Ljava/lang/Exception;
        //  293    312    2023   2029   Any
        //  328    338    1803   1812   Ljava/lang/Exception;
        //  328    338    2023   2029   Any
        //  350    360    1803   1812   Ljava/lang/Exception;
        //  350    360    2023   2029   Any
        //  377    386    1803   1812   Ljava/lang/Exception;
        //  377    386    2023   2029   Any
        //  398    403    1803   1812   Ljava/lang/Exception;
        //  398    403    2023   2029   Any
        //  415    420    1803   1812   Ljava/lang/Exception;
        //  415    420    2023   2029   Any
        //  432    446    1803   1812   Ljava/lang/Exception;
        //  432    446    2023   2029   Any
        //  458    465    1803   1812   Ljava/lang/Exception;
        //  458    465    2023   2029   Any
        //  477    484    1803   1812   Ljava/lang/Exception;
        //  477    484    2023   2029   Any
        //  501    513    1803   1812   Ljava/lang/Exception;
        //  501    513    2023   2029   Any
        //  530    536    1803   1812   Ljava/lang/Exception;
        //  530    536    2023   2029   Any
        //  548    555    1803   1812   Ljava/lang/Exception;
        //  548    555    2023   2029   Any
        //  580    596    1413   1422   Ljava/lang/Exception;
        //  580    596    1404   1413   Any
        //  604    609    1413   1422   Ljava/lang/Exception;
        //  604    609    1404   1413   Any
        //  617    622    1413   1422   Ljava/lang/Exception;
        //  617    622    1404   1413   Any
        //  630    635    1413   1422   Ljava/lang/Exception;
        //  630    635    1404   1413   Any
        //  643    648    1413   1422   Ljava/lang/Exception;
        //  643    648    1404   1413   Any
        //  656    661    1413   1422   Ljava/lang/Exception;
        //  656    661    1404   1413   Any
        //  677    687    1413   1422   Ljava/lang/Exception;
        //  677    687    1404   1413   Any
        //  707    717    1413   1422   Ljava/lang/Exception;
        //  707    717    1404   1413   Any
        //  725    735    1413   1422   Ljava/lang/Exception;
        //  725    735    1404   1413   Any
        //  743    753    1413   1422   Ljava/lang/Exception;
        //  743    753    1404   1413   Any
        //  783    789    1413   1422   Ljava/lang/Exception;
        //  783    789    1404   1413   Any
        //  797    803    1413   1422   Ljava/lang/Exception;
        //  797    803    1404   1413   Any
        //  811    818    1413   1422   Ljava/lang/Exception;
        //  811    818    1404   1413   Any
        //  818    843    1392   1397   Ljava/lang/Exception;
        //  818    843    1375   1392   Any
        //  843    872    1339   1345   Any
        //  877    887    1339   1345   Any
        //  887    896    1339   1345   Any
        //  901    913    1339   1345   Any
        //  913    952    1339   1345   Any
        //  956    1013   1330   1339   Any
        //  1016   1028   1330   1339   Any
        //  1032   1094   1330   1339   Any
        //  1099   1120   1330   1339   Any
        //  1120   1125   1330   1339   Any
        //  1132   1137   1330   1339   Any
        //  1137   1158   1325   1330   Ljava/lang/Exception;
        //  1137   1158   1312   1325   Any
        //  1183   1190   1803   1812   Ljava/lang/Exception;
        //  1183   1190   2023   2029   Any
        //  1207   1219   1803   1812   Ljava/lang/Exception;
        //  1207   1219   2023   2029   Any
        //  1236   1246   1803   1812   Ljava/lang/Exception;
        //  1236   1246   2023   2029   Any
        //  1258   1264   1803   1812   Ljava/lang/Exception;
        //  1258   1264   2023   2029   Any
        //  1276   1292   1803   1812   Ljava/lang/Exception;
        //  1276   1292   2023   2029   Any
        //  1357   1360   1803   1812   Ljava/lang/Exception;
        //  1357   1360   2023   2029   Any
        //  1372   1375   1803   1812   Ljava/lang/Exception;
        //  1372   1375   2023   2029   Any
        //  1439   1449   1803   1812   Ljava/lang/Exception;
        //  1439   1449   2023   2029   Any
        //  1461   1471   1803   1812   Ljava/lang/Exception;
        //  1461   1471   2023   2029   Any
        //  1486   1491   1803   1812   Ljava/lang/Exception;
        //  1486   1491   2023   2029   Any
        //  1503   1510   1803   1812   Ljava/lang/Exception;
        //  1503   1510   2023   2029   Any
        //  1522   1525   1803   1812   Ljava/lang/Exception;
        //  1522   1525   2023   2029   Any
        //  1542   1550   1803   1812   Ljava/lang/Exception;
        //  1542   1550   2023   2029   Any
        //  1562   1572   1803   1812   Ljava/lang/Exception;
        //  1562   1572   2023   2029   Any
        //  1584   1594   1803   1812   Ljava/lang/Exception;
        //  1584   1594   2023   2029   Any
        //  1609   1614   1803   1812   Ljava/lang/Exception;
        //  1609   1614   2023   2029   Any
        //  1626   1633   1803   1812   Ljava/lang/Exception;
        //  1626   1633   2023   2029   Any
        //  1645   1648   1803   1812   Ljava/lang/Exception;
        //  1645   1648   2023   2029   Any
        //  1664   1674   1803   1812   Ljava/lang/Exception;
        //  1664   1674   2023   2029   Any
        //  1686   1696   1803   1812   Ljava/lang/Exception;
        //  1686   1696   2023   2029   Any
        //  1715   1720   1803   1812   Ljava/lang/Exception;
        //  1715   1720   2023   2029   Any
        //  1732   1739   1803   1812   Ljava/lang/Exception;
        //  1732   1739   2023   2029   Any
        //  1751   1754   1803   1812   Ljava/lang/Exception;
        //  1751   1754   2023   2029   Any
        //  1759   1773   1776   1795   Ljava/lang/Exception;
        //  1795   1800   1996   2015   Ljava/lang/Exception;
        //  1833   1842   2023   2029   Any
        //  1850   1855   2023   2029   Any
        //  1863   1868   2023   2029   Any
        //  1876   1885   2023   2029   Any
        //  1893   1903   2023   2029   Any
        //  1911   1925   2023   2029   Any
        //  1933   1942   2023   2029   Any
        //  1947   1961   1964   1983   Ljava/lang/Exception;
        //  1988   1993   1996   2015   Ljava/lang/Exception;
        //  2034   2048   2051   2070   Ljava/lang/Exception;
        //  2075   2080   2083   2102   Ljava/lang/Exception;
        // 
        // The error that occurred was:
        // 
        // java.lang.IllegalStateException: Expression is linked from several locations: Label_0516:
        //     at com.strobel.decompiler.ast.Error.expressionLinkedFromMultipleLocations(Error.java:27)
        //     at com.strobel.decompiler.ast.AstOptimizer.mergeDisparateObjectInitializations(AstOptimizer.java:2604)
        //     at com.strobel.decompiler.ast.AstOptimizer.optimize(AstOptimizer.java:235)
        //     at com.strobel.decompiler.ast.AstOptimizer.optimize(AstOptimizer.java:42)
        //     at com.strobel.decompiler.languages.java.ast.AstMethodBodyBuilder.createMethodBody(AstMethodBodyBuilder.java:206)
        //     at com.strobel.decompiler.languages.java.ast.AstMethodBodyBuilder.createMethodBody(AstMethodBodyBuilder.java:93)
        //     at com.strobel.decompiler.languages.java.ast.AstBuilder.createMethodBody(AstBuilder.java:868)
        //     at com.strobel.decompiler.languages.java.ast.AstBuilder.createMethod(AstBuilder.java:761)
        //     at com.strobel.decompiler.languages.java.ast.AstBuilder.addTypeMembers(AstBuilder.java:638)
        //     at com.strobel.decompiler.languages.java.ast.AstBuilder.createTypeCore(AstBuilder.java:605)
        //     at com.strobel.decompiler.languages.java.ast.AstBuilder.createTypeNoCache(AstBuilder.java:195)
        //     at com.strobel.decompiler.languages.java.ast.AstBuilder.createType(AstBuilder.java:162)
        //     at com.strobel.decompiler.languages.java.ast.AstBuilder.addType(AstBuilder.java:137)
        //     at com.strobel.decompiler.languages.java.JavaLanguage.buildAst(JavaLanguage.java:71)
        //     at com.strobel.decompiler.languages.java.JavaLanguage.decompileType(JavaLanguage.java:59)
        //     at com.strobel.decompiler.DecompilerDriver.decompileType(DecompilerDriver.java:333)
        //     at com.strobel.decompiler.DecompilerDriver.decompileJar(DecompilerDriver.java:254)
        //     at com.strobel.decompiler.DecompilerDriver.main(DecompilerDriver.java:129)
        // 
        throw new IllegalStateException("An error occurred while decompiling this method.");
    }
}
